Workbook
Name _._IMPUESTOS_SOBRE_COMBUSTIBLES_Y_GAS_NATURAL: #REF!
Name _._IMPUESTOS_SOBRE_ENERGIA_ELECTRICA: #REF!
Name AJESTA: #REF!
Name ALFA: #REF!
Name CEMENTO: #REF!
Name CICESP: #REF!
Name COMB: #REF!
Name CONSTRUC: #REF!
Name COPA: #N/A
Name COPARTICIPACION_FEDERAL__LEY_N__23548: #REF!
Name DIFTA: #REF!
Name EEI: #REF!
Name EMPLEO: #REF!
Name EPH: #REF!
Name EPH_POB: #REF!
Name EXCEDENTE_DEL_10__SEGUN_EL_TOPE_ASIGNADO_A__BUENOS_AIRES__LEY_N__23621: #REF!
Name FAE_BOVINOS: #REF!
Name FONDO_COMPENSADOR_DE_DESEQUILIBRIOS_FISCALES_PROVINCIALES: #REF!
Name FONDO_EDUCATIVO__LEY_N__23906_ART._3_Y_4: #REF!
Name FONDO_ESPECIAL_DE_DESARROLLO_ELECTRICO_DEL_INTERIOR__LEYES_NROS._23966_ART._19_Y_24065: #REF!
Name FONDO_NACIONAL_DE_LA_VIVIENDA__LEY_N__23966_ART._18: #REF!
Name GAS: #REF!
Name ICC_FM: #REF!
Name IDL_UTDT: #REF!
Name IND_ACEITERA: #REF!
Name IPC_GBA: #REF!
Name IPC_NAC: #REF!
Name IPC_SFE: #REF!
Name IPM: #REF!
Name IPMPE: #REF!
Name IRR: #REF!
Name L_: #N/A
Name LACTEA: #REF!
Name MAQ_AGR: #REF!
Name NA: #REF!
Name O: #N/A
Name OBRAS_DE_INFRAESTRUCTURA__LEY_N__23966_ART._19: #REF!
Name OBRAS_DE_INFRAESTRUCTURA_BASICA_SOCIAL_Y_NECESIDADES_BASICAS_INSATISFECHAS__LEY_N__23621: #REF!
Name ORGANISMOS_DE_VIALIDAD__LEY_N__23966_ART._19: #REF!
Name PATENTES: #REF!
Name PBG: #REF!
Name PGCLAS: #REF!
Name PGCREC: #REF!
Name REC: #REF!
Name sct: #REF!
Name SEGURIDAD_SOCIAL___BS._PERS._NO_INCORP._AL_PROCESO_ECONOMICO__LEY_N__23966__ART._30: #REF!
Name SEGURIDAD_SOCIAL___IVA__LEY_N__23966_ART._5_PTO._2: #REF!
Name SUMA_FIJA_FINANCIADA_CON__LA_COPARTICIPACION_FEDERAL_DE_NACION__LEY_N__23621_ART._1: #REF!
Name TOTAL: #REF!
Name TRANSFERENCIA_DE_SERVICIOS__LEY_N__24049_Y_COMPLEMENTARIAS: #REF!
Name Trigo: #REF!
Name VARCRI: #REF!
Name VARTA: #REF!
Name VENTAS: #REF!
Name XCER: #REF!

Sheet INDICE
E2: Centro de Estudios y Servicios - Bolsa de Comercio de Santa Fe -
E3: San Martín 2231 - CP 3000 - Santa Fe - Argentina
E4: Teléfono: (0342) 4845800
E5: Email: ces@bcsf.com.ar
E6: Website: https://bcsf.com.ar/ces/ o bien http://www.bcsf.com.ar
C8: BASE DE DATOS ESTADÍSTICOS DE LAS 24 JURISDICCIONES (PROVINCIAS Y CABA)
C10: Última actualización: 29/6/2026 | F10: < Próxima fecha de publicación: mayo 2027 >
C11: Aclaración general: los datos subrayados implican estimaciones propias y los datos en azul la existencia de una fórmula. Los datos en amarillo oscuro indican información provisoria.
C13: Recursos | F13: Frecuencia | G13: Nº de series | H13: Fecha de inicio
C14: 1.1. Recursos totales por provincia | F14: Anual | G14: =COLUMNS('1.1'!B:Z) -> 25 | H14: 1992
C15: 1.1.1. Recursos corrientes por provincia | F15: Anual | G15: =COLUMNS('1.1.1'!B:Z) -> 25 | H15: 1992
B16: Ir a | C16: 1.1.1.1. Recursos tributarios de origen provincial por provincia | F16: Anual | G16: =COLUMNS('1.1.1.1'!B:Z) -> 25 | H16: 1992
C17: 1.1.1.1.1 Ingresos brutos | F17: Anual | G17: =COLUMNS('1.1.1.1.1'!B:Z) -> 25 | H17: 1992
C18: 1.1.1.1.2 Inmobiliario | F18: Anual | G18: =COLUMNS('1.1.1.1.2'!B:Z) -> 25 | H18: 1992
C19: 1.1.1.1.3 Sellos | F19: Anual | G19: =COLUMNS('1.1.1.1.3'!B:Z) -> 25 | H19: 1992
C20: 1.1.1.1.4 Automotores | F20: Anual | G20: =COLUMNS('1.1.1.1.4'!B:Z) -> 25 | H20: 1992
C21: 1.1.1.1.5 Otros impuestos provinciales | F21: Anual | G21: =COLUMNS('1.1.1.1.5'!B:Z) -> 25 | H21: 1992
C22: 1.1.1.2. Recursos de origen nacional (coparticipación) por provincia | F22: Anual | G22: =COLUMNS('1.1.1.2'!B:Z) -> 25 | H22: 1992
C23: 1.1.1.3. Recursos no tributarios por provincia | F23: Anual | G23: =COLUMNS('1.1.1.3'!B:Z) -> 25 | H23: 1992
C24: 1.1.1.3.1. Regalías por provincia | F24: Anual | G24: =COLUMNS('1.1.1.3.1'!B:Z) -> 25 | H24: 1992
C25: 1.1.1.4. Venta de bienes y servicios de la Administración pública por provincia | F25: Anual | G25: =COLUMNS('1.1.1.4'!B:Z) -> 25 | H25: 1996
C26: 1.1.1.5. Rentas de la propiedad por provincia | F26: Anual | G26: =COLUMNS('1.1.1.5'!B:Z) -> 25 | H26: 1996
C27: 1.1.1.6. Transferencias corrientes por provincia | F27: Anual | G27: =COLUMNS('1.1.1.6'!B:Z) -> 25 | H27: 1992
C28: 1.1.2. Recursos de capital por provincia | F28: Anual | G28: =COLUMNS('1.1.2'!B:Z) -> 25 | H28: 1992
C29: 1.2. Recaudación de Impuestos Nacionales por provincia | F29: Anual | G29: =COLUMNS('1.2'!B:Z) -> 25 | H29: 2001
C30: 1.2.1. Recaudación del Impuesto al Valor Agregado (IVA) por provincia | F30: Anual | G30: =COLUMNS('1.2.1'!B:AA) -> 26 | H30: 2001
C31: 1.2.2. Recaudación del Impuesto a las Ganancias por provincia | F31: Anual | G31: =COLUMNS('1.2.2'!B:AA) -> 26 | H31: 2001
C32: 1.2.3. Recaudación del Impuesto a los Bienes Personales por provincia | F32: Anual | G32: =COLUMNS('1.2.3'!B:AA) -> 26 | H32: 2001
C33: 1.2.4. Recaudación del Impuesto a las Cuentas Corrientes por provincia | F33: Anual | G33: =COLUMNS('1.2.4'!B:AA) -> 26 | H33: 2001
C34: 1.2.4.1. Porción no coparticipable del Impuesto al Cheque por provincia | F34: Anual | G34: =COLUMNS('1.2.4.1'!B:AA) -> 26 | H34: 2001
C35: 1.2.5. Recaudación de las Ganancias mínimas presuntas por provincia | F35: Anual | G35: =COLUMNS('1.2.5'!B:AA) -> 26 | H35: 2001
C36: 1.2.6. Recaudación de los Impuestos Internos por provincia | F36: Anual | G36: =COLUMNS('1.2.6'!B:AA) -> 26 | H36: 2001
C37: 1.2.7. Recaudación del Monotributo por provincia | F37: Anual | G37: =COLUMNS('1.2.7'!B:AA) -> 26 | H37: 2001
C38: 1.2.8. Recaudación de otros impuestos por provincia | F38: Anual | G38: =COLUMNS('1.2.8'!B:AA) -> 26 | H38: 2001
C39: 1.2.9. Recaudación de Impuestos Aduaneros por provincia | F39: Anual | G39: =COLUMNS('1.2.9'!B:AA) -> 26 | H39: 2001
C40: Gastos | F40: Frecuencia | G40: Nº de series | H40: Fecha de inicio
C41: 2. Gasto público total por provincia | F41: Anual | G41: =COLUMNS('2'!B:Z) -> 25 | H41: 1992
C42: 2.1. Gastos corrientes por provincia | F42: Anual | G42: =COLUMNS('2.1'!B:Z) -> 25 | H42: 1992
C43: 2.1.1. Gasto de consumo | F43: Anual | G43: =COLUMNS('2.1.1'!B:Z) -> 25 | H43: 1992
C44: 2.1.1.1 Gasto público en personal por provincia | F44: Anual | G44: =COLUMNS('2.1.1.1'!B:Z) -> 25 | H44: 1992
C45: 2.1.1.1.1 Planta ocupada | F45: Anual | G45: =COLUMNS('2.1.1.1.1'!B:Z) -> 25 | H45: 1992
C46: 2.1.1.1.2 Empleados cada mil habitantes | F46: Anual | G46: =COLUMNS('2.1.1.1.2'!B:Z) -> 25 | H46: 1992
C47: 2.1.1.1.3 Gasto medio salarial | F47: Anual | G47: =COLUMNS('2.1.1.1.3'!B:Z) -> 25 | H47: 1992
C48: 2.1.2. Rentas de la propiedad por provincia | F48: Anual | G48: =COLUMNS('2.1.2'!B:Z) -> 25 | H48: 1992
C49: 2.1.3. Transferencias corrientes por provincia | F49: Anual | G49: =COLUMNS('2.1.3'!B:Z) -> 25 | H49: 1992
C50: 2.2. Gastos de capital por provincia | F50: Anual | G50: =COLUMNS('2.2'!B:Z) -> 25 | H50: 1992
C51: 2.2.1. Inversión real directa por provincia | F51: Anual | G51: =COLUMNS('2.2.1'!B:Z) -> 25 | H51: 1992
C52: 2.2.2. Transferencias de capital por provincia | F52: Anual | G52: =COLUMNS('2.2.2'!B:Z) -> 25 | H52: 1992
C53: 2.2.3. Inversión financiera por provincia | F53: Anual | G53: =COLUMNS('2.2.3'!B:Z) -> 25 | H53: 1992
C54: Resultados | F54: Frecuencia | G54: Nº de series | H54: Fecha de inicio
C55: 3.1. Resultado económico por provincia (1.1.1 - 2.1) | F55: Anual | G55: =COLUMNS('3.1'!B:Z) -> 25 | H55: 1992
C56: 3.2. Resultado financiero por provincia (1.1 - 2) | F56: Anual | G56: =COLUMNS('3.2'!B:Z) -> 25 | H56: 1992
C57: 3.3. Resultado primario por provincia (3.2 + 2.1.2) | F57: Anual | G57: =COLUMNS('3.3'!B:Z) -> 25 | H57: 1992
C58: Deuda | F58: Frecuencia | G58: Nº de series | H58: Fecha de inicio
C59: 4. Deuda pública por provincia | F59: Anual | G59: =COLUMNS('4'!B:Z) -> 25 | H59: 1996
C60: 4.1. Deuda pública con el Gobierno Nacional por provincia | F60: Anual | G60: =COLUMNS('4.1'!B:Z) -> 25 | H60: 1996
C61: 4.2. Fondo Fiduciario de Infraestructura Regional por provincia | F61: Anual | G61: =COLUMNS('4.2'!B:Z) -> 25 | H61: 2000
C62: 4.3. Fondo Fiduciario de Desarrollo Provincial por provincia | F62: Anual | G62: =COLUMNS('4.3'!B:Z) -> 25 | H62: 2000
C63: 4.4. Deuda pública con entidades bancarias y financieras por provincia | F63: Anual | G63: =COLUMNS('4.4'!B:Z) -> 25 | H63: 1996
C64: 4.5. Deuda pública consolidada por provincia | F64: Anual | G64: =COLUMNS('4.5'!B:Z) -> 25 | H64: 1996
C65: 4.6. Títulos públicos (bonos) por provincia | F65: Anual | G65: =COLUMNS('4.6'!B:Z) -> 25 | H65: 1996
C66: 4.7. Deuda pública con Organismos Internacionales por provincia | F66: Anual | G66: =COLUMNS('4.7'!B:Z) -> 25 | H66: 1996
C67: 4.8. Otros conceptos de deuda pública por provincia | F67: Anual | G67: =COLUMNS('4.8'!B:Z) -> 25 | H67: 1996
C68: Fondo Federal Solidario | F68: Frecuencia | G68: Nº de series | H68: Fecha de inicio
C69: 5. Fondo Federal Solidario | F69: Anual | G69: =COLUMNS('5'!B:Z) -> 25 | H69: 2009
C70: Gasto por Finalidad y Función | F70: Frecuencia | G70: Nº de series | H70: Fecha de inicio
C71: 6.1. Administración gubernamental | F71: Anual | G71: =COLUMNS('6.1'!B:Z) -> 25 | H71: 1992
C72: 6.2. Servicios de seguridad | F72: Anual | G72: =COLUMNS('6.2'!B:Z) -> 25 | H72: 1992
C73: 6.3. Servicios sociales | F73: Anual | G73: =COLUMNS('6.3'!B:Z) -> 25 | H73: 1992
C74: 6.3.1. Salud | F74: Anual | G74: =COLUMNS('6.3.1'!B:Z) -> 25 | H74: 1992
C75: 6.3.2. Promoción y asistencia social | F75: Anual | G75: =COLUMNS('6.3.2'!B:Z) -> 25 | H75: 1992
C76: 6.3.3. Seguridad Social | F76: Anual | G76: =COLUMNS('6.3.3'!B:Z) -> 25 | H76: 1992
C77: 6.3.4. Educación y cultura | F77: Anual | G77: =COLUMNS('6.3.4'!B:Z) -> 25 | H77: 1992
C78: 6.3.5. Ciencia y técnica | F78: Anual | G78: =COLUMNS('6.3.5'!B:Z) -> 25 | H78: 1992
C79: 6.3.6. Trabajo | F79: Anual | G79: =COLUMNS('6.3.6'!B:Z) -> 25 | H79: 1995
C80: 6.3.7. Vivienda y urbanismo | F80: Anual | G80: =COLUMNS('6.3.7'!B:Z) -> 25 | H80: 1992
C81: 6.3.8. Agua potable y alcantarillado | F81: Anual | G81: =COLUMNS('6.3.8'!B:Z) -> 25 | H81: 1992
C82: 6.3.9. Otros servicios urbanos | F82: Anual | G82: =COLUMNS('6.3.9'!B:Z) -> 25 | H82: 1992
C83: 6.4. Servicios económicos | F83: Anual | G83: =COLUMNS('6.4'!B:Z) -> 25 | H83: 1992
C84: 6.5. Deuda pública | F84: Anual | G84: =COLUMNS('6.5'!B:Z) -> 25 | H84: 1992
C85: Total de series | G85: =SUM(G14:G39,G41:G53,G55:G57,G59:G67,G69,G71:G84) -> 1660

Sheet Deflactores
A3: Título | B3: Precios minoristas al consumidor. Deflactor.
A4: Fuentes | B4: INDEC - UBA - IPEC - Congreso - IDECBA
A6: Empalmes | B6: IPC Nacional - BA City - IPC Santa Fe - Congreso - IPC Nacional
A8: Unidad de medida | B8: Indice base 2016=100
B9: Media geométrica anual
A10: 1992 | B10: 5.2104099
A11: 1993 | B11: 5.6288937
A12: 1994 | B12: 5.7685507
A13: 1995 | B13: 6.0736247
A14: 1996 | B14: 6.121665
A15: 1997 | B15: 5.9241227
A16: 1998 | B16: 5.705479
A17: 1999 | B17: 5.4667572
A18: 2000 | B18: 5.2520619
A19: 2001 | B19: 5.1211084
A20: 2002 | B20: 7.4273682
A21: 2003 | B21: 8.972316
... A44: 2026 | B44: 12345.954
A45: 2027 | B45: #N/A
A46: 2028 | B46: #N/A
A47: 2029 | B47: #N/A
A48: 2030 | B48: #N/A

Sheet 1.1
A2: Título | B2: Recursos totales por provincia | N2: =B2 -> Recursos totales por provincia
A3: Fuente | B3: Dirección Nacional de Asuntos Provinciales - Ministerio de Economía de la Nación | N3: =B3 -> Dirección Nacional de Asuntos Provinciales - Ministerio de Economía de la Nación
A5: VOLVER AL ÍNDICE | B5: Administración Pública No Financiera | N5: =B5 -> Administración Pública No Financiera
A7: Unidad de medida | B7: Millones de pesos constantes de 2016 | C7: Millones de pesos constantes de 2016 | D7: Millones de pesos constantes de 2016 | E7: Millones de pesos constantes de 2016 | F7: Millones de pesos constantes de 2016 | G7: Millones de pesos constantes de 2016 | H7: Millones de pesos constantes de 2016 | I7: Millones de pesos constantes de 2016 | J7: Millones de pesos constantes de 2016 | K7: Millones de pesos constantes de 2016 | L7: Millones de pesos constantes de 2016 | M7: Millones de pesos constantes de 2016 | N7: Millones de pesos constantes de 2016 | O7: Millones de pesos constantes de 2016 | P7: Millones de pesos constantes de 2016 | Q7: Millones de pesos constantes de 2016 | R7: Millones de pesos constantes de 2016 | S7: Millones de pesos constantes de 2016 | T7: Millones de pesos constantes de 2016 | U7: Millones de pesos constantes de 2016 | V7: Millones de pesos constantes de 2016 | W7: Millones de pesos constantes de 2016 | X7: Millones de pesos constantes de 2016 | Y7: Millones de pesos constantes de 2016 | Z7: Millones de pesos constantes de 2016
A8: CÓDIGO | B8: 1.1.1 | C8: 1.1.2 | D8: 1.1.3 | E8: 1.1.4 | F8: 1.1.5 | G8: 1.1.6 | H8: 1.1.7 | I8: 1.1.8 | J8: 1.1.9 | K8: 1.1.10 | L8: 1.1.11 | M8: 1.1.12 | N8: 1.1.13 | O8: 1.1.14 | P8: 1.1.15 | Q8: 1.1.16 | R8: 1.1.17 | S8: 1.1.18 | T8: 1.1.19 | U8: 1.1.20 | V8: 1.1.21 | W8: 1.1.22 | X8: 1.1.23 | Y8: 1.1.24 | Z8: 1.1.25
A9: Jurisdicción | B9: C.A.B.A. | C9: Buenos Aires | D9: Catamarca | E9: Córdoba | F9: Corrientes | G9: Chaco | H9: Chubut | I9: Entre Ríos | J9: Formosa | K9: Jujuy | L9: La Pampa | M9: La Rioja | N9: Mendoza | O9: Misiones | P9: Neuquén | Q9: Río Negro | R9: Salta | S9: San Juan | T9: San Luis | U9: Santa Cruz | V9: Santa Fe | W9: Santiago del Estero | X9: Tucumán | Y9: Tierra del Fuego | Z9: Total
A10: 1992 | B10: =+'[1]1.1'!B10/Deflactores!$B10*100 -> 49533.76 | C10: =+'[1]1.1'!C10/Deflactores!$B10*100 -> 108900.62 | D10: =+'[1]1.1'!D10/Deflactores!$B10*100 -> 7317.3868 | E10: =+'[1]1.1'!E10/Deflactores!$B10*100 -> 35578.963 | F10: =+'[1]1.1'!F10/Deflactores!$B10*100 -> 10534.012 | G10: =+'[1]1.1'!G10/Deflactores!$B10*100 -> 12972.108 | H10: =+'[1]1.1'!H10/Deflactores!$B10*100 -> 7941.7935 | I10: =+'[1]1.1'!I10/Deflactores!$B10*100 -> 15930.065 | ... Y10: =+'[1]1.1'!Y10/Deflactores!$B10*100 -> 4552.5522 | Z10: =SUM(B10:Y10) -> 429906.96
A11: 1993 | B11: =+'[1]1.1'!B11/Deflactores!$B11*100 -> 47815.322 | C11: =+'[1]1.1'!C11/Deflactores!$B11*100 -> 124752.93 | D11: =+'[1]1.1'!D11/Deflactores!$B11*100 -> 6561.7605 | E11: =+'[1]1.1'!E11/Deflactores!$B11*100 -> 34585.191 | F11: =+'[1]1.1'!F11/Deflactores!$B11*100 -> 10546.072 | G11: =+'[1]1.1'!G11/Deflactores!$B11*100 -> 11947.266 | H11: =+'[1]1.1'!H11/Deflactores!$B11*100 -> 7174.6776 | I11: =+'[1]1.1'!I11/Deflactores!$B11*100 -> 15590.782 | ... Y11: =+'[1]1.1'!Y11/Deflactores!$B11*100 -> 5021.6576 | Z11: =SUM(B11:Y11) -> 453144.58
A12: 1994 | B12: =+'[1]1.1'!B12/Deflactores!$B12*100 -> 47857.118 | C12: =+'[1]1.1'!C12/Deflactores!$B12*100 -> 134248.46 | D12: =+'[1]1.1'!D12/Deflactores!$B12*100 -> 6748.6535 | E12: =+'[1]1.1'!E12/Deflactores!$B12*100 -> 37148.948 | F12: =+'[1]1.1'!F12/Deflactores!$B12*100 -> 10349.902 | G12: =+'[1]1.1'!G12/Deflactores!$B12*100 -> 12218.679 | H12: =+'[1]1.1'!H12/Deflactores!$B12*100 -> 7443.124 | I12: =+'[1]1.1'!I12/Deflactores!$B12*100 -> 17242.033 | ... Y12: =+'[1]1.1'!Y12/Deflactores!$B12*100 -> 5720.6479 | Z12: =SUM(B12:Y12) -> 474478.7
A13: 1995 | B13: =+'[1]1.1'!B13/Deflactores!$B13*100 -> 44100.353 | C13: =+'[1]1.1'!C13/Deflactores!$B13*100 -> 126065.66 | D13: =+'[1]1.1'!D13/Deflactores!$B13*100 -> 6276.6211 | E13: =+'[1]1.1'!E13/Deflactores!$B13*100 -> 33206.098 | F13: =+'[1]1.1'!F13/Deflactores!$B13*100 -> 9669.3592 | G13: =+'[1]1.1'!G13/Deflactores!$B13*100 -> 11612.631 | H13: =+'[1]1.1'!H13/Deflactores!$B13*100 -> 7913.131 | I13: =+'[1]1.1'!I13/Deflactores!$B13*100 -> 15810.644 | ... Y13: =+'[1]1.1'!Y13/Deflactores!$B13*100 -> 5060.7236 | Z13: =SUM(B13:Y13) -> 439509.51
A14: 1996 | B14: =+'[1]1.1'!B14/Deflactores!$B14*100 -> 44704.347 | C14: =+'[1]1.1'!C14/Deflactores!$B14*100 -> 132894.53 | D14: =+'[1]1.1'!D14/Deflactores!$B14*100 -> 6609.2752 | E14: =+'[1]1.1'!E14/Deflactores!$B14*100 -> 36657.594 | F14: =+'[1]1.1'!F14/Deflactores!$B14*100 -> 10216.165 | G14: =+'[1]1.1'!G14/Deflactores!$B14*100 -> 12627.356 | H14: =+'[1]1.1'!H14/Deflactores!$B14*100 -> 8022.7395 | I14: =+'[1]1.1'!I14/Deflactores!$B14*100 -> 19782.281 | ... Y14: =+'[1]1.1'!Y14/Deflactores!$B14*100 -> 5264.8489 | Z14: =SUM(B14:Y14) -> 475048.7
A15: 1997 | B15: =+'[1]1.1'!B15/Deflactores!$B15*100 -> 48870.654 | C15: =+'[1]1.1'!C15/Deflactores!$B15*100 -> 173553.99 | D15: =+'[1]1.1'!D15/Deflactores!$B15*100 -> 8566.3244 | E15: =+'[1]1.1'!E15/Deflactores!$B15*100 -> 40783.694 | F15: =+'[1]1.1'!F15/Deflactores!$B15*100 -> 12383.846 | G15: =+'[1]1.1'!G15/Deflactores!$B15*100 -> 14869.676 | H15: =+'[1]1.1'!H15/Deflactores!$B15*100 -> 8738.5506 | I15: =+'[1]1.1'!I15/Deflactores!$B15*100 -> 19729.035 | ... Y15: =+'[1]1.1'!Y15/Deflactores!$B15*100 -> 5993.5222 | Z15: =SUM(B15:Y15) -> 550583.7
A16: 1998 | B16: =+'[1]1.1'!B16/Deflactores!$B16*100 -> 56362.653 | C16: =+'[1]1.1'!C16/Deflactores!$B16*100 -> 164334.7 | D16: =+'[1]1.1'!D16/Deflactores!$B16*100 -> 9049.7995 | E16: =+'[1]1.1'!E16/Deflactores!$B16*100 -> 44042.636 | F16: =+'[1]1.1'!F16/Deflactores!$B16*100 -> 12878.81 | G16: =+'[1]1.1'!G16/Deflactores!$B16*100 -> 16729.25 | H16: =+'[1]1.1'!H16/Deflactores!$B16*100 -> 8943.1066 | I16: =+'[1]1.1'!I16/Deflactores!$B16*100 -> 21009.681 | ... Y16: =+'[1]1.1'!Y16/Deflactores!$B16*100 -> 6301.9858 | Z16: =SUM(B16:Y16) -> 580330.28
A17: 1999 | B17: =+'[1]1.1'!B17/Deflactores!$B17*100 -> 58308.079 | C17: =+'[1]1.1'!C17/Deflactores!$B17*100 -> 171713.86 | D17: =+'[1]1.1'!D17/Deflactores!$B17*100 -> 9253.6812 | E17: =+'[1]1.1'!E17/Deflactores!$B17*100 -> 43247.449 | F17: =+'[1]1.1'!F17/Deflactores!$B17*100 -> 13506.874 | G17: =+'[1]1.1'!G17/Deflactores!$B17*100 -> 16573.692 | H17: =+'[1]1.1'!H17/Deflactores!$B17*100 -> 9321.8282 | I17: =+'[1]1.1'!I17/Deflactores!$B17*100 -> 21353.703 | ... Y17: =+'[1]1.1'!Y17/Deflactores!$B17*100 -> 6659.4956 | Z17: =SUM(B17:Y17) -> 590363.74
A18: 2000 | B18: =+'[1]1.1'!B18/Deflactores!$B18*100 -> 61747.929 | C18: =+'[1]1.1'!C18/Deflactores!$B18*100 -> 173830.19 | D18: =+'[1]1.1'!D18/Deflactores!$B18*100 -> 9473.3443 | E18: =+'[1]1.1'!E18/Deflactores!$B18*100 -> 45642.615 | F18: =+'[1]1.1'!F18/Deflactores!$B18*100 -> 14155.757 | G18: =+'[1]1.1'!G18/Deflactores!$B18*100 -> 17610.265 | H18: =+'[1]1.1'!H18/Deflactores!$B18*100 -> 11323.1 | I18: =+'[1]1.1'!I18/Deflactores!$B18*100 -> 21274.777 | ... Y18: =+'[1]1.1'!Y18/Deflactores!$B18*100 -> 7913.8243 | Z18: =SUM(B18:Y18) -> 619705.93
A19: 2001 | B19: =+'[1]1.1'!B19/Deflactores!$B19*100 -> 57323.535 | C19: =+'[1]1.1'!C19/Deflactores!$B19*100 -> 154675.83 | D19: =+'[1]1.1'!D19/Deflactores!$B19*100 -> 9772.0085 | E19: =+'[1]1.1'!E19/Deflactores!$B19*100 -> 43067.06 | F19: =+'[1]1.1'!F19/Deflactores!$B19*100 -> 14149.066 | G19: =+'[1]1.1'!G19/Deflactores!$B19*100 -> 17073.245 | H19: =+'[1]1.1'!H19/Deflactores!$B19*100 -> 11081.385 | I19: =+'[1]1.1'!I19/Deflactores!$B19*100 -> 21591.692 | ... Y19: =+'[1]1.1'!Y19/Deflactores!$B19*100 -> 8148.8149 | Z19: =SUM(B19:Y19) -> 586517.33
A20: 2002 | B20: =+'[1]1.1'!B20/Deflactores!$B20*100 -> 38952.1 | C20: =+'[1]1.1'!C20/Deflactores!$B20*100 -> 117828.27 | D20: =+'[1]1.1'!D20/Deflactores!$B20*100 -> 6589.6587 | E20: =+'[1]1.1'!E20/Deflactores!$B20*100 -> 31268.19 | F20: =+'[1]1.1'!F20/Deflactores!$B20*100 -> 8882.0277 | G20: =+'[1]1.1'!G20/Deflactores!$B20*100 -> 12278.732 | H20: =+'[1]1.1'!H20/Deflactores!$B20*100 -> 11514.026 | I20: =+'[1]1.1'!I20/Deflactores!$B20*100 -> 13658.288 | ... Y20: =+'[1]1.1'!Y20/Deflactores!$B20*100 -> 5846.3452 | Z20: =SUM(B20:Y20) -> 436016.46
A21: 2003 | B21: =+'[1]1.1'!B21/Deflactores!$B21*100 -> 44548.383 | C21: =+'[1]1.1'!C21/Deflactores!$B21*100 -> 128496.43 | D21: =+'[1]1.1'!D21/Deflactores!$B21*100 -> 7522.4472 | E21: =+'[1]1.1'!E21/Deflactores!$B21*100 -> 35270.105 | F21: =+'[1]1.1'!F21/Deflactores!$B21*100 -> 9804.7917 | G21: =+'[1]1.1'!G21/Deflactores!$B21*100 -> 13393.365 | H21: =+'[1]1.1'!H21/Deflactores!$B21*100 -> 11974.689 | I21: =+'[1]1.1'!I21/Deflactores!$B21*100 -> 15261.116 | ... Y21: =+'[1]1.1'!Y21/Deflactores!$B21*100 -> 6138.7099 | Z21: =SUM(B21:Y21) -> 475573.58
... A41: 2023 | B41: =+'[1]1.1'!B41/Deflactores!$B41*100 -> 159438.69 | C41: =+'[1]1.1'!C41/Deflactores!$B41*100 -> 422561.47 | D41: =+'[1]1.1'!D41/Deflactores!$B41*100 -> 25125.202 | E41: =+'[1]1.1'!E41/Deflactores!$B41*100 -> 133084.63 | F41: =+'[1]1.1'!F41/Deflactores!$B41*100 -> 35635.024 | G41: =+'[1]1.1'!G41/Deflactores!$B41*100 -> 49320.928 | H41: =+'[1]1.1'!H41/Deflactores!$B41*100 -> 31385.397 | I41: =+'[1]1.1'!I41/Deflactores!$B41*100 -> 56074.272 | ... Y41: =+'[1]1.1'!Y41/Deflactores!$B41*100 -> 17643.706 | Z41: =SUM(B41:Y41) -> 1547711.3
A42: 2024 | B42: =+'[1]1.1'!B42/Deflactores!$B42*100 -> 136724.55 | C42: =+'[1]1.1'!C42/Deflactores!$B42*100 -> 346937.22 | D42: =+'[1]1.1'!D42/Deflactores!$B42*100 -> 19472.677 | E42: =+'[1]1.1'!E42/Deflactores!$B42*100 -> 113915.37 | F42: =+'[1]1.1'!F42/Deflactores!$B42*100 -> 30361.665 | G42: =+'[1]1.1'!G42/Deflactores!$B42*100 -> 39854.436 | H42: =+'[1]1.1'!H42/Deflactores!$B42*100 -> 27401.45 | I42: =+'[1]1.1'!I42/Deflactores!$B42*100 -> 46575.722 | ... Y42: =+'[1]1.1'!Y42/Deflactores!$B42*100 -> 14697.342 | Z42: =_xlfn.AGGREGATE(9,6,B42:Y42) -> 1281921.9
A43: 2025 | B43: =+'[1]1.1'!B43/Deflactores!$B43*100 -> 135318.15 | C43: =+'[1]1.1'!C43/Deflactores!$B43*100 -> 344851.9 | D43: =+'[1]1.1'!D43/Deflactores!$B43*100 -> 19341.284 | E43: =+'[1]1.1'!E43/Deflactores!$B43*100 -> 118489.84 | F43: =+'[1]1.1'!F43/Deflactores!$B43*100 -> 30968.179 | G43: =+'[1]1.1'!G43/Deflactores!$B43*100 -> 41698.106 | H43: =+'[1]1.1'!H43/Deflactores!$B43*100 -> 27407.546 | I43: =+'[1]1.1'!I43/Deflactores!$B43*100 -> 48489.916 | ... Y43: =+'[1]1.1'!Y43/Deflactores!$B43*100 -> 14112.09 | Z43: =SUM(B43:Y43) -> #N/A
A44: 2026 | B44: =+'[1]1.1'!B44/Deflactores!$B44*100 -> #N/A | C44: =+'[1]1.1'!C44/Deflactores!$B44*100 -> #N/A | D44: =+'[1]1.1'!D44/Deflactores!$B44*100 -> #N/A | E44: =+'[1]1.1'!E44/Deflactores!$B44*100 -> #N/A | F44: =+'[1]1.1'!F44/Deflactores!$B44*100 -> #N/A | G44: =+'[1]1.1'!G44/Deflactores!$B44*100 -> #N/A | H44: =+'[1]1.1'!H44/Deflactores!$B44*100 -> #N/A | I44: =+'[1]1.1'!I44/Deflactores!$B44*100 -> #N/A | ... Y44: =+'[1]1.1'!Y44/Deflactores!$B44*100 -> #N/A | Z44: =SUM(B44:Y44) -> #N/A
A45: 2027 | B45: =+'[1]1.1'!B45/Deflactores!$B45*100 -> #N/A | C45: =+'[1]1.1'!C45/Deflactores!$B45*100 -> #N/A | D45: =+'[1]1.1'!D45/Deflactores!$B45*100 -> #N/A | E45: =+'[1]1.1'!E45/Deflactores!$B45*100 -> #N/A | F45: =+'[1]1.1'!F45/Deflactores!$B45*100 -> #N/A | G45: =+'[1]1.1'!G45/Deflactores!$B45*100 -> #N/A | H45: =+'[1]1.1'!H45/Deflactores!$B45*100 -> #N/A | I45: =+'[1]1.1'!I45/Deflactores!$B45*100 -> #N/A | ... Y45: =+'[1]1.1'!Y45/Deflactores!$B45*100 -> #N/A | Z45: =SUM(B45:Y45) -> #N/A
A46: 2028 | B46: =+'[1]1.1'!B46/Deflactores!$B46*100 -> #N/A | C46: =+'[1]1.1'!C46/Deflactores!$B46*100 -> #N/A | D46: =+'[1]1.1'!D46/Deflactores!$B46*100 -> #N/A | E46: =+'[1]1.1'!E46/Deflactores!$B46*100 -> #N/A | F46: =+'[1]1.1'!F46/Deflactores!$B46*100 -> #N/A | G46: =+'[1]1.1'!G46/Deflactores!$B46*100 -> #N/A | H46: =+'[1]1.1'!H46/Deflactores!$B46*100 -> #N/A | I46: =+'[1]1.1'!I46/Deflactores!$B46*100 -> #N/A | ... Y46: =+'[1]1.1'!Y46/Deflactores!$B46*100 -> #N/A | Z46: =SUM(B46:Y46) -> #N/A
A47: 2029 | B47: =+'[1]1.1'!B47/Deflactores!$B47*100 -> #N/A | C47: =+'[1]1.1'!C47/Deflactores!$B47*100 -> #N/A | D47: =+'[1]1.1'!D47/Deflactores!$B47*100 -> #N/A | E47: =+'[1]1.1'!E47/Deflactores!$B47*100 -> #N/A | F47: =+'[1]1.1'!F47/Deflactores!$B47*100 -> #N/A | G47: =+'[1]1.1'!G47/Deflactores!$B47*100 -> #N/A | H47: =+'[1]1.1'!H47/Deflactores!$B47*100 -> #N/A | I47: =+'[1]1.1'!I47/Deflactores!$B47*100 -> #N/A | ... Y47: =+'[1]1.1'!Y47/Deflactores!$B47*100 -> #N/A | Z47: =SUM(B47:Y47) -> #N/A
A48: 2030 | B48: =+'[1]1.1'!B48/Deflactores!$B48*100 -> #N/A | C48: =+'[1]1.1'!C48/Deflactores!$B48*100 -> #N/A | D48: =+'[1]1.1'!D48/Deflactores!$B48*100 -> #N/A | E48: =+'[1]1.1'!E48/Deflactores!$B48*100 -> #N/A | F48: =+'[1]1.1'!F48/Deflactores!$B48*100 -> #N/A | G48: =+'[1]1.1'!G48/Deflactores!$B48*100 -> #N/A | H48: =+'[1]1.1'!H48/Deflactores!$B48*100 -> #N/A | I48: =+'[1]1.1'!I48/Deflactores!$B48*100 -> #N/A | ... Y48: =+'[1]1.1'!Y48/Deflactores!$B48*100 -> #N/A | Z48: =SUM(B48:Y48) -> #N/A

Sheet 1.1.1
A2: Título | B2: Recursos corrientes por provincia | N2: =B2 -> Recursos corrientes por provincia
A3: Fuente | B3: Dirección Nacional de Asuntos Provinciales - Ministerio de Economía de la Nación | N3: =B3 -> Dirección Nacional de Asuntos Provinciales - Ministerio de Economía de la Nación
A5: VOLVER AL ÍNDICE | B5: Administración Pública No Financiera | N5: =B5 -> Administración Pública No Financiera
A7: Unidad de medida | B7: Millones de pesos constantes de 2016 | C7: Millones de pesos constantes de 2016 | D7: Millones de pesos constantes de 2016 | E7: Millones de pesos constantes de 2016 | F7: Millones de pesos constantes de 2016 | G7: Millones de pesos constantes de 2016 | H7: Millones de pesos constantes de 2016 | I7: Millones de pesos constantes de 2016 | J7: Millones de pesos constantes de 2016 | K7: Millones de pesos constantes de 2016 | L7: Millones de pesos constantes de 2016 | M7: Millones de pesos constantes de 2016 | N7: Millones de pesos constantes de 2016 | O7: Millones de pesos constantes de 2016 | P7: Millones de pesos constantes de 2016 | Q7: Millones de pesos constantes de 2016 | R7: Millones de pesos constantes de 2016 | S7: Millones de pesos constantes de 2016 | T7: Millones de pesos constantes de 2016 | U7: Millones de pesos constantes de 2016 | V7: Millones de pesos constantes de 2016 | W7: Millones de pesos constantes de 2016 | X7: Millones de pesos constantes de 2016 | Y7: Millones de pesos constantes de 2016 | Z7: Millones de pesos constantes de 2016
A8: CÓDIGO | B8: 1.1.1.1 | C8: 1.1.1.2 | D8: 1.1.1.3 | E8: 1.1.1.4 | F8: 1.1.1.5 | G8: 1.1.1.6 | H8: 1.1.1.7 | I8: 1.1.1.8 | J8: 1.1.1.9 | K8: 1.1.1.10 | L8: 1.1.1.11 | M8: 1.1.1.12 | N8: 1.1.1.13 | O8: 1.1.1.14 | P8: 1.1.1.15 | Q8: 1.1.1.16 | R8: 1.1.1.17 | S8: 1.1.1.18 | T8: 1.1.1.19 | U8: 1.1.1.20 | V8: 1.1.1.21 | W8: 1.1.1.22 | X8: 1.1.1.23 | Y8: 1.1.1.24 | Z8: 1.1.1.25
A9: Jurisdicción | B9: C.A.B.A. | C9: Buenos Aires | D9: Catamarca | E9: Córdoba | F9: Corrientes | G9: Chaco | H9: Chubut | I9: Entre Ríos | J9: Formosa | K9: Jujuy | L9: La Pampa | M9: La Rioja | N9: Mendoza | O9: Misiones | P9: Neuquén | Q9: Río Negro | R9: Salta | S9: San Juan | T9: San Luis | U9: Santa Cruz | V9: Santa Fe | W9: Santiago del Estero | X9: Tucumán | Y9: Tierra del Fuego | Z9: Total
A10: 1992 | B10: =+'[1]1.1.1'!B10/Deflactores!$B10*100 -> 40593.665 | C10: =+'[1]1.1.1'!C10/Deflactores!$B10*100 -> 113440.29 | D10: =+'[1]1.1.1'!D10/Deflactores!$B10*100 -> 6698.6499 | E10: =+'[1]1.1.1'!E10/Deflactores!$B10*100 -> 32717.264 | F10: =+'[1]1.1.1'!F10/Deflactores!$B10*100 -> 10015.013 | G10: =+'[1]1.1.1'!G10/Deflactores!$B10*100 -> 12118.197 | H10: =+'[1]1.1.1'!H10/Deflactores!$B10*100 -> 7063.1274 | I10: =+'[1]1.1.1'!I10/Deflactores!$B10*100 -> 14730.308 | ... Y10: =+'[1]1.1.1'!Y10/Deflactores!$B10*100 -> 4353.4504 | Z10: =SUM(B10:Y10) -> 414391.17
A11: 1993 | B11: =+'[1]1.1.1'!B11/Deflactores!$B11*100 -> 47756.135 | C11: =+'[1]1.1.1'!C11/Deflactores!$B11*100 -> 122257.51 | D11: =+'[1]1.1.1'!D11/Deflactores!$B11*100 -> 6510.4396 | E11: =+'[1]1.1.1'!E11/Deflactores!$B11*100 -> 34275.532 | F11: =+'[1]1.1.1'!F11/Deflactores!$B11*100 -> 10426.807 | G11: =+'[1]1.1.1'!G11/Deflactores!$B11*100 -> 11802.811 | H11: =+'[1]1.1.1'!H11/Deflactores!$B11*100 -> 7148.7973 | I11: =+'[1]1.1.1'!I11/Deflactores!$B11*100 -> 15527.239 | ... Y11: =+'[1]1.1.1'!Y11/Deflactores!$B11*100 -> 4679.7458 | Z11: =SUM(B11:Y11) -> 440021.69
A12: 1994 | B12: =+'[1]1.1.1'!B12/Deflactores!$B12*100 -> 47819.778 | C12: =+'[1]1.1.1'!C12/Deflactores!$B12*100 -> 132221.66 | D12: =+'[1]1.1.1'!D12/Deflactores!$B12*100 -> 6715.625 | E12: =+'[1]1.1.1'!E12/Deflactores!$B12*100 -> 36832.345 | F12: =+'[1]1.1.1'!F12/Deflactores!$B12*100 -> 10161.447 | G12: =+'[1]1.1.1'!G12/Deflactores!$B12*100 -> 12084.682 | H12: =+'[1]1.1.1'!H12/Deflactores!$B12*100 -> 7288.1521 | I12: =+'[1]1.1.1'!I12/Deflactores!$B12*100 -> 16559.584 | ... Y12: =+'[1]1.1.1'!Y12/Deflactores!$B12*100 -> 5554.1585 | Z12: =SUM(B12:Y12) -> 464291.59
A13: 1995 | B13: =+'[1]1.1.1'!B13/Deflactores!$B13*100 -> 44073.349 | C13: =+'[1]1.1.1'!C13/Deflactores!$B13*100 -> 124840.17 | D13: =+'[1]1.1.1'!D13/Deflactores!$B13*100 -> 6039.2967 | E13: =+'[1]1.1.1'!E13/Deflactores!$B13*100 -> 32806.799 | F13: =+'[1]1.1.1'!F13/Deflactores!$B13*100 -> 9396.5801 | G13: =+'[1]1.1.1'!G13/Deflactores!$B13*100 -> 11475.289 | H13: =+'[1]1.1.1'!H13/Deflactores!$B13*100 -> 7690.4559 | I13: =+'[1]1.1.1'!I13/Deflactores!$B13*100 -> 15473.804 | ... Y13: =+'[1]1.1.1'!Y13/Deflactores!$B13*100 -> 5013.4416 | Z13: =SUM(B13:Y13) -> 428165.79
A14: 1996 | B14: =+'[1]1.1.1'!B14/Deflactores!$B14*100 -> 44525.439 | C14: =+'[1]1.1.1'!C14/Deflactores!$B14*100 -> 131007.65 | D14: =+'[1]1.1.1'!D14/Deflactores!$B14*100 -> 6561.3442 | E14: =+'[1]1.1.1'!E14/Deflactores!$B14*100 -> 36141.521 | F14: =+'[1]1.1.1'!F14/Deflactores!$B14*100 -> 9995.6538 | G14: =+'[1]1.1.1'!G14/Deflactores!$B14*100 -> 12500.87 | H14: =+'[1]1.1.1'!H14/Deflactores!$B14*100 -> 7810.3105 | I14: =+'[1]1.1.1'!I14/Deflactores!$B14*100 -> 16965.498 | ... Y14: =+'[1]1.1.1'!Y14/Deflactores!$B14*100 -> 5106.4553 | Z14: =SUM(B14:Y14) -> 456305.71
A15: 1997 | B15: =+'[1]1.1.1'!B15/Deflactores!$B15*100 -> 48860.733 | C15: =+'[1]1.1.1'!C15/Deflactores!$B15*100 -> 150729.2 | D15: =+'[1]1.1.1'!D15/Deflactores!$B15*100 -> 8305.362 | E15: =+'[1]1.1.1'!E15/Deflactores!$B15*100 -> 40300.241 | F15: =+'[1]1.1.1'!F15/Deflactores!$B15*100 -> 12117.402 | G15: =+'[1]1.1.1'!G15/Deflactores!$B15*100 -> 14500.884 | H15: =+'[1]1.1.1'!H15/Deflactores!$B15*100 -> 8638.7151 | I15: =+'[1]1.1.1'!I15/Deflactores!$B15*100 -> 19148.236 | ... Y15: =+'[1]1.1.1'!Y15/Deflactores!$B15*100 -> 5634.3483 | Z15: =SUM(B15:Y15) -> 520191.27
A16: 1998 | B16: =+'[1]1.1.1'!B16/Deflactores!$B16*100 -> 56357.513 | C16: =+'[1]1.1.1'!C16/Deflactores!$B16*100 -> 161933.82 | D16: =+'[1]1.1.1'!D16/Deflactores!$B16*100 -> 8840.1403 | E16: =+'[1]1.1.1'!E16/Deflactores!$B16*100 -> 43558.126 | F16: =+'[1]1.1.1'!F16/Deflactores!$B16*100 -> 12712.385 | G16: =+'[1]1.1.1'!G16/Deflactores!$B16*100 -> 15794.526 | H16: =+'[1]1.1.1'!H16/Deflactores!$B16*100 -> 8627.8052 | I16: =+'[1]1.1.1'!I16/Deflactores!$B16*100 -> 20492.326 | ... Y16: =+'[1]1.1.1'!Y16/Deflactores!$B16*100 -> 6103.0367 | Z16: =SUM(B16:Y16) -> 561420.75
A17: 1999 | B17: =+'[1]1.1.1'!B17/Deflactores!$B17*100 -> 58302.701 | C17: =+'[1]1.1.1'!C17/Deflactores!$B17*100 -> 160762.12 | D17: =+'[1]1.1.1'!D17/Deflactores!$B17*100 -> 9106.0331 | E17: =+'[1]1.1.1'!E17/Deflactores!$B17*100 -> 42787.372 | F17: =+'[1]1.1.1'!F17/Deflactores!$B17*100 -> 13381.618 | G17: =+'[1]1.1.1'!G17/Deflactores!$B17*100 -> 15953.105 | H17: =+'[1]1.1.1'!H17/Deflactores!$B17*100 -> 9017.9958 | I17: =+'[1]1.1.1'!I17/Deflactores!$B17*100 -> 20343.509 | ... Y17: =+'[1]1.1.1'!Y17/Deflactores!$B17*100 -> 6382.7161 | Z17: =SUM(B17:Y17) -> 568718.41
A18: 2000 | B18: =+'[1]1.1.1'!B18/Deflactores!$B18*100 -> 61742.917 | C18: =+'[1]1.1.1'!C18/Deflactores!$B18*100 -> 171663.67 | D18: =+'[1]1.1.1'!D18/Deflactores!$B18*100 -> 9306.6971 | E18: =+'[1]1.1.1'!E18/Deflactores!$B18*100 -> 45146.796 | F18: =+'[1]1.1.1'!F18/Deflactores!$B18*100 -> 13620.906 | G18: =+'[1]1.1.1'!G18/Deflactores!$B18*100 -> 17022.383 | H18: =+'[1]1.1.1'!H18/Deflactores!$B18*100 -> 11069.054 | I18: =+'[1]1.1.1'!I18/Deflactores!$B18*100 -> 21003.349 | ... Y18: =+'[1]1.1.1'!Y18/Deflactores!$B18*100 -> 7581.5362 | Z18: =SUM(B18:Y18) -> 606331
A19: 2001 | B19: =+'[1]1.1.1'!B19/Deflactores!$B19*100 -> 57318.719 | C19: =+'[1]1.1.1'!C19/Deflactores!$B19*100 -> 152927.5 | D19: =+'[1]1.1.1'!D19/Deflactores!$B19*100 -> 9457.5836 | E19: =+'[1]1.1.1'!E19/Deflactores!$B19*100 -> 42618.582 | F19: =+'[1]1.1.1'!F19/Deflactores!$B19*100 -> 13593.764 | G19: =+'[1]1.1.1'!G19/Deflactores!$B19*100 -> 16442.817 | H19: =+'[1]1.1.1'!H19/Deflactores!$B19*100 -> 10706.13 | I19: =+'[1]1.1.1'!I19/Deflactores!$B19*100 -> 20841.758 | ... Y19: =+'[1]1.1.1'!Y19/Deflactores!$B19*100 -> 7754.628 | Z19: =SUM(B19:Y19) -> 572454.2
A20: 2002 | B20: =+'[1]1.1.1'!B20/Deflactores!$B20*100 -> 38666.685 | C20: =+'[1]1.1.1'!C20/Deflactores!$B20*100 -> 116713.55 | D20: =+'[1]1.1.1'!D20/Deflactores!$B20*100 -> 6440.4261 | E20: =+'[1]1.1.1'!E20/Deflactores!$B20*100 -> 29536.661 | F20: =+'[1]1.1.1'!F20/Deflactores!$B20*100 -> 8744.6553 | G20: =+'[1]1.1.1'!G20/Deflactores!$B20*100 -> 11972.859 | H20: =+'[1]1.1.1'!H20/Deflactores!$B20*100 -> 11228.531 | I20: =+'[1]1.1.1'!I20/Deflactores!$B20*100 -> 13469.34 | ... Y20: =+'[1]1.1.1'!Y20/Deflactores!$B20*100 -> 5525.4426 | Z20: =SUM(B20:Y20) -> 427109.32
A21: 2003 | B21: =+'[1]1.1.1'!B21/Deflactores!$B21*100 -> 44452.879 | C21: =+'[1]1.1.1'!C21/Deflactores!$B21*100 -> 126455.63 | D21: =+'[1]1.1.1'!D21/Deflactores!$B21*100 -> 7400.2702 | E21: =+'[1]1.1.1'!E21/Deflactores!$B21*100 -> 33964.166 | F21: =+'[1]1.1.1'!F21/Deflactores!$B21*100 -> 9588.91 | G21: =+'[1]1.1.1'!G21/Deflactores!$B21*100 -> 12910.886 | H21: =+'[1]1.1.1'!H21/Deflactores!$B21*100 -> 11687.632 | I21: =+'[1]1.1.1'!I21/Deflactores!$B21*100 -> 15006.982 | ... Y21: =+'[1]1.1.1'!Y21/Deflactores!$B21*100 -> 5812.6142 | Z21: =SUM(B21:Y21) -> 466512.84
... A48: 2030 | B48: =+'[1]1.1.1'!B48/Deflactores!$B48*100 -> #N/A | C48: =+'[1]1.1.1'!C48/Deflactores!$B48*100 -> #N/A | D48: =+'[1]1.1.1'!D48/Deflactores!$B48*100 -> #N/A | E48: =+'[1]1.1.1'!E48/Deflactores!$B48*100 -> #N/A | F48: =+'[1]1.1.1'!F48/Deflactores!$B48*100 -> #N/A | G48: =+'[1]1.1.1'!G48/Deflactores!$B48*100 -> #N/A | H48: =+'[1]1.1.1'!H48/Deflactores!$B48*100 -> #N/A | I48: =+'[1]1.1.1'!I48/Deflactores!$B48*100 -> #N/A | ... Y48: =+'[1]1.1.1'!Y48/Deflactores!$B48*100 -> #N/A | Z48: =SUM(B48:Y48) -> #N/A

Sheet 1.1.1.1
A2: Título | B2: Recursos tributarios de origen provincial (Impuestos provinciales) por provincia | N2: =B2 -> Recursos tributarios de origen provincial (Impuestos provinciales) por provincia
A3: Fuente | B3: Dirección Nacional de Asuntos Provinciales - Ministerio de Economía de la Nación | N3: =B3 -> Dirección Nacional de Asuntos Provinciales - Ministerio de Economía de la Nación
A5: VOLVER AL ÍNDICE | B5: Administración Pública No Financiera | N5: =B5 -> Administración Pública No Financiera
A7: Unidad de medida | B7: Millones de pesos constantes de 2016 | C7: Millones de pesos constantes de 2016 | D7: Millones de pesos constantes de 2016 | E7: Millones de pesos constantes de 2016 | F7: Millones de pesos constantes de 2016 | G7: Millones de pesos constantes de 2016 | H7: Millones de pesos constantes de 2016 | I7: Millones de pesos constantes de 2016 | J7: Millones de pesos constantes de 2016 | K7: Millones de pesos constantes de 2016 | L7: Millones de pesos constantes de 2016 | M7: Millones de pesos constantes de 2016 | N7: Millones de pesos constantes de 2016 | O7: Millones de pesos constantes de 2016 | P7: Millones de pesos constantes de 2016 | Q7: Millones de pesos constantes de 2016 | R7: Millones de pesos constantes de 2016 | S7: Millones de pesos constantes de 2016 | T7: Millones de pesos constantes de 2016 | U7: Millones de pesos constantes de 2016 | V7: Millones de pesos constantes de 2016 | W7: Millones de pesos constantes de 2016 | X7: Millones de pesos constantes de 2016 | Y7: Millones de pesos constantes de 2016 | Z7: Millones de pesos constantes de 2016
A8: CÓDIGO | B8: 1.1.1.1.1 | C8: 1.1.1.1.2 | D8: 1.1.1.1.3 | E8: 1.1.1.1.4 | F8: 1.1.1.1.5 | G8: 1.1.1.1.6 | H8: 1.1.1.1.7 | I8: 1.1.1.1.8 | J8: 1.1.1.1.9 | K8: 1.1.1.1.10 | L8: 1.1.1.1.11 | M8: 1.1.1.1.12 | N8: 1.1.1.1.13 | O8: 1.1.1.1.14 | P8: 1.1.1.1.15 | Q8: 1.1.1.1.16 | R8: 1.1.1.1.17 | S8: 1.1.1.1.18 | T8: 1.1.1.1.19 | U8: 1.1.1.1.20 | V8: 1.1.1.1.21 | W8: 1.1.1.1.22 | X8: 1.1.1.1.23 | Y8: 1.1.1.1.24 | Z8: 1.1.1.1.25
A9: Jurisdicción | B9: C.A.B.A. | C9: Buenos Aires | D9: Catamarca | E9: Córdoba | F9: Corrientes | G9: Chaco | H9: Chubut | I9: Entre Ríos | J9: Formosa | K9: Jujuy | L9: La Pampa | M9: La Rioja | N9: Mendoza | O9: Misiones | P9: Neuquén | Q9: Río Negro | R9: Salta | S9: San Juan | T9: San Luis | U9: Santa Cruz | V9: Santa Fe | W9: Santiago del Estero | X9: Tucumán | Y9: Tierra del Fuego | Z9: Total
A10: 1992 | B10: =+'[1]1.1.1.1'!B10/Deflactores!$B10*100 -> 35085.397 | C10: =+'[1]1.1.1.1'!C10/Deflactores!$B10*100 -> 52653.247 | D10: =+'[1]1.1.1.1'!D10/Deflactores!$B10*100 -> 328.40734 | E10: =+'[1]1.1.1.1'!E10/Deflactores!$B10*100 -> 12654.609 | F10: =+'[1]1.1.1.1'!F10/Deflactores!$B10*100 -> 1061.8454 | G10: =+'[1]1.1.1.1'!G10/Deflactores!$B10*100 -> 1155.2987 | H10: =+'[1]1.1.1.1'!H10/Deflactores!$B10*100 -> 879.83481 | I10: =+'[1]1.1.1.1'!I10/Deflactores!$B10*100 -> 3036.9396 | ... Y10: =+'[1]1.1.1.1'!Y10/Deflactores!$B10*100 -> 1044.0254 | Z10: =SUM(B10:Y10) -> 141370.88
A11: 1993 | B11: =+'[1]1.1.1.1'!B11/Deflactores!$B11*100 -> 41471.19 | C11: =+'[1]1.1.1.1'!C11/Deflactores!$B11*100 -> 56671.882 | D11: =+'[1]1.1.1.1'!D11/Deflactores!$B11*100 -> 409.08571 | E11: =+'[1]1.1.1.1'!E11/Deflactores!$B11*100 -> 13336.594 | F11: =+'[1]1.1.1.1'!F11/Deflactores!$B11*100 -> 1244.5607 | G11: =+'[1]1.1.1.1'!G11/Deflactores!$B11*100 -> 1254.8895 | H11: =+'[1]1.1.1.1'!H11/Deflactores!$B11*100 -> 875.53205 | I11: =+'[1]1.1.1.1'!I11/Deflactores!$B11*100 -> 3635.9365 | ... Y11: =+'[1]1.1.1.1'!Y11/Deflactores!$B11*100 -> 1098.9494 | Z11: =SUM(B11:Y11) -> 156289.06
A12: 1994 | B12: =+'[1]1.1.1.1'!B12/Deflactores!$B12*100 -> 40788.277 | C12: =+'[1]1.1.1.1'!C12/Deflactores!$B12*100 -> 63135.446 | D12: =+'[1]1.1.1.1'!D12/Deflactores!$B12*100 -> 456.12767 | E12: =+'[1]1.1.1.1'!E12/Deflactores!$B12*100 -> 14912.498 | F12: =+'[1]1.1.1.1'!F12/Deflactores!$B12*100 -> 1227.0036 | G12: =+'[1]1.1.1.1'!G12/Deflactores!$B12*100 -> 1405.9753 | H12: =+'[1]1.1.1.1'!H12/Deflactores!$B12*100 -> 905.02645 | I12: =+'[1]1.1.1.1'!I12/Deflactores!$B12*100 -> 4306.801 | ... Y12: =+'[1]1.1.1.1'!Y12/Deflactores!$B12*100 -> 842.13354 | Z12: =SUM(B12:Y12) -> 167908.47
A13: 1995 | B13: =+'[1]1.1.1.1'!B13/Deflactores!$B13*100 -> 37714.326 | C13: =+'[1]1.1.1.1'!C13/Deflactores!$B13*100 -> 57102.771 | D13: =+'[1]1.1.1.1'!D13/Deflactores!$B13*100 -> 365.40618 | E13: =+'[1]1.1.1.1'!E13/Deflactores!$B13*100 -> 13963.242 | F13: =+'[1]1.1.1.1'!F13/Deflactores!$B13*100 -> 1140.8703 | G13: =+'[1]1.1.1.1'!G13/Deflactores!$B13*100 -> 1619.7511 | H13: =+'[1]1.1.1.1'!H13/Deflactores!$B13*100 -> 867.60351 | I13: =+'[1]1.1.1.1'!I13/Deflactores!$B13*100 -> 4409.973 | ... Y13: =+'[1]1.1.1.1'!Y13/Deflactores!$B13*100 -> 729.10447 | Z13: =SUM(B13:Y13) -> 151006.83
A14: 1996 | B14: =+'[1]1.1.1.1'!B14/Deflactores!$B14*100 -> 37798.219 | C14: =+'[1]1.1.1.1'!C14/Deflactores!$B14*100 -> 63184.04 | D14: =+'[1]1.1.1.1'!D14/Deflactores!$B14*100 -> 585.52044 | E14: =+'[1]1.1.1.1'!E14/Deflactores!$B14*100 -> 14107.232 | F14: =+'[1]1.1.1.1'!F14/Deflactores!$B14*100 -> 1099.8901 | G14: =+'[1]1.1.1.1'!G14/Deflactores!$B14*100 -> 1799.6117 | H14: =+'[1]1.1.1.1'!H14/Deflactores!$B14*100 -> 923.28313 | I14: =+'[1]1.1.1.1'!I14/Deflactores!$B14*100 -> 4673.9693 | ... Y14: =+'[1]1.1.1.1'!Y14/Deflactores!$B14*100 -> 646.66182 | Z14: =SUM(B14:Y14) -> 160118.76
A15: 1997 | B15: =+'[1]1.1.1.1'!B15/Deflactores!$B15*100 -> 41453.782 | C15: =+'[1]1.1.1.1'!C15/Deflactores!$B15*100 -> 76132.346 | D15: =+'[1]1.1.1.1'!D15/Deflactores!$B15*100 -> 653.10396 | E15: =+'[1]1.1.1.1'!E15/Deflactores!$B15*100 -> 14343.929 | F15: =+'[1]1.1.1.1'!F15/Deflactores!$B15*100 -> 1224.8828 | G15: =+'[1]1.1.1.1'!G15/Deflactores!$B15*100 -> 1890.277 | H15: =+'[1]1.1.1.1'!H15/Deflactores!$B15*100 -> 1048.8018 | I15: =+'[1]1.1.1.1'!I15/Deflactores!$B15*100 -> 5037.6064 | ... Y15: =+'[1]1.1.1.1'!Y15/Deflactores!$B15*100 -> 700.89593 | Z15: =SUM(B15:Y15) -> 183946.56
A16: 1998 | B16: =+'[1]1.1.1.1'!B16/Deflactores!$B16*100 -> 48559.005 | C16: =+'[1]1.1.1.1'!C16/Deflactores!$B16*100 -> 82664.636 | D16: =+'[1]1.1.1.1'!D16/Deflactores!$B16*100 -> 708.76191 | E16: =+'[1]1.1.1.1'!E16/Deflactores!$B16*100 -> 15976.882 | F16: =+'[1]1.1.1.1'!F16/Deflactores!$B16*100 -> 1327.7775 | G16: =+'[1]1.1.1.1'!G16/Deflactores!$B16*100 -> 1835.469 | H16: =+'[1]1.1.1.1'!H16/Deflactores!$B16*100 -> 1053.2634 | I16: =+'[1]1.1.1.1'!I16/Deflactores!$B16*100 -> 5306.1148 | ... Y16: =+'[1]1.1.1.1'!Y16/Deflactores!$B16*100 -> 778.21687 | Z16: =SUM(B16:Y16) -> 204276.28
A17: 1999 | B17: =+'[1]1.1.1.1'!B17/Deflactores!$B17*100 -> 50019.873 | C17: =+'[1]1.1.1.1'!C17/Deflactores!$B17*100 -> 79506.014 | D17: =+'[1]1.1.1.1'!D17/Deflactores!$B17*100 -> 714.78724 | E17: =+'[1]1.1.1.1'!E17/Deflactores!$B17*100 -> 15282.412 | F17: =+'[1]1.1.1.1'!F17/Deflactores!$B17*100 -> 1236.1225 | G17: =+'[1]1.1.1.1'!G17/Deflactores!$B17*100 -> 1828.9545 | H17: =+'[1]1.1.1.1'!H17/Deflactores!$B17*100 -> 1190.6787 | I17: =+'[1]1.1.1.1'!I17/Deflactores!$B17*100 -> 5193.4245 | ... Y17: =+'[1]1.1.1.1'!Y17/Deflactores!$B17*100 -> 814.65361 | Z17: =SUM(B17:Y17) -> 202127.56
A18: 2000 | B18: =+'[1]1.1.1.1'!B18/Deflactores!$B18*100 -> 52444.692 | C18: =+'[1]1.1.1.1'!C18/Deflactores!$B18*100 -> 79270.473 | D18: =+'[1]1.1.1.1'!D18/Deflactores!$B18*100 -> 735.12017 | E18: =+'[1]1.1.1.1'!E18/Deflactores!$B18*100 -> 16263.134 | F18: =+'[1]1.1.1.1'!F18/Deflactores!$B18*100 -> 1482.4468 | G18: =+'[1]1.1.1.1'!G18/Deflactores!$B18*100 -> 1761.651 | H18: =+'[1]1.1.1.1'!H18/Deflactores!$B18*100 -> 1376.2016 | I18: =+'[1]1.1.1.1'!I18/Deflactores!$B18*100 -> 4986.9274 | ... Y18: =+'[1]1.1.1.1'!Y18/Deflactores!$B18*100 -> 830.87694 | Z18: =SUM(B18:Y18) -> 206967.99
A19: 2001 | B19: =+'[1]1.1.1.1'!B19/Deflactores!$B19*100 -> 49110.248 | C19: =+'[1]1.1.1.1'!C19/Deflactores!$B19*100 -> 70332.41 | D19: =+'[1]1.1.1.1'!D19/Deflactores!$B19*100 -> 713.33998 | E19: =+'[1]1.1.1.1'!E19/Deflactores!$B19*100 -> 14714.842 | F19: =+'[1]1.1.1.1'!F19/Deflactores!$B19*100 -> 1542.8818 | G19: =+'[1]1.1.1.1'!G19/Deflactores!$B19*100 -> 1568.0121 | H19: =+'[1]1.1.1.1'!H19/Deflactores!$B19*100 -> 1568.4665 | I19: =+'[1]1.1.1.1'!I19/Deflactores!$B19*100 -> 5059.4529 | ... Y19: =+'[1]1.1.1.1'!Y19/Deflactores!$B19*100 -> 899.81085 | Z19: =SUM(B19:Y19) -> 190879.99
A20: 2002 | B20: =+'[1]1.1.1.1'!B20/Deflactores!$B20*100 -> 33055.26 | C20: =+'[1]1.1.1.1'!C20/Deflactores!$B20*100 -> 57191.523 | D20: =+'[1]1.1.1.1'!D20/Deflactores!$B20*100 -> 472.58508 | E20: =+'[1]1.1.1.1'!E20/Deflactores!$B20*100 -> 10777.478 | F20: =+'[1]1.1.1.1'!F20/Deflactores!$B20*100 -> 1059.7544 | G20: =+'[1]1.1.1.1'!G20/Deflactores!$B20*100 -> 1320.5748 | H20: =+'[1]1.1.1.1'!H20/Deflactores!$B20*100 -> 1424.4549 | I20: =+'[1]1.1.1.1'!I20/Deflactores!$B20*100 -> 3343.9128 | ... Y20: =+'[1]1.1.1.1'!Y20/Deflactores!$B20*100 -> 620.84779 | Z20: =SUM(B20:Y20) -> 142662.23
A21: 2003 | B21: =+'[1]1.1.1.1'!B21/Deflactores!$B21*100 -> 36552.313 | C21: =+'[1]1.1.1.1'!C21/Deflactores!$B21*100 -> 63311.892 | D21: =+'[1]1.1.1.1'!D21/Deflactores!$B21*100 -> 644.42946 | E21: =+'[1]1.1.1.1'!E21/Deflactores!$B21*100 -> 11576.633 | F21: =+'[1]1.1.1.1'!F21/Deflactores!$B21*100 -> 1066.2633 | G21: =+'[1]1.1.1.1'!G21/Deflactores!$B21*100 -> 1563.0045 | H21: =+'[1]1.1.1.1'!H21/Deflactores!$B21*100 -> 1630.5524 | I21: =+'[1]1.1.1.1'!I21/Deflactores!$B21*100 -> 3662.096 | ... Y21: =+'[1]1.1.1.1'!Y21/Deflactores!$B21*100 -> 892.7015 | Z21: =SUM(B21:Y21) -> 160141.56
... A48: 2030 | B48: =+'[1]1.1.1.1'!B48/Deflactores!$B48*100 -> #N/A | C48: =+'[1]1.1.1.1'!C48/Deflactores!$B48*100 -> #N/A | D48: =+'[1]1.1.1.1'!D48/Deflactores!$B48*100 -> #N/A | E48: =+'[1]1.1.1.1'!E48/Deflactores!$B48*100 -> #N/A | F48: =+'[1]1.1.1.1'!F48/Deflactores!$B48*100 -> #N/A | G48: =+'[1]1.1.1.1'!G48/Deflactores!$B48*100 -> #N/A | H48: =+'[1]1.1.1.1'!H48/Deflactores!$B48*100 -> #N/A | I48: =+'[1]1.1.1.1'!I48/Deflactores!$B48*100 -> #N/A | ... Y48: =+'[1]1.1.1.1'!Y48/Deflactores!$B48*100 -> #N/A | Z48: =SUM(B48:Y48) -> #N/A

Sheet 1.1.1.1.1
A2: Título | B2: Ingresos Brutos | N2: =B2 -> Ingresos Brutos
A3: Fuente | B3: Dirección Nacional de Asuntos Provinciales - Ministerio de Economía de la Nación | N3: =B3 -> Dirección Nacional de Asuntos Provinciales - Ministerio de Economía de la Nación
A5: VOLVER AL ÍNDICE | B5: Administración Pública No Financiera | N5: =B5 -> Administración Pública No Financiera
A7: Unidad de medida | B7: Millones de pesos constantes de 2016 | C7: Millones de pesos constantes de 2016 | D7: Millones de pesos constantes de 2016 | E7: Millones de pesos constantes de 2016 | F7: Millones de pesos constantes de 2016 | G7: Millones de pesos constantes de 2016 | H7: Millones de pesos constantes de 2016 | I7: Millones de pesos constantes de 2016 | J7: Millones de pesos constantes de 2016 | K7: Millones de pesos constantes de 2016 | L7: Millones de pesos constantes de 2016 | M7: Millones de pesos constantes de 2016 | N7: Millones de pesos constantes de 2016 | O7: Millones de pesos constantes de 2016 | P7: Millones de pesos constantes de 2016 | Q7: Millones de pesos constantes de 2016 | R7: Millones de pesos constantes de 2016 | S7: Millones de pesos constantes de 2016 | T7: Millones de pesos constantes de 2016 | U7: Millones de pesos constantes de 2016 | V7: Millones de pesos constantes de 2016 | W7: Millones de pesos constantes de 2016 | X7: Millones de pesos constantes de 2016 | Y7: Millones de pesos constantes de 2016 | Z7: Millones de pesos constantes de 2016
A8: CÓDIGO | B8: 1.1.1.1.1.1 | C8: 1.1.1.1.1.2 | D8: 1.1.1.1.1.3 | E8: 1.1.1.1.1.4 | F8: 1.1.1.1.1.5 | G8: 1.1.1.1.1.6 | H8: 1.1.1.1.1.7 | I8: 1.1.1.1.1.8 | J8: 1.1.1.1.1.9 | K8: 1.1.1.1.1.10 | L8: 1.1.1.1.1.11 | M8: 1.1.1.1.1.12 | N8: 1.1.1.1.1.13 | O8: 1.1.1.1.1.14 | P8: 1.1.1.1.1.15 | Q8: 1.1.1.1.1.16 | R8: 1.1.1.1.1.17 | S8: 1.1.1.1.1.18 | T8: 1.1.1.1.1.19 | U8: 1.1.1.1.1.20 | V8: 1.1.1.1.1.21 | W8: 1.1.1.1.1.22 | X8: 1.1.1.1.1.23 | Y8: 1.1.1.1.1.24 | Z8: 1.1.1.1.1.25
A9: Jurisdicción | B9: C.A.B.A. | C9: Buenos Aires | D9: Catamarca | E9: Córdoba | F9: Corrientes | G9: Chaco | H9: Chubut | I9: Entre Ríos | J9: Formosa | K9: Jujuy | L9: La Pampa | M9: La Rioja | N9: Mendoza | O9: Misiones | P9: Neuquén | Q9: Río Negro | R9: Salta | S9: San Juan | T9: San Luis | U9: Santa Cruz | V9: Santa Fe | W9: Santiago del Estero | X9: Tucumán | Y9: Tierra del Fuego | Z9: Total
A10: 1992 | B10: =+'[1]1.1.1.1.1'!B10/Deflactores!$B10*100 -> 22889.715 | C10: =+'[1]1.1.1.1.1'!C10/Deflactores!$B10*100 -> 24767.13 | D10: =+'[1]1.1.1.1.1'!D10/Deflactores!$B10*100 -> 200.87518 | E10: =+'[1]1.1.1.1.1'!E10/Deflactores!$B10*100 -> 6868.3848 | F10: =+'[1]1.1.1.1.1'!F10/Deflactores!$B10*100 -> 698.16005 | G10: =+'[1]1.1.1.1.1'!G10/Deflactores!$B10*100 -> 784.71754 | H10: =+'[1]1.1.1.1.1'!H10/Deflactores!$B10*100 -> 645.90082 | I10: =+'[1]1.1.1.1.1'!I10/Deflactores!$B10*100 -> 1187.6183 | ... Y10: =+'[1]1.1.1.1.1'!Y10/Deflactores!$B10*100 -> 579.70488 | Z10: =SUM(B10:Y10) -> 77959.141
A11: 1993 | B11: =+'[1]1.1.1.1.1'!B11/Deflactores!$B11*100 -> 29341.267 | C11: =+'[1]1.1.1.1.1'!C11/Deflactores!$B11*100 -> 26629.748 | D11: =+'[1]1.1.1.1.1'!D11/Deflactores!$B11*100 -> 250.22323 | E11: =+'[1]1.1.1.1.1'!E11/Deflactores!$B11*100 -> 7473.2091 | F11: =+'[1]1.1.1.1.1'!F11/Deflactores!$B11*100 -> 831.9219 | G11: =+'[1]1.1.1.1.1'!G11/Deflactores!$B11*100 -> 821.57031 | H11: =+'[1]1.1.1.1.1'!H11/Deflactores!$B11*100 -> 658.55391 | I11: =+'[1]1.1.1.1.1'!I11/Deflactores!$B11*100 -> 1421.8606 | ... Y11: =+'[1]1.1.1.1.1'!Y11/Deflactores!$B11*100 -> 674.85019 | Z11: =SUM(B11:Y11) -> 89268.518
A12: 1994 | B12: =+'[1]1.1.1.1.1'!B12/Deflactores!$B12*100 -> 27070.881 | C12: =+'[1]1.1.1.1.1'!C12/Deflactores!$B12*100 -> 31281.118 | D12: =+'[1]1.1.1.1.1'!D12/Deflactores!$B12*100 -> 265.37428 | E12: =+'[1]1.1.1.1.1'!E12/Deflactores!$B12*100 -> 8686.8613 | F12: =+'[1]1.1.1.1.1'!F12/Deflactores!$B12*100 -> 825.82667 | G12: =+'[1]1.1.1.1.1'!G12/Deflactores!$B12*100 -> 965.50768 | H12: =+'[1]1.1.1.1.1'!H12/Deflactores!$B12*100 -> 673.49603 | I12: =+'[1]1.1.1.1.1'!I12/Deflactores!$B12*100 -> 1684.2073 | ... Y12: =+'[1]1.1.1.1.1'!Y12/Deflactores!$B12*100 -> 715.59673 | Z12: =SUM(B12:Y12) -> 95513.963
A13: 1995 | B13: =+'[1]1.1.1.1.1'!B13/Deflactores!$B13*100 -> 24963.35 | C13: =+'[1]1.1.1.1.1'!C13/Deflactores!$B13*100 -> 28292.166 | D13: =+'[1]1.1.1.1.1'!D13/Deflactores!$B13*100 -> 232.94969 | E13: =+'[1]1.1.1.1.1'!E13/Deflactores!$B13*100 -> 7824.3575 | F13: =+'[1]1.1.1.1.1'!F13/Deflactores!$B13*100 -> 652.99409 | G13: =+'[1]1.1.1.1.1'!G13/Deflactores!$B13*100 -> 1184.9175 | H13: =+'[1]1.1.1.1.1'!H13/Deflactores!$B13*100 -> 644.79931 | I13: =+'[1]1.1.1.1.1'!I13/Deflactores!$B13*100 -> 1587.4932 | ... Y13: =+'[1]1.1.1.1.1'!Y13/Deflactores!$B13*100 -> 713.44481 | Z13: =SUM(B13:Y13) -> 85953.571
A14: 1996 | B14: =+'[1]1.1.1.1.1'!B14/Deflactores!$B14*100 -> 23739.011 | C14: =+'[1]1.1.1.1.1'!C14/Deflactores!$B14*100 -> 31305.194 | D14: =+'[1]1.1.1.1.1'!D14/Deflactores!$B14*100 -> 404.45859 | E14: =+'[1]1.1.1.1.1'!E14/Deflactores!$B14*100 -> 7905.0391 | F14: =+'[1]1.1.1.1.1'!F14/Deflactores!$B14*100 -> 764.7805 | G14: =+'[1]1.1.1.1.1'!G14/Deflactores!$B14*100 -> 1168.9625 | H14: =+'[1]1.1.1.1.1'!H14/Deflactores!$B14*100 -> 686.18015 | I14: =+'[1]1.1.1.1.1'!I14/Deflactores!$B14*100 -> 2229.4172 | ... Y14: =+'[1]1.1.1.1.1'!Y14/Deflactores!$B14*100 -> 635.10646 | Z14: =SUM(B14:Y14) -> 89632.242
A15: 1997 | B15: =+'[1]1.1.1.1.1'!B15/Deflactores!$B15*100 -> 26875.005 | C15: =+'[1]1.1.1.1.1'!C15/Deflactores!$B15*100 -> 35678.7 | D15: =+'[1]1.1.1.1.1'!D15/Deflactores!$B15*100 -> 496.14873 | E15: =+'[1]1.1.1.1.1'!E15/Deflactores!$B15*100 -> 7787.3429 | F15: =+'[1]1.1.1.1.1'!F15/Deflactores!$B15*100 -> 862.50796 | G15: =+'[1]1.1.1.1.1'!G15/Deflactores!$B15*100 -> 1296.1283 | H15: =+'[1]1.1.1.1.1'!H15/Deflactores!$B15*100 -> 823.81429 | I15: =+'[1]1.1.1.1.1'!I15/Deflactores!$B15*100 -> 2491.1666 | ... Y15: =+'[1]1.1.1.1.1'!Y15/Deflactores!$B15*100 -> 669.22955 | Z15: =SUM(B15:Y15) -> 101460.4
A16: 1998 | B16: =+'[1]1.1.1.1.1'!B16/Deflactores!$B16*100 -> 32733.853 | C16: =+'[1]1.1.1.1.1'!C16/Deflactores!$B16*100 -> 39855.883 | D16: =+'[1]1.1.1.1.1'!D16/Deflactores!$B16*100 -> 487.6928 | E16: =+'[1]1.1.1.1.1'!E16/Deflactores!$B16*100 -> 8757.3461 | F16: =+'[1]1.1.1.1.1'!F16/Deflactores!$B16*100 -> 941.05508 | G16: =+'[1]1.1.1.1.1'!G16/Deflactores!$B16*100 -> 1561.2169 | H16: =+'[1]1.1.1.1.1'!H16/Deflactores!$B16*100 -> 789.29973 | I16: =+'[1]1.1.1.1.1'!I16/Deflactores!$B16*100 -> 2539.7195 | ... Y16: =+'[1]1.1.1.1.1'!Y16/Deflactores!$B16*100 -> 754.67809 | Z16: =SUM(B16:Y16) -> 114829.72
A17: 1999 | B17: =+'[1]1.1.1.1.1'!B17/Deflactores!$B17*100 -> 34510.697 | C17: =+'[1]1.1.1.1.1'!C17/Deflactores!$B17*100 -> 38723.708 | D17: =+'[1]1.1.1.1.1'!D17/Deflactores!$B17*100 -> 497.44152 | E17: =+'[1]1.1.1.1.1'!E17/Deflactores!$B17*100 -> 8316.0878 | F17: =+'[1]1.1.1.1.1'!F17/Deflactores!$B17*100 -> 890.60568 | G17: =+'[1]1.1.1.1.1'!G17/Deflactores!$B17*100 -> 1582.2285 | H17: =+'[1]1.1.1.1.1'!H17/Deflactores!$B17*100 -> 878.59124 | I17: =+'[1]1.1.1.1.1'!I17/Deflactores!$B17*100 -> 2566.7575 | ... Y17: =+'[1]1.1.1.1.1'!Y17/Deflactores!$B17*100 -> 730.57735 | Z17: =SUM(B17:Y17) -> 114244.37
A18: 2000 | B18: =+'[1]1.1.1.1.1'!B18/Deflactores!$B18*100 -> 35736.929 | C18: =+'[1]1.1.1.1.1'!C18/Deflactores!$B18*100 -> 38678.018 | D18: =+'[1]1.1.1.1.1'!D18/Deflactores!$B18*100 -> 482.68986 | E18: =+'[1]1.1.1.1.1'!E18/Deflactores!$B18*100 -> 7723.3759 | F18: =+'[1]1.1.1.1.1'!F18/Deflactores!$B18*100 -> 1029.748 | G18: =+'[1]1.1.1.1.1'!G18/Deflactores!$B18*100 -> 1544.9679 | H18: =+'[1]1.1.1.1.1'!H18/Deflactores!$B18*100 -> 1048.4589 | I18: =+'[1]1.1.1.1.1'!I18/Deflactores!$B18*100 -> 2321.6063 | ... Y18: =+'[1]1.1.1.1.1'!Y18/Deflactores!$B18*100 -> 755.43436 | Z18: =SUM(B18:Y18) -> 116415.2
A19: 2001 | B19: =+'[1]1.1.1.1.1'!B19/Deflactores!$B19*100 -> 33315.373 | C19: =+'[1]1.1.1.1.1'!C19/Deflactores!$B19*100 -> 34979.141 | D19: =+'[1]1.1.1.1.1'!D19/Deflactores!$B19*100 -> 489.88985 | E19: =+'[1]1.1.1.1.1'!E19/Deflactores!$B19*100 -> 7843.8098 | F19: =+'[1]1.1.1.1.1'!F19/Deflactores!$B19*100 -> 1042.3253 | G19: =+'[1]1.1.1.1.1'!G19/Deflactores!$B19*100 -> 1333.0845 | H19: =+'[1]1.1.1.1.1'!H19/Deflactores!$B19*100 -> 1075.0858 | I19: =+'[1]1.1.1.1.1'!I19/Deflactores!$B19*100 -> 2218.2715 | ... Y19: =+'[1]1.1.1.1.1'!Y19/Deflactores!$B19*100 -> 770.42287 | Z19: =SUM(B19:Y19) -> 109210.93
A20: 2002 | B20: =+'[1]1.1.1.1.1'!B20/Deflactores!$B20*100 -> 23111.713 | C20: =+'[1]1.1.1.1.1'!C20/Deflactores!$B20*100 -> 28074.817 | D20: =+'[1]1.1.1.1.1'!D20/Deflactores!$B20*100 -> 342.22634 | E20: =+'[1]1.1.1.1.1'!E20/Deflactores!$B20*100 -> 5789.9976 | F20: =+'[1]1.1.1.1.1'!F20/Deflactores!$B20*100 -> 784.5837 | G20: =+'[1]1.1.1.1.1'!G20/Deflactores!$B20*100 -> 1112.631 | H20: =+'[1]1.1.1.1.1'!H20/Deflactores!$B20*100 -> 1142.3517 | I20: =+'[1]1.1.1.1.1'!I20/Deflactores!$B20*100 -> 1641.5307 | ... Y20: =+'[1]1.1.1.1.1'!Y20/Deflactores!$B20*100 -> 575.42495 | Z20: =SUM(B20:Y20) -> 82776.004
A21: 2003 | B21: =+'[1]1.1.1.1.1'!B21/Deflactores!$B21*100 -> 25305.895 | C21: =+'[1]1.1.1.1.1'!C21/Deflactores!$B21*100 -> 34614.318 | D21: =+'[1]1.1.1.1.1'!D21/Deflactores!$B21*100 -> 467.24669 | E21: =+'[1]1.1.1.1.1'!E21/Deflactores!$B21*100 -> 6954.2275 | F21: =+'[1]1.1.1.1.1'!F21/Deflactores!$B21*100 -> 754.58443 | G21: =+'[1]1.1.1.1.1'!G21/Deflactores!$B21*100 -> 1310.4643 | H21: =+'[1]1.1.1.1.1'!H21/Deflactores!$B21*100 -> 1299.5696 | I21: =+'[1]1.1.1.1.1'!I21/Deflactores!$B21*100 -> 1785.3952 | ... Y21: =+'[1]1.1.1.1.1'!Y21/Deflactores!$B21*100 -> 744.42318 | Z21: =SUM(B21:Y21) -> 98960.113
... A48: 2030 | B48: =+'[1]1.1.1.1.1'!B48/Deflactores!$B48*100 -> #N/A | C48: =+'[1]1.1.1.1.1'!C48/Deflactores!$B48*100 -> #N/A | D48: =+'[1]1.1.1.1.1'!D48/Deflactores!$B48*100 -> #N/A | E48: =+'[1]1.1.1.1.1'!E48/Deflactores!$B48*100 -> #N/A | F48: =+'[1]1.1.1.1.1'!F48/Deflactores!$B48*100 -> #N/A | G48: =+'[1]1.1.1.1.1'!G48/Deflactores!$B48*100 -> #N/A | H48: =+'[1]1.1.1.1.1'!H48/Deflactores!$B48*100 -> #N/A | I48: =+'[1]1.1.1.1.1'!I48/Deflactores!$B48*100 -> #N/A | ... Y48: =+'[1]1.1.1.1.1'!Y48/Deflactores!$B48*100 -> #N/A | Z48: =SUM(B48:Y48) -> #N/A

Sheet 1.1.1.1.2
A2: Título | B2: Inmobiliario | N2: =B2 -> Inmobiliario
A3: Fuente | B3: Dirección Nacional de Asuntos Provinciales - Ministerio de Economía de la Nación | N3: =B3 -> Dirección Nacional de Asuntos Provinciales - Ministerio de Economía de la Nación
A5: VOLVER AL ÍNDICE | B5: Administración Pública No Financiera | N5: =B5 -> Administración Pública No Financiera
A7: Unidad de medida | B7: Millones de pesos constantes de 2016 | C7: Millones de pesos constantes de 2016 | D7: Millones de pesos constantes de 2016 | E7: Millones de pesos constantes de 2016 | F7: Millones de pesos constantes de 2016 | G7: Millones de pesos constantes de 2016 | H7: Millones de pesos constantes de 2016 | I7: Millones de pesos constantes de 2016 | J7: Millones de pesos constantes de 2016 | K7: Millones de pesos constantes de 2016 | L7: Millones de pesos constantes de 2016 | M7: Millones de pesos constantes de 2016 | N7: Millones de pesos constantes de 2016 | O7: Millones de pesos constantes de 2016 | P7: Millones de pesos constantes de 2016 | Q7: Millones de pesos constantes de 2016 | R7: Millones de pesos constantes de 2016 | S7: Millones de pesos constantes de 2016 | T7: Millones de pesos constantes de 2016 | U7: Millones de pesos constantes de 2016 | V7: Millones de pesos constantes de 2016 | W7: Millones de pesos constantes de 2016 | X7: Millones de pesos constantes de 2016 | Y7: Millones de pesos constantes de 2016 | Z7: Millones de pesos constantes de 2016
A8: CÓDIGO | B8: 1.1.1.1.2.1 | C8: 1.1.1.1.2.2 | D8: 1.1.1.1.2.3 | E8: 1.1.1.1.2.4 | F8: 1.1.1.1.2.5 | G8: 1.1.1.1.2.6 | H8: 1.1.1.1.2.7 | I8: 1.1.1.1.2.8 | J8: 1.1.1.1.2.9 | K8: 1.1.1.1.2.10 | L8: 1.1.1.1.2.11 | M8: 1.1.1.1.2.12 | N8: 1.1.1.1.2.13 | O8: 1.1.1.1.2.14 | P8: 1.1.1.1.2.15 | Q8: 1.1.1.1.2.16 | R8: 1.1.1.1.2.17 | S8: 1.1.1.1.2.18 | T8: 1.1.1.1.2.19 | U8: 1.1.1.1.2.20 | V8: 1.1.1.1.2.21 | W8: 1.1.1.1.2.22 | X8: 1.1.1.1.2.23 | Y8: 1.1.1.1.2.24 | Z8: 1.1.1.1.2.25
A9: Jurisdicción | B9: C.A.B.A. | C9: Buenos Aires | D9: Catamarca | E9: Córdoba | F9: Corrientes | G9: Chaco | H9: Chubut | I9: Entre Ríos | J9: Formosa | K9: Jujuy | L9: La Pampa | M9: La Rioja | N9: Mendoza | O9: Misiones | P9: Neuquén | Q9: Río Negro | R9: Salta | S9: San Juan | T9: San Luis | U9: Santa Cruz | V9: Santa Fe | W9: Santiago del Estero | X9: Tucumán | Y9: Tierra del Fuego | Z9: Total
A10: 1992 | B10: =+'[1]1.1.1.1.2'!B10/Deflactores!$B10*100 -> 7395.9988 | C10: =+'[1]1.1.1.1.2'!C10/Deflactores!$B10*100 -> 8844.5825 | D10: =+'[1]1.1.1.1.2'!D10/Deflactores!$B10*100 -> 32.062545 | E10: =+'[1]1.1.1.1.2'!E10/Deflactores!$B10*100 -> 3979.3607 | F10: =+'[1]1.1.1.1.2'!F10/Deflactores!$B10*100 -> 193.26503 | G10: =+'[1]1.1.1.1.2'!G10/Deflactores!$B10*100 -> 28.961253 | H10: =+'[1]1.1.1.1.2'!H10/Deflactores!$B10*100 -> 2.1077037 | I10: =+'[1]1.1.1.1.2'!I10/Deflactores!$B10*100 -> 831.77276 | ... Y10: =+'[1]1.1.1.1.2'!Y10/Deflactores!$B10*100 -> 1.266695 | Z10: =SUM(B10:Y10) -> 26568.457
A11: 1993 | B11: =+'[1]1.1.1.1.2'!B11/Deflactores!$B11*100 -> 6810.7441 | C11: =+'[1]1.1.1.1.2'!C11/Deflactores!$B11*100 -> 9524.8092 | D11: =+'[1]1.1.1.1.2'!D11/Deflactores!$B11*100 -> 39.939287 | E11: =+'[1]1.1.1.1.2'!E11/Deflactores!$B11*100 -> 3792.6706 | F11: =+'[1]1.1.1.1.2'!F11/Deflactores!$B11*100 -> 208.45659 | G11: =+'[1]1.1.1.1.2'!G11/Deflactores!$B11*100 -> 27.51482 | H11: =+'[1]1.1.1.1.2'!H11/Deflactores!$B11*100 -> 2.021001 | I11: =+'[1]1.1.1.1.2'!I11/Deflactores!$B11*100 -> 995.82924 | ... Y11: =+'[1]1.1.1.1.2'!Y11/Deflactores!$B11*100 -> 1.1076777 | Z11: =SUM(B11:Y11) -> 26515.719
A12: 1994 | B12: =+'[1]1.1.1.1.2'!B12/Deflactores!$B12*100 -> 7216.1193 | C12: =+'[1]1.1.1.1.2'!C12/Deflactores!$B12*100 -> 9670.0535 | D12: =+'[1]1.1.1.1.2'!D12/Deflactores!$B12*100 -> 59.661606 | E12: =+'[1]1.1.1.1.2'!E12/Deflactores!$B12*100 -> 4036.9759 | F12: =+'[1]1.1.1.1.2'!F12/Deflactores!$B12*100 -> 175.65261 | G12: =+'[1]1.1.1.1.2'!G12/Deflactores!$B12*100 -> 47.464262 | H12: =+'[1]1.1.1.1.2'!H12/Deflactores!$B12*100 -> 1.8739542 | I12: =+'[1]1.1.1.1.2'!I12/Deflactores!$B12*100 -> 1179.5691 | ... Y12: =+'[1]1.1.1.1.2'!Y12/Deflactores!$B12*100 -> 1.5657312 | Z12: =SUM(B12:Y12) -> 28592.317
A13: 1995 | B13: =+'[1]1.1.1.1.2'!B13/Deflactores!$B13*100 -> 6700.1066 | C13: =+'[1]1.1.1.1.2'!C13/Deflactores!$B13*100 -> 8746.0671 | D13: =+'[1]1.1.1.1.2'!D13/Deflactores!$B13*100 -> 38.56264 | E13: =+'[1]1.1.1.1.2'!E13/Deflactores!$B13*100 -> 3970.8792 | F13: =+'[1]1.1.1.1.2'!F13/Deflactores!$B13*100 -> 143.65853 | G13: =+'[1]1.1.1.1.2'!G13/Deflactores!$B13*100 -> 51.168127 | H13: =+'[1]1.1.1.1.2'!H13/Deflactores!$B13*100 -> 10.671881 | I13: =+'[1]1.1.1.1.2'!I13/Deflactores!$B13*100 -> 1232.0944 | ... Y13: =+'[1]1.1.1.1.2'!Y13/Deflactores!$B13*100 -> 1.1971434 | Z13: =SUM(B13:Y13) -> 25739.244
A14: 1996 | B14: =+'[1]1.1.1.1.2'!B14/Deflactores!$B14*100 -> 6400.4125 | C14: =+'[1]1.1.1.1.2'!C14/Deflactores!$B14*100 -> 9677.4962 | D14: =+'[1]1.1.1.1.2'!D14/Deflactores!$B14*100 -> 68.494437 | E14: =+'[1]1.1.1.1.2'!E14/Deflactores!$B14*100 -> 4011.8254 | F14: =+'[1]1.1.1.1.2'!F14/Deflactores!$B14*100 -> 145.00352 | G14: =+'[1]1.1.1.1.2'!G14/Deflactores!$B14*100 -> 50.479241 | H14: =+'[1]1.1.1.1.2'!H14/Deflactores!$B14*100 -> 11.356714 | I14: =+'[1]1.1.1.1.2'!I14/Deflactores!$B14*100 -> 1080.9695 | ... Y14: =+'[1]1.1.1.1.2'!Y14/Deflactores!$B14*100 -> 0.95856274 | Z14: =SUM(B14:Y14) -> 26578.576
A15: 1997 | B15: =+'[1]1.1.1.1.2'!B15/Deflactores!$B15*100 -> 7595.6066 | C15: =+'[1]1.1.1.1.2'!C15/Deflactores!$B15*100 -> 11264.031 | D15: =+'[1]1.1.1.1.2'!D15/Deflactores!$B15*100 -> 59.25468 | E15: =+'[1]1.1.1.1.2'!E15/Deflactores!$B15*100 -> 4228.146 | F15: =+'[1]1.1.1.1.2'!F15/Deflactores!$B15*100 -> 173.71568 | G15: =+'[1]1.1.1.1.2'!G15/Deflactores!$B15*100 -> 45.065069 | H15: =+'[1]1.1.1.1.2'!H15/Deflactores!$B15*100 -> 1.1957889 | I15: =+'[1]1.1.1.1.2'!I15/Deflactores!$B15*100 -> 1066.5275 | ... Y15: =+'[1]1.1.1.1.2'!Y15/Deflactores!$B15*100 -> 2.3728408 | Z15: =SUM(B15:Y15) -> 30591.625
A16: 1998 | B16: =+'[1]1.1.1.1.2'!B16/Deflactores!$B16*100 -> 8418.1435 | C16: =+'[1]1.1.1.1.2'!C16/Deflactores!$B16*100 -> 11517.492 | D16: =+'[1]1.1.1.1.2'!D16/Deflactores!$B16*100 -> 66.834354 | E16: =+'[1]1.1.1.1.2'!E16/Deflactores!$B16*100 -> 5009.813 | F16: =+'[1]1.1.1.1.2'!F16/Deflactores!$B16*100 -> 131.08435 | G16: =+'[1]1.1.1.1.2'!G16/Deflactores!$B16*100 -> 38.137026 | H16: =+'[1]1.1.1.1.2'!H16/Deflactores!$B16*100 -> 1.8862571 | I16: =+'[1]1.1.1.1.2'!I16/Deflactores!$B16*100 -> 1171.8539 | ... Y16: =+'[1]1.1.1.1.2'!Y16/Deflactores!$B16*100 -> 1.1743098 | Z16: =SUM(B16:Y16) -> 32968.938
A17: 1999 | B17: =+'[1]1.1.1.1.2'!B17/Deflactores!$B17*100 -> 8754.916 | C17: =+'[1]1.1.1.1.2'!C17/Deflactores!$B17*100 -> 10818.038 | D17: =+'[1]1.1.1.1.2'!D17/Deflactores!$B17*100 -> 64.249424 | E17: =+'[1]1.1.1.1.2'!E17/Deflactores!$B17*100 -> 5023.1999 | F17: =+'[1]1.1.1.1.2'!F17/Deflactores!$B17*100 -> 123.2932 | G17: =+'[1]1.1.1.1.2'!G17/Deflactores!$B17*100 -> 35.847577 | H17: =+'[1]1.1.1.1.2'!H17/Deflactores!$B17*100 -> 0.98742267 | I17: =+'[1]1.1.1.1.2'!I17/Deflactores!$B17*100 -> 1140.9036 | ... Y17: =+'[1]1.1.1.1.2'!Y17/Deflactores!$B17*100 -> 1.5338161 | Z17: =SUM(B17:Y17) -> 32523.963
A18: 2000 | B18: =+'[1]1.1.1.1.2'!B18/Deflactores!$B18*100 -> 9644.6753 | C18: =+'[1]1.1.1.1.2'!C18/Deflactores!$B18*100 -> 11930.402 | D18: =+'[1]1.1.1.1.2'!D18/Deflactores!$B18*100 -> 83.881914 | E18: =+'[1]1.1.1.1.2'!E18/Deflactores!$B18*100 -> 3896.2348 | F18: =+'[1]1.1.1.1.2'!F18/Deflactores!$B18*100 -> 223.96061 | G18: =+'[1]1.1.1.1.2'!G18/Deflactores!$B18*100 -> 31.709642 | H18: =+'[1]1.1.1.1.2'!H18/Deflactores!$B18*100 -> 0.52703111 | I18: =+'[1]1.1.1.1.2'!I18/Deflactores!$B18*100 -> 1053.8248 | ... Y18: =+'[1]1.1.1.1.2'!Y18/Deflactores!$B18*100 -> 1.1471685 | Z18: =SUM(B18:Y18) -> 34452.501
A19: 2001 | B19: =+'[1]1.1.1.1.2'!B19/Deflactores!$B19*100 -> 9570.0283 | C19: =+'[1]1.1.1.1.2'!C19/Deflactores!$B19*100 -> 10849.243 | D19: =+'[1]1.1.1.1.2'!D19/Deflactores!$B19*100 -> 81.248817 | E19: =+'[1]1.1.1.1.2'!E19/Deflactores!$B19*100 -> 3388.1337 | F19: =+'[1]1.1.1.1.2'!F19/Deflactores!$B19*100 -> 243.51389 | G19: =+'[1]1.1.1.1.2'!G19/Deflactores!$B19*100 -> 33.010432 | H19: =+'[1]1.1.1.1.2'!H19/Deflactores!$B19*100 -> 0.055261474 | I19: =+'[1]1.1.1.1.2'!I19/Deflactores!$B19*100 -> 1167.8087 | ... Y19: =+'[1]1.1.1.1.2'!Y19/Deflactores!$B19*100 -> 1.0154052 | Z19: =SUM(B19:Y19) -> 32241.068
A20: 2002 | B20: =+'[1]1.1.1.1.2'!B20/Deflactores!$B20*100 -> 6241.1239 | C20: =+'[1]1.1.1.1.2'!C20/Deflactores!$B20*100 -> 8034.4744 | D20: =+'[1]1.1.1.1.2'!D20/Deflactores!$B20*100 -> 46.816044 | E20: =+'[1]1.1.1.1.2'!E20/Deflactores!$B20*100 -> 2316.6922 | F20: =+'[1]1.1.1.1.2'!F20/Deflactores!$B20*100 -> 143.45754 | G20: =+'[1]1.1.1.1.2'!G20/Deflactores!$B20*100 -> 32.23349 | H20: =+'[1]1.1.1.1.2'!H20/Deflactores!$B20*100 -> 0.26671628 | I20: =+'[1]1.1.1.1.2'!I20/Deflactores!$B20*100 -> 841.81177 | ... Y20: =+'[1]1.1.1.1.2'!Y20/Deflactores!$B20*100 -> 1.2264102 | Z20: =SUM(B20:Y20) -> 22735.209
A21: 2003 | B21: =+'[1]1.1.1.1.2'!B21/Deflactores!$B21*100 -> 6364.1897 | C21: =+'[1]1.1.1.1.2'!C21/Deflactores!$B21*100 -> 8976.1662 | D21: =+'[1]1.1.1.1.2'!D21/Deflactores!$B21*100 -> 63.01461 | E21: =+'[1]1.1.1.1.2'!E21/Deflactores!$B21*100 -> 3105.3382 | F21: =+'[1]1.1.1.1.2'!F21/Deflactores!$B21*100 -> 311.67895 | G21: =+'[1]1.1.1.1.2'!G21/Deflactores!$B21*100 -> 47.498327 | H21: =+'[1]1.1.1.1.2'!H21/Deflactores!$B21*100 -> 0.25656698 | I21: =+'[1]1.1.1.1.2'!I21/Deflactores!$B21*100 -> 940.51803 | ... Y21: =+'[1]1.1.1.1.2'!Y21/Deflactores!$B21*100 -> 1.0030855 | Z21: =SUM(B21:Y21) -> 24736.476
... A48: 2030 | B48: =+'[1]1.1.1.1.2'!B48/Deflactores!$B48*100 -> #N/A | C48: =+'[1]1.1.1.1.2'!C48/Deflactores!$B48*100 -> #N/A | D48: =+'[1]1.1.1.1.2'!D48/Deflactores!$B48*100 -> #N/A | E48: =+'[1]1.1.1.1.2'!E48/Deflactores!$B48*100 -> #N/A | F48: =+'[1]1.1.1.1.2'!F48/Deflactores!$B48*100 -> #N/A | G48: =+'[1]1.1.1.1.2'!G48/Deflactores!$B48*100 -> #N/A | H48: =+'[1]1.1.1.1.2'!H48/Deflactores!$B48*100 -> #N/A | I48: =+'[1]1.1.1.1.2'!I48/Deflactores!$B48*100 -> #N/A | ... Y48: =+'[1]1.1.1.1.2'!Y48/Deflactores!$B48*100 -> #N/A | Z48: =SUM(B48:Y48) -> #N/A
B80: 291200 | C80: 460419 | D80: 640.00283 | E80: 88328.005 | F80: 10014.003 | G80: 3660.0062 | H80: 915.99807 | I80: 36823.996 | J80: 1266.0034 | K80: 3893.9947 | L80: 13114.303 | M80: 916.99458 | N80: 25834 | O80: 6133.9982 | P80: 4493.9965 | Q80: 13200.999 | R80: 10509.998 | S80: 3882.9947 | T80: 6682.9991 | U80: 47.998616 | V80: 110239.99 | W80: 6022.504 | X80: 19407.002 | Y80: 106.99718 | Z80: 1117755.8
B81: 1248700 | C81: 2476751 | D81: 3103.012 | E81: 512561.02 | F81: 29578.973 | G81: 9183.0142 | H81: 10990.02 | I81: 200628.02 | J81: 5240.9783 | K81: 21730.994 | L81: 56129.996 | M81: 2679.9824 | N81: 130581.97 | O81: 15327.006 | P81: 26476.022 | Q81: 56279.999 | R81: 25946.975 | S81: 8722.9734 | T81: 22362.021 | U81: 3539.0108 | V81: 620087 | W81: 20659.014 | X81: 36847.985 | Y81: 1766.9972 | Z81: 5545873.9
B82: 41753.594 | C82: 85627.5 | D82: 39.69864 | E82: 11657.176 | F82: 461.56611 | G82: 158.05967 | H82: 214.02916 | I82: 5617.2554 | J82: 64.881091 | K82: 700.7323 | L82: 1553.5337 | M82: 29.220231 | N82: 3657.2578 | O82: 468.80356 | P82: 379.14462 | Q82: 1203.729 | R82: 301.94582 | S82: 252.80505 | T82: 789.99902 | U82: 4.3412324 | V82: 10200.172 | W82: 242.96864 | X82: 607.7904 | Y82: 4.7953794 | Z82: 165991
B83: 874366.15 | C83: 1894519.5 | D83: 1923.9747 | E83: 440999.66 | F83: 26329.274 | G83: 7816.2793 | H83: 1257.8673 | I83: 160748.94 | J83: 4446.4154 | K83: 15002.838 | L83: 52444.984 | M83: 2294.016 | N83: 84477.795 | O83: 20408.364 | P83: 10537.008 | Q83: 26212.991 | R83: 8992.5545 | S83: 13495.186 | T83: 21639.924 | U83: 803.00497 | V83: 366101.92 | W83: 8651.8217 | X83: 9415.0035 | Y83: 178.9975 | Z83: 4053064.5
B84: 3219470.4 | C84: 4120000 | D84: 17240 | E84: 1164000 | F84: 69606 | G84: 13882.098 | H84: 914.37 | I84: 277669.03 | J84: 13603.646 | K84: 56650 | L84: 132356 | M84: 9139 | N84: 259000 | O84: 48541.5 | P84: 34284 | Q84: 64180 | R84: 21264 | S84: 43684 | T84: 72061 | U84: 520.87 | V84: 1164412.3 | W84: 28579 | X84: 111914.28 | Y84: 1642.54 | Z84: 10944614
B85: 385361.85 | C85: 460839 | D85: 1670.5919 | E85: 207341 | F85: 10069.9 | G85: 1509 | H85: 109.82063 | I85: 43338.774 | J85: 1650 | K85: 6677 | L85: 12765.97 | M85: 1903.1 | N85: 31213.503 | O85: 11735 | P85: 8455 | Q85: 10774 | R85: 4294 | S85: 5493.6 | T85: 7510 | U85: 66 | V85: 151768 | W85: 4634.8 | X85: 15079.621 | Y85: 66 | Z85: 1384325.5
B86: 383369.55 | C86: 536141.39 | D86: 2248.1381 | E86: 213485.4 | F86: 11733.8 | G86: 1548.776 | H86: 113.75806 | I86: 56054.168 | J86: 1561.0386 | K86: 9659.8 | L86: 13185.713 | M86: 2630.924 | N86: 38096.579 | O86: 9906.4 | P86: 13012.583 | Q86: 14927 | R86: 3601.2677 | S86: 5591.9 | T86: 11060 | U86: 118.1 | V86: 149040.84 | W86: 5815.6846 | X86: 9576.5 | Y86: 62.35 | Z86: 1492541.7
B87: 416265.5 | C87: 557821.94 | D87: 3441.609 | E87: 232875 | F87: 10132.607 | G87: 2738 | H87: 108.1 | I87: 68044.041 | J87: 1064.422 | K87: 10207.648 | L87: 14745.873 | M87: 1957.053 | N87: 55951.32 | O87: 11776.9 | P87: 10129 | Q87: 17926 | R87: 4372.08 | S87: 5590.621 | T87: 16330 | U87: 104.428 | V87: 181402.43 | W87: 7520.3878 | X87: 18766.996 | Y87: 90.315 | Z87: 1649362.3
B88: 406939.33 | C88: 531203.29 | D88: 2342.1484 | E88: 241176.3 | F88: 8725.279 | G88: 3107.761 | H88: 648.168 | I88: 74832.787 | J88: 708.331 | K88: 8499.952 | L88: 14324.392 | M88: 1439.559 | N88: 34884.512 | O88: 11018.2 | P88: 11178.868 | Q88: 14058 | R88: 4042.081 | S88: 6070.671 | T88: 14842.585 | U88: 18.494 | V88: 154573 | W88: 6980.7046 | X88: 11617.928 | Y88: 72.714 | Z88: 1563305.1
B89: 391811.81 | C89: 592423.9 | D89: 4193 | E89: 245590.51 | F89: 8876.632 | G89: 3090.1654 | H89: 695.22086 | I89: 66173.327 | J89: 799.1757 | K89: 9433.0566 | L89: 14764.231 | M89: 2282.1181 | N89: 34499.532 | O89: 10933.727 | P89: 11658.344 | Q89: 16820.38 | R89: 4674.3498 | S89: 8727.979 | T89: 16025.087 | U89: 17.049232 | V89: 154964.43 | W89: 8232.803 | X89: 20305.889 | Y89: 58.68 | Z89: 1627051.4
B90: 449973.06 | C90: 667295 | D90: 3510.32 | E90: 250480.56 | F90: 10291.126 | G90: 2669.71 | H90: 70.843 | I90: 63182.404 | J90: 939.368 | K90: 8220.984 | L90: 15837.737 | M90: 3307.6282 | N90: 47970 | O90: 12510.6 | P90: 12102 | Q90: 21005.933 | R90: 6844.45 | S90: 5835 | T90: 13851.65 | U90: 15.349 | V90: 188429.71 | W90: 8768.341 | X90: 19033.098 | Y90: 140.572 | Z90: 1812285.4
B91: 480295.41 | C91: 657128.1 | D91: 3813.216 | E91: 285833.83 | F91: 7478.994 | G91: 2175.9 | H91: 107.619 | I91: 66859.876 | J91: 1024.6543 | K91: 7801.674 | L91: 18388.831 | M91: 1370.6908 | N91: 52886.925 | O91: 13497.937 | P91: 13587.707 | Q91: 22737.5 | R91: 6297.5008 | S91: 8066.458 | T91: 17801.36 | U91: 13.58496 | V91: 186139.5 | W91: 8407.9978 | X91: 19253.568 | Y91: 67 | Z91: 1881035.8
... B113: 21005215 | C113: 35385604 | D113: 125567.64 | E113: 15328000 | F113: 0 | G113: 94408.845 | H113: 0 | I113: 4567781.2 | J113: 51496.176 | K113: 387941.94 | L113: 0 | M113: 41829.763 | N113: 1826827.9 | O113: 0 | P113: 1102355 | Q113: 981257.68 | R113: 180586.3 | S113: 470913.47 | T113: 449922.25 | U113: 2297.0691 | V113: 5119160 | W113: 0 | X113: 753208.09 | Y113: 234.94223 | Z113: 21005215

Sheet 1.1.1.1.3
A2: Título | B2: Sellos | N2: =B2 -> Sellos
A3: Fuente | B3: Dirección Nacional de Asuntos Provinciales - Ministerio de Economía de la Nación | N3: =B3 -> Dirección Nacional de Asuntos Provinciales - Ministerio de Economía de la Nación
A5: VOLVER AL ÍNDICE | B5: Administración Pública No Financiera | N5: =B5 -> Administración Pública No Financiera
A7: Unidad de medida | B7: Millones de pesos constantes de 2016 | C7: Millones de pesos constantes de 2016 | D7: Millones de pesos constantes de 2016 | E7: Millones de pesos constantes de 2016 | F7: Millones de pesos constantes de 2016 | G7: Millones de pesos constantes de 2016 | H7: Millones de pesos constantes de 2016 | I7: Millones de pesos constantes de 2016 | J7: Millones de pesos constantes de 2016 | K7: Millones de pesos constantes de 2016 | L7: Millones de pesos constantes de 2016 | M7: Millones de pesos constantes de 2016 | N7: Millones de pesos constantes de 2016 | O7: Millones de pesos constantes de 2016 | P7: Millones de pesos constantes de 2016 | Q7: Millones de pesos constantes de 2016 | R7: Millones de pesos constantes de 2016 | S7: Millones de pesos constantes de 2016 | T7: Millones de pesos constantes de 2016 | U7: Millones de pesos constantes de 2016 | V7: Millones de pesos constantes de 2016 | W7: Millones de pesos constantes de 2016 | X7: Millones de pesos constantes de 2016 | Y7: Millones de pesos constantes de 2016 | Z7: Millones de pesos constantes de 2016
A8: CÓDIGO | B8: 1.1.1.1.3.1 | C8: 1.1.1.1.3.2 | D8: 1.1.1.1.3.3 | E8: 1.1.1.1.3.4 | F8: 1.1.1.1.3.5 | G8: 1.1.1.1.3.6 | H8: 1.1.1.1.3.7 | I8: 1.1.1.1.3.8 | J8: 1.1.1.1.3.9 | K8: 1.1.1.1.3.10 | L8: 1.1.1.1.3.11 | M8: 1.1.1.1.3.12 | N8: 1.1.1.1.3.13 | O8: 1.1.1.1.3.14 | P8: 1.1.1.1.3.15 | Q8: 1.1.1.1.3.16 | R8: 1.1.1.1.3.17 | S8: 1.1.1.1.3.18 | T8: 1.1.1.1.3.19 | U8: 1.1.1.1.3.20 | V8: 1.1.1.1.3.21 | W8: 1.1.1.1.3.22 | X8: 1.1.1.1.3.23 | Y8: 1.1.1.1.3.24 | Z8: 1.1.1.1.3.25
A9: Jurisdicción | B9: C.A.B.A. | C9: Buenos Aires | D9: Catamarca | E9: Córdoba | F9: Corrientes | G9: Chaco | H9: Chubut | I9: Entre Ríos | J9: Formosa | K9: Jujuy | L9: La Pampa | M9: La Rioja | N9: Mendoza | O9: Misiones | P9: Neuquén | Q9: Río Negro | R9: Salta | S9: San Juan | T9: San Luis | U9: Santa Cruz | V9: Santa Fe | W9: Santiago del Estero | X9: Tucumán | Y9: Tierra del Fuego | Z9: Total
A10: 1992 | B10: =+'[1]1.1.1.1.3'!B10/Deflactores!$B10*100 -> 0 | C10: =+'[1]1.1.1.1.3'!C10/Deflactores!$B10*100 -> 6189.3979 | D10: =+'[1]1.1.1.1.3'!D10/Deflactores!$B10*100 -> 52.160772 | E10: =+'[1]1.1.1.1.3'!E10/Deflactores!$B10*100 -> 1371.9458 | F10: =+'[1]1.1.1.1.3'!F10/Deflactores!$B10*100 -> 170.42037 | G10: =+'[1]1.1.1.1.3'!G10/Deflactores!$B10*100 -> 151.08984 | H10: =+'[1]1.1.1.1.3'!H10/Deflactores!$B10*100 -> 188.26216 | I10: =+'[1]1.1.1.1.3'!I10/Deflactores!$B10*100 -> 503.44427 | ... Y10: =+'[1]1.1.1.1.3'!Y10/Deflactores!$B10*100 -> 81.951326 | Z10: =SUM(B10:Y10) -> 14966.337
A11: 1993 | B11: =+'[1]1.1.1.1.3'!B11/Deflactores!$B11*100 -> 0 | C11: =+'[1]1.1.1.1.3'!C11/Deflactores!$B11*100 -> 6654.4001 | D11: =+'[1]1.1.1.1.3'!D11/Deflactores!$B11*100 -> 64.974756 | E11: =+'[1]1.1.1.1.3'!E11/Deflactores!$B11*100 -> 1482.4796 | F11: =+'[1]1.1.1.1.3'!F11/Deflactores!$B11*100 -> 204.18222 | G11: =+'[1]1.1.1.1.3'!G11/Deflactores!$B11*100 -> 177.04296 | H11: =+'[1]1.1.1.1.3'!H11/Deflactores!$B11*100 -> 206.69035 | I11: =+'[1]1.1.1.1.3'!I11/Deflactores!$B11*100 -> 602.74206 | ... Y11: =+'[1]1.1.1.1.3'!Y11/Deflactores!$B11*100 -> 88.652411 | Z11: =SUM(B11:Y11) -> 16807.211
A12: 1994 | B12: =+'[1]1.1.1.1.3'!B12/Deflactores!$B12*100 -> 0 | C12: =+'[1]1.1.1.1.3'!C12/Deflactores!$B12*100 -> 7321.1581 | D12: =+'[1]1.1.1.1.3'!D12/Deflactores!$B12*100 -> 84.807437 | E12: =+'[1]1.1.1.1.3'!E12/Deflactores!$B12*100 -> 1552.227 | F12: =+'[1]1.1.1.1.3'!F12/Deflactores!$B12*100 -> 225.52441 | G12: =+'[1]1.1.1.1.3'!G12/Deflactores!$B12*100 -> 164.07414 | H12: =+'[1]1.1.1.1.3'!H12/Deflactores!$B12*100 -> 217.85333 | I12: =+'[1]1.1.1.1.3'!I12/Deflactores!$B12*100 -> 713.95368 | ... Y12: =+'[1]1.1.1.1.3'!Y12/Deflactores!$B12*100 -> 57.0639 | Z12: =SUM(B12:Y12) -> 17688.107
A13: 1995 | B13: =+'[1]1.1.1.1.3'!B13/Deflactores!$B13*100 -> 0 | C13: =+'[1]1.1.1.1.3'!C13/Deflactores!$B13*100 -> 6621.6118 | D13: =+'[1]1.1.1.1.3'!D13/Deflactores!$B13*100 -> 55.413533 | E13: =+'[1]1.1.1.1.3'!E13/Deflactores!$B13*100 -> 1552.1377 | F13: =+'[1]1.1.1.1.3'!F13/Deflactores!$B13*100 -> 145.37711 | G13: =+'[1]1.1.1.1.3'!G13/Deflactores!$B13*100 -> 157.14883 | H13: =+'[1]1.1.1.1.3'!H13/Deflactores!$B13*100 -> 202.06188 | I13: =+'[1]1.1.1.1.3'!I13/Deflactores!$B13*100 -> 566.79762 | ... Y13: =+'[1]1.1.1.1.3'!Y13/Deflactores!$B13*100 -> 14.462533 | Z13: =SUM(B13:Y13) -> 14950.411
A14: 1996 | B14: =+'[1]1.1.1.1.3'!B14/Deflactores!$B14*100 -> 0 | C14: =+'[1]1.1.1.1.3'!C14/Deflactores!$B14*100 -> 7326.7931 | D14: =+'[1]1.1.1.1.3'!D14/Deflactores!$B14*100 -> 55.965166 | E14: =+'[1]1.1.1.1.3'!E14/Deflactores!$B14*100 -> 1568.1428 | F14: =+'[1]1.1.1.1.3'!F14/Deflactores!$B14*100 -> 170.96509 | G14: =+'[1]1.1.1.1.3'!G14/Deflactores!$B14*100 -> 155.03282 | H14: =+'[1]1.1.1.1.3'!H14/Deflactores!$B14*100 -> 215.02941 | I14: =+'[1]1.1.1.1.3'!I14/Deflactores!$B14*100 -> 438.13946 | ... Y14: =+'[1]1.1.1.1.3'!Y14/Deflactores!$B14*100 -> 10.59679 | Z14: =SUM(B14:Y14) -> 15718.805
A15: 1997 | B15: =+'[1]1.1.1.1.3'!B15/Deflactores!$B15*100 -> 0 | C15: =+'[1]1.1.1.1.3'!C15/Deflactores!$B15*100 -> 7070.4983 | D15: =+'[1]1.1.1.1.3'!D15/Deflactores!$B15*100 -> 60.614207 | E15: =+'[1]1.1.1.1.3'!E15/Deflactores!$B15*100 -> 1617.7182 | F15: =+'[1]1.1.1.1.3'!F15/Deflactores!$B15*100 -> 174.28521 | G15: =+'[1]1.1.1.1.3'!G15/Deflactores!$B15*100 -> 128.00207 | H15: =+'[1]1.1.1.1.3'!H15/Deflactores!$B15*100 -> 204.12643 | I15: =+'[1]1.1.1.1.3'!I15/Deflactores!$B15*100 -> 497.01941 | ... Y15: =+'[1]1.1.1.1.3'!Y15/Deflactores!$B15*100 -> 23.323284 | Z15: =SUM(B15:Y15) -> 15619.685
A16: 1998 | B16: =+'[1]1.1.1.1.3'!B16/Deflactores!$B16*100 -> 0 | C16: =+'[1]1.1.1.1.3'!C16/Deflactores!$B16*100 -> 7483.2678 | D16: =+'[1]1.1.1.1.3'!D16/Deflactores!$B16*100 -> 93.057218 | E16: =+'[1]1.1.1.1.3'!E16/Deflactores!$B16*100 -> 1495.6395 | F16: =+'[1]1.1.1.1.3'!F16/Deflactores!$B16*100 -> 255.63813 | G16: =+'[1]1.1.1.1.3'!G16/Deflactores!$B16*100 -> 133.01775 | H16: =+'[1]1.1.1.1.3'!H16/Deflactores!$B16*100 -> 230.55295 | I16: =+'[1]1.1.1.1.3'!I16/Deflactores!$B16*100 -> 554.29982 | ... Y16: =+'[1]1.1.1.1.3'!Y16/Deflactores!$B16*100 -> 22.364468 | Z16: =SUM(B16:Y16) -> 17297.253
A17: 1999 | B17: =+'[1]1.1.1.1.3'!B17/Deflactores!$B17*100 -> 0 | C17: =+'[1]1.1.1.1.3'!C17/Deflactores!$B17*100 -> 6912.7914 | D17: =+'[1]1.1.1.1.3'!D17/Deflactores!$B17*100 -> 92.814073 | E17: =+'[1]1.1.1.1.3'!E17/Deflactores!$B17*100 -> 1369.4651 | F17: =+'[1]1.1.1.1.3'!F17/Deflactores!$B17*100 -> 222.22351 | G17: =+'[1]1.1.1.1.3'!G17/Deflactores!$B17*100 -> 121.80841 | H17: =+'[1]1.1.1.1.3'!H17/Deflactores!$B17*100 -> 209.40495 | I17: =+'[1]1.1.1.1.3'!I17/Deflactores!$B17*100 -> 508.06683 | ... Y17: =+'[1]1.1.1.1.3'!Y17/Deflactores!$B17*100 -> 82.542535 | Z17: =SUM(B17:Y17) -> 16762.091
A18: 2000 | B18: =+'[1]1.1.1.1.3'!B18/Deflactores!$B18*100 -> 0 | C18: =+'[1]1.1.1.1.3'!C18/Deflactores!$B18*100 -> 5997.8229 | D18: =+'[1]1.1.1.1.3'!D18/Deflactores!$B18*100 -> 94.360084 | E18: =+'[1]1.1.1.1.3'!E18/Deflactores!$B18*100 -> 1364.6943 | F18: =+'[1]1.1.1.1.3'!F18/Deflactores!$B18*100 -> 228.73817 | G18: =+'[1]1.1.1.1.3'!G18/Deflactores!$B18*100 -> 107.46065 | H18: =+'[1]1.1.1.1.3'!H18/Deflactores!$B18*100 -> 228.62792 | I18: =+'[1]1.1.1.1.3'!I18/Deflactores!$B18*100 -> 486.35604 | ... Y18: =+'[1]1.1.1.1.3'!Y18/Deflactores!$B18*100 -> 74.295583 | Z18: =SUM(B18:Y18) -> 15311.026
A19: 2001 | B19: =+'[1]1.1.1.1.3'!B19/Deflactores!$B19*100 -> 0 | C19: =+'[1]1.1.1.1.3'!C19/Deflactores!$B19*100 -> 5914.4126 | D19: =+'[1]1.1.1.1.3'!D19/Deflactores!$B19*100 -> 76.891948 | E19: =+'[1]1.1.1.1.3'!E19/Deflactores!$B19*100 -> 1021.2397 | F19: =+'[1]1.1.1.1.3'!F19/Deflactores!$B19*100 -> 257.0426 | G19: =+'[1]1.1.1.1.3'!G19/Deflactores!$B19*100 -> 125.50018 | H19: =+'[1]1.1.1.1.3'!H19/Deflactores!$B19*100 -> 264.77647 | I19: =+'[1]1.1.1.1.3'!I19/Deflactores!$B19*100 -> 539.73218 | ... Y19: =+'[1]1.1.1.1.3'!Y19/Deflactores!$B19*100 -> 128.3726 | Z19: =SUM(B19:Y19) -> 14786.397
A20: 2002 | B20: =+'[1]1.1.1.1.3'!B20/Deflactores!$B20*100 -> 0 | C20: =+'[1]1.1.1.1.3'!C20/Deflactores!$B20*100 -> 3978.3944 | D20: =+'[1]1.1.1.1.3'!D20/Deflactores!$B20*100 -> 49.113494 | E20: =+'[1]1.1.1.1.3'!E20/Deflactores!$B20*100 -> 633.56102 | F20: =+'[1]1.1.1.1.3'!F20/Deflactores!$B20*100 -> 112.69631 | G20: =+'[1]1.1.1.1.3'!G20/Deflactores!$B20*100 -> 85.727539 | H20: =+'[1]1.1.1.1.3'!H20/Deflactores!$B20*100 -> 148.75242 | I20: =+'[1]1.1.1.1.3'!I20/Deflactores!$B20*100 -> 271.28048 | ... Y20: =+'[1]1.1.1.1.3'!Y20/Deflactores!$B20*100 -> 35.465591 | Z20: =SUM(B20:Y20) -> 9587.9076
A21: 2003 | B21: =+'[1]1.1.1.1.3'!B21/Deflactores!$B21*100 -> 238.298 | C21: =+'[1]1.1.1.1.3'!C21/Deflactores!$B21*100 -> 4740.3034 | D21: =+'[1]1.1.1.1.3'!D21/Deflactores!$B21*100 -> 66.521397 | E21: =+'[1]1.1.1.1.3'!E21/Deflactores!$B21*100 -> 628.65574 | F21: =+'[1]1.1.1.1.3'!F21/Deflactores!$B21*100 -> 0 | G21: =+'[1]1.1.1.1.3'!G21/Deflactores!$B21*100 -> 110.44083 | H21: =+'[1]1.1.1.1.3'!H21/Deflactores!$B21*100 -> 176.16967 | I21: =+'[1]1.1.1.1.3'!I21/Deflactores!$B21*100 -> 292.92637 | ... Y21: =+'[1]1.1.1.1.3'!Y21/Deflactores!$B21*100 -> 63.796237 | Z21: =SUM(B21:Y21) -> 11407.772
... A48: 2030 | B48: =+'[1]1.1.1.1.3'!B48/Deflactores!$B48*100 -> #N/A | C48: =+'[1]1.1.1.1.3'!C48/Deflactores!$B48*100 -> #N/A | D48: =+'[1]1.1.1.1.3'!D48/Deflactores!$B48*100 -> #N/A | E48: =+'[1]1.1.1.1.3'!E48/Deflactores!$B48*100 -> #N/A | F48: =+'[1]1.1.1.1.3'!F48/Deflactores!$B48*100 -> #N/A | G48: =+'[1]1.1.1.1.3'!G48/Deflactores!$B48*100 -> #N/A | H48: =+'[1]1.1.1.1.3'!H48/Deflactores!$B48*100 -> #N/A | I48: =+'[1]1.1.1.1.3'!I48/Deflactores!$B48*100 -> #N/A | ... Y48: =+'[1]1.1.1.1.3'!Y48/Deflactores!$B48*100 -> #N/A | Z48: =SUM(B48:Y48) -> #N/A

Sheet 1.1.1.1.4
A2: Título | B2: Automotores | N2: =B2 -> Automotores
A3: Fuente | B3: Dirección Nacional de Asuntos Provinciales - Ministerio de Economía de la Nación | N3: =B3 -> Dirección Nacional de Asuntos Provinciales - Ministerio de Economía de la Nación
A5: VOLVER AL ÍNDICE | B5: Administración Pública No Financiera | N5: =B5 -> Administración Pública No Financiera
A7: Unidad de medida | B7: Millones de pesos constantes de 2016 | C7: Millones de pesos constantes de 2016 | D7: Millones de pesos constantes de 2016 | E7: Millones de pesos constantes de 2016 | F7: Millones de pesos constantes de 2016 | G7: Millones de pesos constantes de 2016 | H7: Millones de pesos constantes de 2016 | I7: Millones de pesos constantes de 2016 | J7: Millones de pesos constantes de 2016 | K7: Millones de pesos constantes de 2016 | L7: Millones de pesos constantes de 2016 | M7: Millones de pesos constantes de 2016 | N7: Millones de pesos constantes de 2016 | O7: Millones de pesos constantes de 2016 | P7: Millones de pesos constantes de 2016 | Q7: Millones de pesos constantes de 2016 | R7: Millones de pesos constantes de 2016 | S7: Millones de pesos constantes de 2016 | T7: Millones de pesos constantes de 2016 | U7: Millones de pesos constantes de 2016 | V7: Millones de pesos constantes de 2016 | W7: Millones de pesos constantes de 2016 | X7: Millones de pesos constantes de 2016 | Y7: Millones de pesos constantes de 2016 | Z7: Millones de pesos constantes de 2016
A8: CÓDIGO | B8: 1.1.1.1.4.1 | C8: 1.1.1.1.4.2 | D8: 1.1.1.1.4.3 | E8: 1.1.1.1.4.4 | F8: 1.1.1.1.4.5 | G8: 1.1.1.1.4.6 | H8: 1.1.1.1.4.7 | I8: 1.1.1.1.4.8 | J8: 1.1.1.1.4.9 | K8: 1.1.1.1.4.10 | L8: 1.1.1.1.4.11 | M8: 1.1.1.1.4.12 | N8: 1.1.1.1.4.13 | O8: 1.1.1.1.4.14 | P8: 1.1.1.1.4.15 | Q8: 1.1.1.1.4.16 | R8: 1.1.1.1.4.17 | S8: 1.1.1.1.4.18 | T8: 1.1.1.1.4.19 | U8: 1.1.1.1.4.20 | V8: 1.1.1.1.4.21 | W8: 1.1.1.1.4.22 | X8: 1.1.1.1.4.23 | Y8: 1.1.1.1.4.24 | Z8: 1.1.1.1.4.25
A9: Jurisdicción | B9: C.A.B.A. | C9: Buenos Aires | D9: Catamarca | E9: Córdoba | F9: Corrientes | G9: Chaco | H9: Chubut | I9: Entre Ríos | J9: Formosa | K9: Jujuy | L9: La Pampa | M9: La Rioja | N9: Mendoza | O9: Misiones | P9: Neuquén | Q9: Río Negro | R9: Salta | S9: San Juan | T9: San Luis | U9: Santa Cruz | V9: Santa Fe | W9: Santiago del Estero | X9: Tucumán | Y9: Tierra del Fuego | Z9: Total
A10: 1992 | B10: =+'[1]1.1.1.1.4'!B10/Deflactores!$B10*100 -> 4087.45 | C10: =+'[1]1.1.1.1.4'!C10/Deflactores!$B10*100 -> 5583.5339 | D10: =+'[1]1.1.1.1.4'!D10/Deflactores!$B10*100 -> 36.230355 | E10: =+'[1]1.1.1.1.4'!E10/Deflactores!$B10*100 -> 434.9178 | F10: =+'[1]1.1.1.1.4'!F10/Deflactores!$B10*100 -> 0 | G10: =+'[1]1.1.1.1.4'!G10/Deflactores!$B10*100 -> 0 | H10: =+'[1]1.1.1.1.4'!H10/Deflactores!$B10*100 -> 0 | I10: =+'[1]1.1.1.1.4'!I10/Deflactores!$B10*100 -> 457.73904 | ... Y10: =+'[1]1.1.1.1.4'!Y10/Deflactores!$B10*100 -> 0 | Z10: =SUM(B10:Y10) -> 12202.871
A11: 1993 | B11: =+'[1]1.1.1.1.4'!B11/Deflactores!$B11*100 -> 4772.4206 | C11: =+'[1]1.1.1.1.4'!C11/Deflactores!$B11*100 -> 6002.7019 | D11: =+'[1]1.1.1.1.4'!D11/Deflactores!$B11*100 -> 45.13107 | E11: =+'[1]1.1.1.1.4'!E11/Deflactores!$B11*100 -> 0 | F11: =+'[1]1.1.1.1.4'!F11/Deflactores!$B11*100 -> 0 | G11: =+'[1]1.1.1.1.4'!G11/Deflactores!$B11*100 -> 0 | H11: =+'[1]1.1.1.1.4'!H11/Deflactores!$B11*100 -> 0 | I11: =+'[1]1.1.1.1.4'!I11/Deflactores!$B11*100 -> 548.02207 | ... Y11: =+'[1]1.1.1.1.4'!Y11/Deflactores!$B11*100 -> 0 | Z11: =SUM(B11:Y11) -> 13012.668
A12: 1994 | B12: =+'[1]1.1.1.1.4'!B12/Deflactores!$B12*100 -> 4807.5582 | C12: =+'[1]1.1.1.1.4'!C12/Deflactores!$B12*100 -> 7262.6225 | D12: =+'[1]1.1.1.1.4'!D12/Deflactores!$B12*100 -> 46.284416 | E12: =+'[1]1.1.1.1.4'!E12/Deflactores!$B12*100 -> 0 | F12: =+'[1]1.1.1.1.4'!F12/Deflactores!$B12*100 -> 0 | G12: =+'[1]1.1.1.1.4'!G12/Deflactores!$B12*100 -> 0 | H12: =+'[1]1.1.1.1.4'!H12/Deflactores!$B12*100 -> 0 | I12: =+'[1]1.1.1.1.4'!I12/Deflactores!$B12*100 -> 649.1374 | ... Y12: =+'[1]1.1.1.1.4'!Y12/Deflactores!$B12*100 -> 0 | Z12: =SUM(B12:Y12) -> 14683.862
A13: 1995 | B13: =+'[1]1.1.1.1.4'!B13/Deflactores!$B13*100 -> 4487.1157 | C13: =+'[1]1.1.1.1.4'!C13/Deflactores!$B13*100 -> 6568.6695 | D13: =+'[1]1.1.1.1.4'!D13/Deflactores!$B13*100 -> 38.480316 | E13: =+'[1]1.1.1.1.4'!E13/Deflactores!$B13*100 -> 0 | F13: =+'[1]1.1.1.1.4'!F13/Deflactores!$B13*100 -> 0 | G13: =+'[1]1.1.1.1.4'!G13/Deflactores!$B13*100 -> 0 | H13: =+'[1]1.1.1.1.4'!H13/Deflactores!$B13*100 -> 0 | I13: =+'[1]1.1.1.1.4'!I13/Deflactores!$B13*100 -> 596.44268 | ... Y13: =+'[1]1.1.1.1.4'!Y13/Deflactores!$B13*100 -> 0 | Z13: =SUM(B13:Y13) -> 13363.648
A14: 1996 | B14: =+'[1]1.1.1.1.4'!B14/Deflactores!$B14*100 -> 3757.0429 | C14: =+'[1]1.1.1.1.4'!C14/Deflactores!$B14*100 -> 7268.2123 | D14: =+'[1]1.1.1.1.4'!D14/Deflactores!$B14*100 -> 56.602248 | E14: =+'[1]1.1.1.1.4'!E14/Deflactores!$B14*100 -> 0 | F14: =+'[1]1.1.1.1.4'!F14/Deflactores!$B14*100 -> 0 | G14: =+'[1]1.1.1.1.4'!G14/Deflactores!$B14*100 -> 0 | H14: =+'[1]1.1.1.1.4'!H14/Deflactores!$B14*100 -> 0 | I14: =+'[1]1.1.1.1.4'!I14/Deflactores!$B14*100 -> 511.45759 | ... Y14: =+'[1]1.1.1.1.4'!Y14/Deflactores!$B14*100 -> 0 | Z14: =SUM(B14:Y14) -> 13445.69
A15: 1997 | B15: =+'[1]1.1.1.1.4'!B15/Deflactores!$B15*100 -> 4350.461 | C15: =+'[1]1.1.1.1.4'!C15/Deflactores!$B15*100 -> 8180.6374 | D15: =+'[1]1.1.1.1.4'!D15/Deflactores!$B15*100 -> 37.086335 | E15: =+'[1]1.1.1.1.4'!E15/Deflactores!$B15*100 -> 590.80477 | F15: =+'[1]1.1.1.1.4'!F15/Deflactores!$B15*100 -> 0 | G15: =+'[1]1.1.1.1.4'!G15/Deflactores!$B15*100 -> 0 | H15: =+'[1]1.1.1.1.4'!H15/Deflactores!$B15*100 -> 0 | I15: =+'[1]1.1.1.1.4'!I15/Deflactores!$B15*100 -> 520.75541 | ... Y15: =+'[1]1.1.1.1.4'!Y15/Deflactores!$B15*100 -> 0 | Z15: =SUM(B15:Y15) -> 15916.817
A16: 1998 | B16: =+'[1]1.1.1.1.4'!B16/Deflactores!$B16*100 -> 4740.3536 | C16: =+'[1]1.1.1.1.4'!C16/Deflactores!$B16*100 -> 8739.6838 | D16: =+'[1]1.1.1.1.4'!D16/Deflactores!$B16*100 -> 60.954392 | E16: =+'[1]1.1.1.1.4'!E16/Deflactores!$B16*100 -> 705.98893 | F16: =+'[1]1.1.1.1.4'!F16/Deflactores!$B16*100 -> 0 | G16: =+'[1]1.1.1.1.4'!G16/Deflactores!$B16*100 -> 0 | H16: =+'[1]1.1.1.1.4'!H16/Deflactores!$B16*100 -> 0 | I16: =+'[1]1.1.1.1.4'!I16/Deflactores!$B16*100 -> 498.0602 | ... Y16: =+'[1]1.1.1.1.4'!Y16/Deflactores!$B16*100 -> 0 | Z16: =SUM(B16:Y16) -> 17154.432
A17: 1999 | B17: =+'[1]1.1.1.1.4'!B17/Deflactores!$B17*100 -> 5179.8715 | C17: =+'[1]1.1.1.1.4'!C17/Deflactores!$B17*100 -> 7928.1487 | D17: =+'[1]1.1.1.1.4'!D17/Deflactores!$B17*100 -> 59.72956 | E17: =+'[1]1.1.1.1.4'!E17/Deflactores!$B17*100 -> 572.27747 | F17: =+'[1]1.1.1.1.4'!F17/Deflactores!$B17*100 -> 0 | G17: =+'[1]1.1.1.1.4'!G17/Deflactores!$B17*100 -> 0 | H17: =+'[1]1.1.1.1.4'!H17/Deflactores!$B17*100 -> 0 | I17: =+'[1]1.1.1.1.4'!I17/Deflactores!$B17*100 -> 416.53542 | ... Y17: =+'[1]1.1.1.1.4'!Y17/Deflactores!$B17*100 -> 0 | Z17: =SUM(B17:Y17) -> 16447.924
A18: 2000 | B18: =+'[1]1.1.1.1.4'!B18/Deflactores!$B18*100 -> 4810.5619 | C18: =+'[1]1.1.1.1.4'!C18/Deflactores!$B18*100 -> 7569.7269 | D18: =+'[1]1.1.1.1.4'!D18/Deflactores!$B18*100 -> 73.668401 | E18: =+'[1]1.1.1.1.4'!E18/Deflactores!$B18*100 -> 506.27926 | F18: =+'[1]1.1.1.1.4'!F18/Deflactores!$B18*100 -> 0 | G18: =+'[1]1.1.1.1.4'!G18/Deflactores!$B18*100 -> 0 | H18: =+'[1]1.1.1.1.4'!H18/Deflactores!$B18*100 -> 0 | I18: =+'[1]1.1.1.1.4'!I18/Deflactores!$B18*100 -> 513.60134 | ... Y18: =+'[1]1.1.1.1.4'!Y18/Deflactores!$B18*100 -> 0 | Z18: =SUM(B18:Y18) -> 15861.44
A19: 2001 | B19: =+'[1]1.1.1.1.4'!B19/Deflactores!$B19*100 -> 4331.4282 | C19: =+'[1]1.1.1.1.4'!C19/Deflactores!$B19*100 -> 7117.2553 | D19: =+'[1]1.1.1.1.4'!D19/Deflactores!$B19*100 -> 64.870527 | E19: =+'[1]1.1.1.1.4'!E19/Deflactores!$B19*100 -> 677.39242 | F19: =+'[1]1.1.1.1.4'!F19/Deflactores!$B19*100 -> 0 | G19: =+'[1]1.1.1.1.4'!G19/Deflactores!$B19*100 -> 0 | H19: =+'[1]1.1.1.1.4'!H19/Deflactores!$B19*100 -> 0 | I19: =+'[1]1.1.1.1.4'!I19/Deflactores!$B19*100 -> 495.04576 | ... Y19: =+'[1]1.1.1.1.4'!Y19/Deflactores!$B19*100 -> 0 | Z19: =SUM(B19:Y19) -> 15023.497
A20: 2002 | B20: =+'[1]1.1.1.1.4'!B20/Deflactores!$B20*100 -> 2578.6792 | C20: =+'[1]1.1.1.1.4'!C20/Deflactores!$B20*100 -> 4399.8088 | D20: =+'[1]1.1.1.1.4'!D20/Deflactores!$B20*100 -> 34.228679 | E20: =+'[1]1.1.1.1.4'!E20/Deflactores!$B20*100 -> 320.21504 | F20: =+'[1]1.1.1.1.4'!F20/Deflactores!$B20*100 -> 0 | G20: =+'[1]1.1.1.1.4'!G20/Deflactores!$B20*100 -> 0 | H20: =+'[1]1.1.1.1.4'!H20/Deflactores!$B20*100 -> 0 | I20: =+'[1]1.1.1.1.4'!I20/Deflactores!$B20*100 -> 303.14143 | ... Y20: =+'[1]1.1.1.1.4'!Y20/Deflactores!$B20*100 -> 0 | Z20: =SUM(B20:Y20) -> 9050.6799
A21: 2003 | B21: =+'[1]1.1.1.1.4'!B21/Deflactores!$B21*100 -> 3225.6959 | C21: =+'[1]1.1.1.1.4'!C21/Deflactores!$B21*100 -> 4109.3292 | D21: =+'[1]1.1.1.1.4'!D21/Deflactores!$B21*100 -> 47.47559 | E21: =+'[1]1.1.1.1.4'!E21/Deflactores!$B21*100 -> 411.91527 | F21: =+'[1]1.1.1.1.4'!F21/Deflactores!$B21*100 -> 0 | G21: =+'[1]1.1.1.1.4'!G21/Deflactores!$B21*100 -> 0 | H21: =+'[1]1.1.1.1.4'!H21/Deflactores!$B21*100 -> 0 | I21: =+'[1]1.1.1.1.4'!I21/Deflactores!$B21*100 -> 280.99489 | ... Y21: =+'[1]1.1.1.1.4'!Y21/Deflactores!$B21*100 -> 0 | Z21: =SUM(B21:Y21) -> 9701.1896
... A48: 2030 | B48: =+'[1]1.1.1.1.4'!B48/Deflactores!$B48*100 -> #N/A | C48: =+'[1]1.1.1.1.4'!C48/Deflactores!$B48*100 -> #N/A | D48: =+'[1]1.1.1.1.4'!D48/Deflactores!$B48*100 -> #N/A | E48: =+'[1]1.1.1.1.4'!E48/Deflactores!$B48*100 -> #N/A | F48: =+'[1]1.1.1.1.4'!F48/Deflactores!$B48*100 -> #N/A | G48: =+'[1]1.1.1.1.4'!G48/Deflactores!$B48*100 -> #N/A | H48: =+'[1]1.1.1.1.4'!H48/Deflactores!$B48*100 -> #N/A | I48: =+'[1]1.1.1.1.4'!I48/Deflactores!$B48*100 -> #N/A | ... Y48: =+'[1]1.1.1.1.4'!Y48/Deflactores!$B48*100 -> #N/A | Z48: =SUM(B48:Y48) -> #N/A

Sheet 1.1.1.1.5
A2: Título | B2: Otros | N2: =B2 -> Otros
A3: Fuente | B3: Dirección Nacional de Asuntos Provinciales - Ministerio de Economía de la Nación | N3: =B3 -> Dirección Nacional de Asuntos Provinciales - Ministerio de Economía de la Nación
A5: VOLVER AL ÍNDICE | B5: Administración Pública No Financiera | N5: =B5 -> Administración Pública No Financiera
A7: Unidad de medida | B7: Millones de pesos constantes de 2016 | C7: Millones de pesos constantes de 2016 | D7: Millones de pesos constantes de 2016 | E7: Millones de pesos constantes de 2016 | F7: Millones de pesos constantes de 2016 | G7: Millones de pesos constantes de 2016 | H7: Millones de pesos constantes de 2016 | I7: Millones de pesos constantes de 2016 | J7: Millones de pesos constantes de 2016 | K7: Millones de pesos constantes de 2016 | L7: Millones de pesos constantes de 2016 | M7: Millones de pesos constantes de 2016 | N7: Millones de pesos constantes de 2016 | O7: Millones de pesos constantes de 2016 | P7: Millones de pesos constantes de 2016 | Q7: Millones de pesos constantes de 2016 | R7: Millones de pesos constantes de 2016 | S7: Millones de pesos constantes de 2016 | T7: Millones de pesos constantes de 2016 | U7: Millones de pesos constantes de 2016 | V7: Millones de pesos constantes de 2016 | W7: Millones de pesos constantes de 2016 | X7: Millones de pesos constantes de 2016 | Y7: Millones de pesos constantes de 2016 | Z7: Millones de pesos constantes de 2016
A8: CÓDIGO | B8: 1.1.1.1.5.1 | C8: 1.1.1.1.5.2 | D8: 1.1.1.1.5.3 | E8: 1.1.1.1.5.4 | F8: 1.1.1.1.5.5 | G8: 1.1.1.1.5.6 | H8: 1.1.1.1.5.7 | I8: 1.1.1.1.5.8 | J8: 1.1.1.1.5.9 | K8: 1.1.1.1.5.10 | L8: 1.1.1.1.5.11 | M8: 1.1.1.1.5.12 | N8: 1.1.1.1.5.13 | O8: 1.1.1.1.5.14 | P8: 1.1.1.1.5.15 | Q8: 1.1.1.1.5.16 | R8: 1.1.1.1.5.17 | S8: 1.1.1.1.5.18 | T8: 1.1.1.1.5.19 | U8: 1.1.1.1.5.20 | V8: 1.1.1.1.5.21 | W8: 1.1.1.1.5.22 | X8: 1.1.1.1.5.23 | Y8: 1.1.1.1.5.24 | Z8: 1.1.1.1.5.25
A9: Jurisdicción | B9: C.A.B.A. | C9: Buenos Aires | D9: Catamarca | E9: Córdoba | F9: Corrientes | G9: Chaco | H9: Chubut | I9: Entre Ríos | J9: Formosa | K9: Jujuy | L9: La Pampa | M9: La Rioja | N9: Mendoza | O9: Misiones | P9: Neuquén | Q9: Río Negro | R9: Salta | S9: San Juan | T9: San Luis | U9: Santa Cruz | V9: Santa Fe | W9: Santiago del Estero | X9: Tucumán | Y9: Tierra del Fuego | Z9: Total
A10: 1992 | B10: =+'[1]1.1.1.1.5'!B10/Deflactores!$B10*100 -> 712.2338 | C10: =+'[1]1.1.1.1.5'!C10/Deflactores!$B10*100 -> 7268.6029 | D10: =+'[1]1.1.1.1.5'!D10/Deflactores!$B10*100 -> 7.0785218 | E10: =+'[1]1.1.1.1.5'!E10/Deflactores!$B10*100 -> 0 | F10: =+'[1]1.1.1.1.5'!F10/Deflactores!$B10*100 -> 0 | G10: =+'[1]1.1.1.1.5'!G10/Deflactores!$B10*100 -> 190.53012 | H10: =+'[1]1.1.1.1.5'!H10/Deflactores!$B10*100 -> 43.564135 | I10: =+'[1]1.1.1.1.5'!I10/Deflactores!$B10*100 -> 56.365048 | ... Y10: =+'[1]1.1.1.1.5'!Y10/Deflactores!$B10*100 -> 381.10246 | Z10: =SUM(B10:Y10) -> 9674.0731
A11: 1993 | B11: =+'[1]1.1.1.1.5'!B11/Deflactores!$B11*100 -> 546.75823 | C11: =+'[1]1.1.1.1.5'!C11/Deflactores!$B11*100 -> 7860.2223 | D11: =+'[1]1.1.1.1.5'!D11/Deflactores!$B11*100 -> 8.8173631 | E11: =+'[1]1.1.1.1.5'!E11/Deflactores!$B11*100 -> 588.23459 | F11: =+'[1]1.1.1.1.5'!F11/Deflactores!$B11*100 -> 0 | G11: =+'[1]1.1.1.1.5'!G11/Deflactores!$B11*100 -> 228.76165 | H11: =+'[1]1.1.1.1.5'!H11/Deflactores!$B11*100 -> 8.2668109 | I11: =+'[1]1.1.1.1.5'!I11/Deflactores!$B11*100 -> 67.482354 | ... Y11: =+'[1]1.1.1.1.5'!Y11/Deflactores!$B11*100 -> 334.33923 | Z11: =SUM(B11:Y11) -> 10684.945
A12: 1994 | B12: =+'[1]1.1.1.1.5'!B12/Deflactores!$B12*100 -> 1693.719 | C12: =+'[1]1.1.1.1.5'!C12/Deflactores!$B12*100 -> 7600.4942 | D12: =+'[1]1.1.1.1.5'!D12/Deflactores!$B12*100 -> 0 | E12: =+'[1]1.1.1.1.5'!E12/Deflactores!$B12*100 -> 636.43369 | F12: =+'[1]1.1.1.1.5'!F12/Deflactores!$B12*100 -> 0 | G12: =+'[1]1.1.1.1.5'!G12/Deflactores!$B12*100 -> 228.92925 | H12: =+'[1]1.1.1.1.5'!H12/Deflactores!$B12*100 -> 11.803138 | I12: =+'[1]1.1.1.1.5'!I12/Deflactores!$B12*100 -> 79.933596 | ... Y12: =+'[1]1.1.1.1.5'!Y12/Deflactores!$B12*100 -> 67.907351 | Z12: =SUM(B12:Y12) -> 11430.22
A13: 1995 | B13: =+'[1]1.1.1.1.5'!B13/Deflactores!$B13*100 -> 1563.754 | C13: =+'[1]1.1.1.1.5'!C13/Deflactores!$B13*100 -> 6874.2568 | D13: =+'[1]1.1.1.1.5'!D13/Deflactores!$B13*100 -> 0 | E13: =+'[1]1.1.1.1.5'!E13/Deflactores!$B13*100 -> 615.86782 | F13: =+'[1]1.1.1.1.5'!F13/Deflactores!$B13*100 -> 198.84074 | G13: =+'[1]1.1.1.1.5'!G13/Deflactores!$B13*100 -> 226.51647 | H13: =+'[1]1.1.1.1.5'!H13/Deflactores!$B13*100 -> 10.070593 | I13: =+'[1]1.1.1.1.5'!I13/Deflactores!$B13*100 -> 427.1451 | ... Y13: =+'[1]1.1.1.1.5'!Y13/Deflactores!$B13*100 -> 0 | Z13: =SUM(B13:Y13) -> 10999.962
A14: 1996 | B14: =+'[1]1.1.1.1.5'!B14/Deflactores!$B14*100 -> 3901.753 | C14: =+'[1]1.1.1.1.5'!C14/Deflactores!$B14*100 -> 7606.344 | D14: =+'[1]1.1.1.1.5'!D14/Deflactores!$B14*100 -> 0 | E14: =+'[1]1.1.1.1.5'!E14/Deflactores!$B14*100 -> 622.225 | F14: =+'[1]1.1.1.1.5'!F14/Deflactores!$B14*100 -> 19.141034 | G14: =+'[1]1.1.1.1.5'!G14/Deflactores!$B14*100 -> 425.13712 | H14: =+'[1]1.1.1.1.5'!H14/Deflactores!$B14*100 -> 10.716856 | I14: =+'[1]1.1.1.1.5'!I14/Deflactores!$B14*100 -> 413.98574 | ... Y14: =+'[1]1.1.1.1.5'!Y14/Deflactores!$B14*100 -> 0 | Z14: =SUM(B14:Y14) -> 14743.447
A15: 1997 | B15: =+'[1]1.1.1.1.5'!B15/Deflactores!$B15*100 -> 2632.7086 | C15: =+'[1]1.1.1.1.5'!C15/Deflactores!$B15*100 -> 13938.479 | D15: =+'[1]1.1.1.1.5'!D15/Deflactores!$B15*100 -> 0 | E15: =+'[1]1.1.1.1.5'!E15/Deflactores!$B15*100 -> 119.91716 | F15: =+'[1]1.1.1.1.5'!F15/Deflactores!$B15*100 -> 14.373943 | G15: =+'[1]1.1.1.1.5'!G15/Deflactores!$B15*100 -> 421.08159 | H15: =+'[1]1.1.1.1.5'!H15/Deflactores!$B15*100 -> 19.665359 | I15: =+'[1]1.1.1.1.5'!I15/Deflactores!$B15*100 -> 462.13745 | ... Y15: =+'[1]1.1.1.1.5'!Y15/Deflactores!$B15*100 -> 5.9701666 | Z15: =SUM(B15:Y15) -> 20358.031
A16: 1998 | B16: =+'[1]1.1.1.1.5'!B16/Deflactores!$B16*100 -> 2666.6552 | C16: =+'[1]1.1.1.1.5'!C16/Deflactores!$B16*100 -> 15068.309 | D16: =+'[1]1.1.1.1.5'!D16/Deflactores!$B16*100 -> 0.22311887 | E16: =+'[1]1.1.1.1.5'!E16/Deflactores!$B16*100 -> 8.0943248 | F16: =+'[1]1.1.1.1.5'!F16/Deflactores!$B16*100 -> 0 | G16: =+'[1]1.1.1.1.5'!G16/Deflactores!$B16*100 -> 103.09739 | H16: =+'[1]1.1.1.1.5'!H16/Deflactores!$B16*100 -> 31.524435 | I16: =+'[1]1.1.1.1.5'!I16/Deflactores!$B16*100 -> 542.18147 | ... Y16: =+'[1]1.1.1.1.5'!Y16/Deflactores!$B16*100 -> 0 | Z16: =SUM(B16:Y16) -> 22025.932
A17: 1999 | B17: =+'[1]1.1.1.1.5'!B17/Deflactores!$B17*100 -> 1574.3886 | C17: =+'[1]1.1.1.1.5'!C17/Deflactores!$B17*100 -> 15123.328 | D17: =+'[1]1.1.1.1.5'!D17/Deflactores!$B17*100 -> 0.55279572 | E17: =+'[1]1.1.1.1.5'!E17/Deflactores!$B17*100 -> 1.3816235 | F17: =+'[1]1.1.1.1.5'!F17/Deflactores!$B17*100 -> 0 | G17: =+'[1]1.1.1.1.5'!G17/Deflactores!$B17*100 -> 89.070171 | H17: =+'[1]1.1.1.1.5'!H17/Deflactores!$B17*100 -> 101.69521 | I17: =+'[1]1.1.1.1.5'!I17/Deflactores!$B17*100 -> 561.16138 | ... Y17: =+'[1]1.1.1.1.5'!Y17/Deflactores!$B17*100 -> 0 | Z17: =SUM(B17:Y17) -> 22149.215
A18: 2000 | B18: =+'[1]1.1.1.1.5'!B18/Deflactores!$B18*100 -> 2252.526 | C18: =+'[1]1.1.1.1.5'!C18/Deflactores!$B18*100 -> 15094.503 | D18: =+'[1]1.1.1.1.5'!D18/Deflactores!$B18*100 -> 0.51998626 | E18: =+'[1]1.1.1.1.5'!E18/Deflactores!$B18*100 -> 2772.5494 | F18: =+'[1]1.1.1.1.5'!F18/Deflactores!$B18*100 -> 0 | G18: =+'[1]1.1.1.1.5'!G18/Deflactores!$B18*100 -> 77.512606 | H18: =+'[1]1.1.1.1.5'!H18/Deflactores!$B18*100 -> 98.587948 | I18: =+'[1]1.1.1.1.5'!I18/Deflactores!$B18*100 -> 611.53869 | ... Y18: =+'[1]1.1.1.1.5'!Y18/Deflactores!$B18*100 -> 0 | Z18: =SUM(B18:Y18) -> 24927.822
A19: 2001 | B19: =+'[1]1.1.1.1.5'!B19/Deflactores!$B19*100 -> 1893.4184 | C19: =+'[1]1.1.1.1.5'!C19/Deflactores!$B19*100 -> 11472.357 | D19: =+'[1]1.1.1.1.5'!D19/Deflactores!$B19*100 -> 0.43896747 | E19: =+'[1]1.1.1.1.5'!E19/Deflactores!$B19*100 -> 1784.2663 | F19: =+'[1]1.1.1.1.5'!F19/Deflactores!$B19*100 -> 0 | G19: =+'[1]1.1.1.1.5'!G19/Deflactores!$B19*100 -> 76.417051 | H19: =+'[1]1.1.1.1.5'!H19/Deflactores!$B19*100 -> 228.54896 | I19: =+'[1]1.1.1.1.5'!I19/Deflactores!$B19*100 -> 638.59476 | ... Y19: =+'[1]1.1.1.1.5'!Y19/Deflactores!$B19*100 -> 0 | Z19: =SUM(B19:Y19) -> 19618.104
A20: 2002 | B20: =+'[1]1.1.1.1.5'!B20/Deflactores!$B20*100 -> 1153.3022 | C20: =+'[1]1.1.1.1.5'!C20/Deflactores!$B20*100 -> 13374.859 | D20: =+'[1]1.1.1.1.5'!D20/Deflactores!$B20*100 -> 0.20047478 | E20: =+'[1]1.1.1.1.5'!E20/Deflactores!$B20*100 -> 1717.0117 | F20: =+'[1]1.1.1.1.5'!F20/Deflactores!$B20*100 -> 19.016965 | G20: =+'[1]1.1.1.1.5'!G20/Deflactores!$B20*100 -> 87.158194 | H20: =+'[1]1.1.1.1.5'!H20/Deflactores!$B20*100 -> 133.08402 | I20: =+'[1]1.1.1.1.5'!I20/Deflactores!$B20*100 -> 286.14846 | ... Y20: =+'[1]1.1.1.1.5'!Y20/Deflactores!$B20*100 -> 0 | Z20: =SUM(B20:Y20) -> 19233.066
A21: 2003 | B21: =+'[1]1.1.1.1.5'!B21/Deflactores!$B21*100 -> 1418.2349 | C21: =+'[1]1.1.1.1.5'!C21/Deflactores!$B21*100 -> 10871.775 | D21: =+'[1]1.1.1.1.5'!D21/Deflactores!$B21*100 -> 0.17119326 | E21: =+'[1]1.1.1.1.5'!E21/Deflactores!$B21*100 -> 476.49614 | F21: =+'[1]1.1.1.1.5'!F21/Deflactores!$B21*100 -> 0 | G21: =+'[1]1.1.1.1.5'!G21/Deflactores!$B21*100 -> 94.600992 | H21: =+'[1]1.1.1.1.5'!H21/Deflactores!$B21*100 -> 154.55675 | I21: =+'[1]1.1.1.1.5'!I21/Deflactores!$B21*100 -> 362.26154 | ... Y21: =+'[1]1.1.1.1.5'!Y21/Deflactores!$B21*100 -> 83.479003 | Z21: =SUM(B21:Y21) -> 15336.013
... A48: 2030 | B48: =+'[1]1.1.1.1.5'!B48/Deflactores!$B48*100 -> #N/A | C48: =+'[1]1.1.1.1.5'!C48/Deflactores!$B48*100 -> #N/A | D48: =+'[1]1.1.1.1.5'!D48/Deflactores!$B48*100 -> #N/A | E48: =+'[1]1.1.1.1.5'!E48/Deflactores!$B48*100 -> #N/A | F48: =+'[1]1.1.1.1.5'!F48/Deflactores!$B48*100 -> #N/A | G48: =+'[1]1.1.1.1.5'!G48/Deflactores!$B48*100 -> #N/A | H48: =+'[1]1.1.1.1.5'!H48/Deflactores!$B48*100 -> #N/A | I48: =+'[1]1.1.1.1.5'!I48/Deflactores!$B48*100 -> #N/A | ... Y48: =+'[1]1.1.1.1.5'!Y48/Deflactores!$B48*100 -> #N/A | Z48: =SUM(B48:Y48) -> #N/A

Sheet 1.1.1.2
A2: Título | B2: Recursos de origen nacional (coparticipación) por provincia | N2: =B2 -> Recursos de origen nacional (coparticipación) por provincia
A3: Fuente | B3: Dirección Nacional de Asuntos Provinciales - Ministerio de Economía de la Nación | N3: =B3 -> Dirección Nacional de Asuntos Provinciales - Ministerio de Economía de la Nación
A5: VOLVER AL ÍNDICE | B5: Administración Pública No Financiera | N5: =B5 -> Administración Pública No Financiera
A7: Unidad de medida | B7: Millones de pesos constantes de 2016 | C7: Millones de pesos constantes de 2016 | D7: Millones de pesos constantes de 2016 | E7: Millones de pesos constantes de 2016 | F7: Millones de pesos constantes de 2016 | G7: Millones de pesos constantes de 2016 | H7: Millones de pesos constantes de 2016 | I7: Millones de pesos constantes de 2016 | J7: Millones de pesos constantes de 2016 | K7: Millones de pesos constantes de 2016 | L7: Millones de pesos constantes de 2016 | M7: Millones de pesos constantes de 2016 | N7: Millones de pesos constantes de 2016 | O7: Millones de pesos constantes de 2016 | P7: Millones de pesos constantes de 2016 | Q7: Millones de pesos constantes de 2016 | R7: Millones de pesos constantes de 2016 | S7: Millones de pesos constantes de 2016 | T7: Millones de pesos constantes de 2016 | U7: Millones de pesos constantes de 2016 | V7: Millones de pesos constantes de 2016 | W7: Millones de pesos constantes de 2016 | X7: Millones de pesos constantes de 2016 | Y7: Millones de pesos constantes de 2016 | Z7: Millones de pesos constantes de 2016
A8: CÓDIGO | B8: 1.1.1.2.1 | C8: 1.1.1.2.2 | D8: 1.1.1.2.3 | E8: 1.1.1.2.4 | F8: 1.1.1.2.5 | G8: 1.1.1.2.6 | H8: 1.1.1.2.7 | I8: 1.1.1.2.8 | J8: 1.1.1.2.9 | K8: 1.1.1.2.10 | L8: 1.1.1.2.11 | M8: 1.1.1.2.12 | N8: 1.1.1.2.13 | O8: 1.1.1.2.14 | P8: 1.1.1.2.15 | Q8: 1.1.1.2.16 | R8: 1.1.1.2.17 | S8: 1.1.1.2.18 | T8: 1.1.1.2.19 | U8: 1.1.1.2.20 | V8: 1.1.1.2.21 | W8: 1.1.1.2.22 | X8: 1.1.1.2.23 | Y8: 1.1.1.2.24 | Z8: 1.1.1.2.25
A9: Jurisdicción | B9: C.A.B.A. | C9: Buenos Aires | D9: Catamarca | E9: Córdoba | F9: Corrientes | G9: Chaco | H9: Chubut | I9: Entre Ríos | J9: Formosa | K9: Jujuy | L9: La Pampa | M9: La Rioja | N9: Mendoza | O9: Misiones | P9: Neuquén | Q9: Río Negro | R9: Salta | S9: San Juan | T9: San Luis | U9: Santa Cruz | V9: Santa Fe | W9: Santiago del Estero | X9: Tucumán | Y9: Tierra del Fuego | Z9: Total
A10: 1992 | B10: =+'[1]1.1.1.2'!B10/Deflactores!$B10*100 -> 3031.9463 | C10: =+'[1]1.1.1.2'!C10/Deflactores!$B10*100 -> 53862.469 | D10: =+'[1]1.1.1.2'!D10/Deflactores!$B10*100 -> 5998.9726 | E10: =+'[1]1.1.1.2'!E10/Deflactores!$B10*100 -> 18753.727 | F10: =+'[1]1.1.1.2'!F10/Deflactores!$B10*100 -> 8166.779 | G10: =+'[1]1.1.1.2'!G10/Deflactores!$B10*100 -> 10380.078 | H10: =+'[1]1.1.1.2'!H10/Deflactores!$B10*100 -> 4467.1791 | I10: =+'[1]1.1.1.2'!I10/Deflactores!$B10*100 -> 10417.043 | ... Y10: =+'[1]1.1.1.2'!Y10/Deflactores!$B10*100 -> 1957.8014 | Z10: =SUM(B10:Y10) -> 229937.56
A11: 1993 | B11: =+'[1]1.1.1.2'!B11/Deflactores!$B11*100 -> 3255.9953 | C11: =+'[1]1.1.1.2'!C11/Deflactores!$B11*100 -> 56912.84 | D11: =+'[1]1.1.1.2'!D11/Deflactores!$B11*100 -> 5980.6374 | E11: =+'[1]1.1.1.2'!E11/Deflactores!$B11*100 -> 18500.02 | F11: =+'[1]1.1.1.2'!F11/Deflactores!$B11*100 -> 8117.5086 | G11: =+'[1]1.1.1.2'!G11/Deflactores!$B11*100 -> 9970.8466 | H11: =+'[1]1.1.1.2'!H11/Deflactores!$B11*100 -> 4513.2571 | I11: =+'[1]1.1.1.2'!I11/Deflactores!$B11*100 -> 10658.46 | ... Y11: =+'[1]1.1.1.2'!Y11/Deflactores!$B11*100 -> 2505.5232 | Z11: =SUM(B11:Y11) -> 235294.16
A12: 1994 | B12: =+'[1]1.1.1.2'!B12/Deflactores!$B12*100 -> 3261.0416 | C12: =+'[1]1.1.1.2'!C12/Deflactores!$B12*100 -> 59591.7 | D12: =+'[1]1.1.1.2'!D12/Deflactores!$B12*100 -> 5978.4885 | E12: =+'[1]1.1.1.2'!E12/Deflactores!$B12*100 -> 18873.319 | F12: =+'[1]1.1.1.2'!F12/Deflactores!$B12*100 -> 8336.793 | G12: =+'[1]1.1.1.2'!G12/Deflactores!$B12*100 -> 10130.033 | H12: =+'[1]1.1.1.2'!H12/Deflactores!$B12*100 -> 4446.2196 | I12: =+'[1]1.1.1.2'!I12/Deflactores!$B12*100 -> 10915.583 | ... Y12: =+'[1]1.1.1.2'!Y12/Deflactores!$B12*100 -> 2530.0816 | Z12: =SUM(B12:Y12) -> 239655.86
A13: 1995 | B13: =+'[1]1.1.1.2'!B13/Deflactores!$B13*100 -> 3461.7252 | C13: =+'[1]1.1.1.2'!C13/Deflactores!$B13*100 -> 55313.211 | D13: =+'[1]1.1.1.2'!D13/Deflactores!$B13*100 -> 5454.2449 | E13: =+'[1]1.1.1.2'!E13/Deflactores!$B13*100 -> 16410.116 | F13: =+'[1]1.1.1.2'!F13/Deflactores!$B13*100 -> 7695.7087 | G13: =+'[1]1.1.1.2'!G13/Deflactores!$B13*100 -> 9335.4661 | H13: =+'[1]1.1.1.2'!H13/Deflactores!$B13*100 -> 4063.1644 | I13: =+'[1]1.1.1.2'!I13/Deflactores!$B13*100 -> 9965.6769 | ... Y13: =+'[1]1.1.1.2'!Y13/Deflactores!$B13*100 -> 2341.2017 | Z13: =SUM(B13:Y13) -> 221014.81
A14: 1996 | B14: =+'[1]1.1.1.2'!B14/Deflactores!$B14*100 -> 3127.2734 | C14: =+'[1]1.1.1.2'!C14/Deflactores!$B14*100 -> 56726.119 | D14: =+'[1]1.1.1.2'!D14/Deflactores!$B14*100 -> 5814.3289 | E14: =+'[1]1.1.1.2'!E14/Deflactores!$B14*100 -> 18613.728 | F14: =+'[1]1.1.1.2'!F14/Deflactores!$B14*100 -> 8301.8105 | G14: =+'[1]1.1.1.2'!G14/Deflactores!$B14*100 -> 10190.169 | H14: =+'[1]1.1.1.2'!H14/Deflactores!$B14*100 -> 4447.8518 | I14: =+'[1]1.1.1.2'!I14/Deflactores!$B14*100 -> 11042.773 | ... Y14: =+'[1]1.1.1.2'!Y14/Deflactores!$B14*100 -> 2441.7487 | Z14: =SUM(B14:Y14) -> 235445.11
A15: 1997 | B15: =+'[1]1.1.1.2'!B15/Deflactores!$B15*100 -> 3266.8205 | C15: =+'[1]1.1.1.2'!C15/Deflactores!$B15*100 -> 64882.56 | D15: =+'[1]1.1.1.2'!D15/Deflactores!$B15*100 -> 6973.0681 | E15: =+'[1]1.1.1.2'!E15/Deflactores!$B15*100 -> 23663.779 | F15: =+'[1]1.1.1.2'!F15/Deflactores!$B15*100 -> 9989.7598 | G15: =+'[1]1.1.1.2'!G15/Deflactores!$B15*100 -> 11828.976 | H15: =+'[1]1.1.1.2'!H15/Deflactores!$B15*100 -> 5004.2373 | I15: =+'[1]1.1.1.2'!I15/Deflactores!$B15*100 -> 12455.876 | ... Y15: =+'[1]1.1.1.2'!Y15/Deflactores!$B15*100 -> 2718.3826 | Z15: =SUM(B15:Y15) -> 275630.28
A16: 1998 | B16: =+'[1]1.1.1.2'!B16/Deflactores!$B16*100 -> 3377.5482 | C16: =+'[1]1.1.1.2'!C16/Deflactores!$B16*100 -> 69443.681 | D16: =+'[1]1.1.1.2'!D16/Deflactores!$B16*100 -> 7338.3309 | E16: =+'[1]1.1.1.2'!E16/Deflactores!$B16*100 -> 23642.86 | F16: =+'[1]1.1.1.2'!F16/Deflactores!$B16*100 -> 10453.533 | G16: =+'[1]1.1.1.2'!G16/Deflactores!$B16*100 -> 12875.265 | H16: =+'[1]1.1.1.2'!H16/Deflactores!$B16*100 -> 5438.3717 | I16: =+'[1]1.1.1.2'!I16/Deflactores!$B16*100 -> 13599.7 | ... Y16: =+'[1]1.1.1.2'!Y16/Deflactores!$B16*100 -> 2900.5791 | Z16: =SUM(B16:Y16) -> 293521.4
A17: 1999 | B17: =+'[1]1.1.1.2'!B17/Deflactores!$B17*100 -> 3962.3694 | C17: =+'[1]1.1.1.2'!C17/Deflactores!$B17*100 -> 71909.455 | D17: =+'[1]1.1.1.2'!D17/Deflactores!$B17*100 -> 7613.4324 | E17: =+'[1]1.1.1.2'!E17/Deflactores!$B17*100 -> 24051.03 | F17: =+'[1]1.1.1.2'!F17/Deflactores!$B17*100 -> 10590.933 | G17: =+'[1]1.1.1.2'!G17/Deflactores!$B17*100 -> 13197.623 | H17: =+'[1]1.1.1.2'!H17/Deflactores!$B17*100 -> 5561.8771 | I17: =+'[1]1.1.1.2'!I17/Deflactores!$B17*100 -> 13813.941 | ... Y17: =+'[1]1.1.1.2'!Y17/Deflactores!$B17*100 -> 3467.263 | Z17: =SUM(B17:Y17) -> 300839.94
A18: 2000 | B18: =+'[1]1.1.1.2'!B18/Deflactores!$B18*100 -> 3211.6798 | C18: =+'[1]1.1.1.2'!C18/Deflactores!$B18*100 -> 73670.079 | D18: =+'[1]1.1.1.2'!D18/Deflactores!$B18*100 -> 7907.645 | E18: =+'[1]1.1.1.2'!E18/Deflactores!$B18*100 -> 25066.791 | F18: =+'[1]1.1.1.2'!F18/Deflactores!$B18*100 -> 11069.908 | G18: =+'[1]1.1.1.2'!G18/Deflactores!$B18*100 -> 13855.267 | H18: =+'[1]1.1.1.2'!H18/Deflactores!$B18*100 -> 5782.2636 | I18: =+'[1]1.1.1.2'!I18/Deflactores!$B18*100 -> 14275.703 | ... Y18: =+'[1]1.1.1.2'!Y18/Deflactores!$B18*100 -> 4441.8716 | Z18: =SUM(B18:Y18) -> 312432.54
A19: 2001 | B19: =+'[1]1.1.1.2'!B19/Deflactores!$B19*100 -> 2827.2418 | C19: =+'[1]1.1.1.2'!C19/Deflactores!$B19*100 -> 69633.456 | D19: =+'[1]1.1.1.2'!D19/Deflactores!$B19*100 -> 7901.5226 | E19: =+'[1]1.1.1.2'!E19/Deflactores!$B19*100 -> 25088.737 | F19: =+'[1]1.1.1.2'!F19/Deflactores!$B19*100 -> 11061.89 | G19: =+'[1]1.1.1.2'!G19/Deflactores!$B19*100 -> 13711.473 | H19: =+'[1]1.1.1.2'!H19/Deflactores!$B19*100 -> 5664.9066 | I19: =+'[1]1.1.1.2'!I19/Deflactores!$B19*100 -> 14250.99 | ... Y19: =+'[1]1.1.1.2'!Y19/Deflactores!$B19*100 -> 4551.5616 | Z19: =SUM(B19:Y19) -> 303881.68
A20: 2002 | B20: =+'[1]1.1.1.2'!B20/Deflactores!$B20*100 -> 2273.5917 | C20: =+'[1]1.1.1.2'!C20/Deflactores!$B20*100 -> 50445.851 | D20: =+'[1]1.1.1.2'!D20/Deflactores!$B20*100 -> 5121.1522 | E20: =+'[1]1.1.1.2'!E20/Deflactores!$B20*100 -> 15719.711 | F20: =+'[1]1.1.1.2'!F20/Deflactores!$B20*100 -> 7067.5738 | G20: =+'[1]1.1.1.2'!G20/Deflactores!$B20*100 -> 8700.2617 | H20: =+'[1]1.1.1.2'!H20/Deflactores!$B20*100 -> 3716.82 | I20: =+'[1]1.1.1.2'!I20/Deflactores!$B20*100 -> 8966.2243 | ... Y20: =+'[1]1.1.1.2'!Y20/Deflactores!$B20*100 -> 2836.1949 | Z20: =SUM(B20:Y20) -> 204978.8
A21: 2003 | B21: =+'[1]1.1.1.2'!B21/Deflactores!$B21*100 -> 3552.0528 | C21: =+'[1]1.1.1.2'!C21/Deflactores!$B21*100 -> 49346.566 | D21: =+'[1]1.1.1.2'!D21/Deflactores!$B21*100 -> 5623.6505 | E21: =+'[1]1.1.1.2'!E21/Deflactores!$B21*100 -> 18089.057 | F21: =+'[1]1.1.1.2'!F21/Deflactores!$B21*100 -> 7896.2745 | G21: =+'[1]1.1.1.2'!G21/Deflactores!$B21*100 -> 9964.2266 | H21: =+'[1]1.1.1.2'!H21/Deflactores!$B21*100 -> 4006.5029 | I21: =+'[1]1.1.1.2'!I21/Deflactores!$B21*100 -> 10207.232 | ... Y21: =+'[1]1.1.1.2'!Y21/Deflactores!$B21*100 -> 3019.2561 | Z21: =SUM(B21:Y21) -> 220240.01
... A39: 2021 | B39: =+'[1]1.1.1.2'!B39/Deflactores!$B39*100 -> 13816.934 | C39: =+'[1]1.1.1.2'!C39/Deflactores!$B39*100 -> 147928.97 | D39: =+'[1]1.1.1.2'!D39/Deflactores!$B39*100 -> 16563.608 | E39: =+'[1]1.1.1.2'!E39/Deflactores!$B39*100 -> 54570.003 | F39: =+'[1]1.1.1.2'!F39/Deflactores!$B39*100 -> 23465.615 | G39: =+'[1]1.1.1.2'!G39/Deflactores!$B39*100 -> 30957.74 | H39: =+'[1]1.1.1.2'!H39/Deflactores!$B39*100 -> 10026.079 | I39: =+'[1]1.1.1.2'!I39/Deflactores!$B39*100 -> 30066.686 | ... Y39: =+'[1]1.1.1.2'!Y39/Deflactores!$B39*100 -> 7606.1724 | Z39: =SUM(B39:Y39) -> 651574.42
A40: 2022 | B40: =+'[1]1.1.1.2'!B40/Deflactores!$B40*100 -> 15244.431 | C40: =+'[1]1.1.1.2'!C40/Deflactores!$B40*100 -> 158641.92 | D40: =+'[1]1.1.1.2'!D40/Deflactores!$B40*100 -> 17992.494 | E40: =+'[1]1.1.1.2'!E40/Deflactores!$B40*100 -> 59149.414 | F40: =+'[1]1.1.1.2'!F40/Deflactores!$B40*100 -> 25289.822 | G40: =+'[1]1.1.1.2'!G40/Deflactores!$B40*100 -> 33505.761 | H40: =+'[1]1.1.1.2'!H40/Deflactores!$B40*100 -> 10748.848 | I40: =+'[1]1.1.1.2'!I40/Deflactores!$B40*100 -> 32563.384 | ... Y40: =+'[1]1.1.1.2'!Y40/Deflactores!$B40*100 -> 8182.7649 | Z40: =SUM(B40:Y40) -> 703466.94
A41: 2023 | B41: =+'[1]1.1.1.2'!B41/Deflactores!$B41*100 -> 14877.551 | C41: =+'[1]1.1.1.2'!C41/Deflactores!$B41*100 -> 154303.43 | D41: =+'[1]1.1.1.2'!D41/Deflactores!$B41*100 -> 17530.687 | E41: =+'[1]1.1.1.2'!E41/Deflactores!$B41*100 -> 57741.387 | F41: =+'[1]1.1.1.2'!F41/Deflactores!$B41*100 -> 24579.473 | G41: =+'[1]1.1.1.2'!G41/Deflactores!$B41*100 -> 32614.864 | H41: =+'[1]1.1.1.2'!H41/Deflactores!$B41*100 -> 10402.477 | I41: =+'[1]1.1.1.2'!I41/Deflactores!$B41*100 -> 31734.5 | ... Y41: =+'[1]1.1.1.2'!Y41/Deflactores!$B41*100 -> 7912.3125 | Z41: =SUM(B41:Y41) -> 684331.4
A42: 2024 | B42: =+'[1]1.1.1.2'!B42/Deflactores!$B42*100 -> 13295.84 | C42: =+'[1]1.1.1.2'!C42/Deflactores!$B42*100 -> 134418.26 | D42: =+'[1]1.1.1.2'!D42/Deflactores!$B42*100 -> 15582.787 | E42: =+'[1]1.1.1.2'!E42/Deflactores!$B42*100 -> 51164.708 | F42: =+'[1]1.1.1.2'!F42/Deflactores!$B42*100 -> 21753.265 | G42: =+'[1]1.1.1.2'!G42/Deflactores!$B42*100 -> 28841.96 | H42: =+'[1]1.1.1.2'!H42/Deflactores!$B42*100 -> 9265.0268 | I42: =+'[1]1.1.1.2'!I42/Deflactores!$B42*100 -> 28113.585 | ... Y42: =+'[1]1.1.1.2'!Y42/Deflactores!$B42*100 -> 7078.1038 | Z42: =SUM(B42:Y42) -> 604539.17
A43: 2025.04 | B43: =+'[1]1.1.1.2'!B43/Deflactores!$B43*100 -> 13087.689 | C43: =+'[1]1.1.1.2'!C43/Deflactores!$B43*100 -> 136756.79 | D43: =+'[1]1.1.1.2'!D43/Deflactores!$B43*100 -> 15341.241 | E43: =+'[1]1.1.1.2'!E43/Deflactores!$B43*100 -> 50148.514 | F43: =+'[1]1.1.1.2'!F43/Deflactores!$B43*100 -> 21660.32 | G43: =+'[1]1.1.1.2'!G43/Deflactores!$B43*100 -> 28652.391 | H43: =+'[1]1.1.1.2'!H43/Deflactores!$B43*100 -> 9165.8231 | I43: =+'[1]1.1.1.2'!I43/Deflactores!$B43*100 -> 27647.445 | ... Y43: =+'[1]1.1.1.2'!Y43/Deflactores!$B43*100 -> 6965.8758 | Z43: =SUM(B43:Y43) -> 601821.57
A44: 2026 | B44: =+'[1]1.1.1.2'!B44/Deflactores!$B44*100 -> #N/A | C44: =+'[1]1.1.1.2'!C44/Deflactores!$B44*100 -> #N/A | D44: =+'[1]1.1.1.2'!D44/Deflactores!$B44*100 -> #N/A | E44: =+'[1]1.1.1.2'!E44/Deflactores!$B44*100 -> #N/A | F44: =+'[1]1.1.1.2'!F44/Deflactores!$B44*100 -> #N/A | G44: =+'[1]1.1.1.2'!G44/Deflactores!$B44*100 -> #N/A | H44: =+'[1]1.1.1.2'!H44/Deflactores!$B44*100 -> #N/A | I44: =+'[1]1.1.1.2'!I44/Deflactores!$B44*100 -> #N/A | ... Y44: =+'[1]1.1.1.2'!Y44/Deflactores!$B44*100 -> #N/A | Z44: =SUM(B44:Y44) -> #N/A
A45: 2027 | B45: =+'[1]1.1.1.2'!B45/Deflactores!$B45*100 -> #N/A | C45: =+'[1]1.1.1.2'!C45/Deflactores!$B45*100 -> #N/A | D45: =+'[1]1.1.1.2'!D45/Deflactores!$B45*100 -> #N/A | E45: =+'[1]1.1.1.2'!E45/Deflactores!$B45*100 -> #N/A | F45: =+'[1]1.1.1.2'!F45/Deflactores!$B45*100 -> #N/A | G45: =+'[1]1.1.1.2'!G45/Deflactores!$B45*100 -> #N/A | H45: =+'[1]1.1.1.2'!H45/Deflactores!$B45*100 -> #N/A | I45: =+'[1]1.1.1.2'!I45/Deflactores!$B45*100 -> #N/A | ... Y45: =+'[1]1.1.1.2'!Y45/Deflactores!$B45*100 -> #N/A | Z45: =SUM(B45:Y45) -> #N/A
A46: 2028 | B46: =+'[1]1.1.1.2'!B46/Deflactores!$B46*100 -> #N/A | C46: =+'[1]1.1.1.2'!C46/Deflactores!$B46*100 -> #N/A | D46: =+'[1]1.1.1.2'!D46/Deflactores!$B46*100 -> #N/A | E46: =+'[1]1.1.1.2'!E46/Deflactores!$B46*100 -> #N/A | F46: =+'[1]1.1.1.2'!F46/Deflactores!$B46*100 -> #N/A | G46: =+'[1]1.1.1.2'!G46/Deflactores!$B46*100 -> #N/A | H46: =+'[1]1.1.1.2'!H46/Deflactores!$B46*100 -> #N/A | I46: =+'[1]1.1.1.2'!I46/Deflactores!$B46*100 -> #N/A | ... Y46: =+'[1]1.1.1.2'!Y46/Deflactores!$B46*100 -> #N/A | Z46: =SUM(B46:Y46) -> #N/A
A47: 2029 | B47: =+'[1]1.1.1.2'!B47/Deflactores!$B47*100 -> #N/A | C47: =+'[1]1.1.1.2'!C47/Deflactores!$B47*100 -> #N/A | D47: =+'[1]1.1.1.2'!D47/Deflactores!$B47*100 -> #N/A | E47: =+'[1]1.1.1.2'!E47/Deflactores!$B47*100 -> #N/A | F47: =+'[1]1.1.1.2'!F47/Deflactores!$B47*100 -> #N/A | G47: =+'[1]1.1.1.2'!G47/Deflactores!$B47*100 -> #N/A | H47: =+'[1]1.1.1.2'!H47/Deflactores!$B47*100 -> #N/A | I47: =+'[1]1.1.1.2'!I47/Deflactores!$B47*100 -> #N/A | ... Y47: =+'[1]1.1.1.2'!Y47/Deflactores!$B47*100 -> #N/A | Z47: =SUM(B47:Y47) -> #N/A
A48: 2030 | B48: =+'[1]1.1.1.2'!B48/Deflactores!$B48*100 -> #N/A | C48: =+'[1]1.1.1.2'!C48/Deflactores!$B48*100 -> #N/A | D48: =+'[1]1.1.1.2'!D48/Deflactores!$B48*100 -> #N/A | E48: =+'[1]1.1.1.2'!E48/Deflactores!$B48*100 -> #N/A | F48: =+'[1]1.1.1.2'!F48/Deflactores!$B48*100 -> #N/A | G48: =+'[1]1.1.1.2'!G48/Deflactores!$B48*100 -> #N/A | H48: =+'[1]1.1.1.2'!H48/Deflactores!$B48*100 -> #N/A | I48: =+'[1]1.1.1.2'!I48/Deflactores!$B48*100 -> #N/A | ... Y48: =+'[1]1.1.1.2'!Y48/Deflactores!$B48*100 -> #N/A | Z48: =SUM(B48:Y48) -> #N/A

Sheet 1.1.1.3
A2: Título | B2: Recursos no tributarios por provincia | N2: =B2 -> Recursos no tributarios por provincia
A3: Fuente | B3: Dirección Nacional de Asuntos Provinciales - Ministerio de Economía de la Nación | N3: =B3 -> Dirección Nacional de Asuntos Provinciales - Ministerio de Economía de la Nación
A5: VOLVER AL ÍNDICE | B5: Administración Pública No Financiera | N5: =B5 -> Administración Pública No Financiera
A7: Unidad de medida | B7: Millones de pesos constantes de 2016 | C7: Millones de pesos constantes de 2016 | D7: Millones de pesos constantes de 2016 | E7: Millones de pesos constantes de 2016 | F7: Millones de pesos constantes de 2016 | G7: Millones de pesos constantes de 2016 | H7: Millones de pesos constantes de 2016 | I7: Millones de pesos constantes de 2016 | J7: Millones de pesos constantes de 2016 | K7: Millones de pesos constantes de 2016 | L7: Millones de pesos constantes de 2016 | M7: Millones de pesos constantes de 2016 | N7: Millones de pesos constantes de 2016 | O7: Millones de pesos constantes de 2016 | P7: Millones de pesos constantes de 2016 | Q7: Millones de pesos constantes de 2016 | R7: Millones de pesos constantes de 2016 | S7: Millones de pesos constantes de 2016 | T7: Millones de pesos constantes de 2016 | U7: Millones de pesos constantes de 2016 | V7: Millones de pesos constantes de 2016 | W7: Millones de pesos constantes de 2016 | X7: Millones de pesos constantes de 2016 | Y7: Millones de pesos constantes de 2016 | Z7: Millones de pesos constantes de 2016
A8: CÓDIGO | B8: 1.1.1.3.1 | C8: 1.1.1.3.2 | D8: 1.1.1.3.3 | E8: 1.1.1.3.4 | F8: 1.1.1.3.5 | G8: 1.1.1.3.6 | H8: 1.1.1.3.7 | I8: 1.1.1.3.8 | J8: 1.1.1.3.9 | K8: 1.1.1.3.10 | L8: 1.1.1.3.11 | M8: 1.1.1.3.12 | N8: 1.1.1.3.13 | O8: 1.1.1.3.14 | P8: 1.1.1.3.15 | Q8: 1.1.1.3.16 | R8: 1.1.1.3.17 | S8: 1.1.1.3.18 | T8: 1.1.1.3.19 | U8: 1.1.1.3.20 | V8: 1.1.1.3.21 | W8: 1.1.1.3.22 | X8: 1.1.1.3.23 | Y8: 1.1.1.3.24 | Z8: 1.1.1.3.25
A9: Jurisdicción | B9: C.A.B.A. | C9: Buenos Aires | D9: Catamarca | E9: Córdoba | F9: Corrientes | G9: Chaco | H9: Chubut | I9: Entre Ríos | J9: Formosa | K9: Jujuy | L9: La Pampa | M9: La Rioja | N9: Mendoza | O9: Misiones | P9: Neuquén | Q9: Río Negro | R9: Salta | S9: San Juan | T9: San Luis | U9: Santa Cruz | V9: Santa Fe | W9: Santiago del Estero | X9: Tucumán | Y9: Tierra del Fuego | Z9: Total
A10: 1992 | B10: =+'[1]1.1.1.3'!B10/Deflactores!$B10*100 -> 2476.3217 | C10: =+'[1]1.1.1.3'!C10/Deflactores!$B10*100 -> 6192.2 | D10: =+'[1]1.1.1.3'!D10/Deflactores!$B10*100 -> 110.59381 | E10: =+'[1]1.1.1.3'!E10/Deflactores!$B10*100 -> 814.54437 | F10: =+'[1]1.1.1.3'!F10/Deflactores!$B10*100 -> 243.15477 | G10: =+'[1]1.1.1.3'!G10/Deflactores!$B10*100 -> 91.317576 | H10: =+'[1]1.1.1.3'!H10/Deflactores!$B10*100 -> 1455.1842 | I10: =+'[1]1.1.1.3'!I10/Deflactores!$B10*100 -> 950.53126 | ... Y10: =+'[1]1.1.1.3'!Y10/Deflactores!$B10*100 -> 869.51799 | Z10: =SUM(B10:Y10) -> 33311.303
A11: 1993 | B11: =+'[1]1.1.1.3'!B11/Deflactores!$B11*100 -> 3028.9491 | C11: =+'[1]1.1.1.3'!C11/Deflactores!$B11*100 -> 7141.723 | D11: =+'[1]1.1.1.3'!D11/Deflactores!$B11*100 -> 41.127087 | E11: =+'[1]1.1.1.3'!E11/Deflactores!$B11*100 -> 2140.7759 | F11: =+'[1]1.1.1.3'!F11/Deflactores!$B11*100 -> 245.50183 | G11: =+'[1]1.1.1.3'!G11/Deflactores!$B11*100 -> 160.06342 | H11: =+'[1]1.1.1.3'!H11/Deflactores!$B11*100 -> 1540.9631 | I11: =+'[1]1.1.1.3'!I11/Deflactores!$B11*100 -> 995.4191 | ... Y11: =+'[1]1.1.1.3'!Y11/Deflactores!$B11*100 -> 969.95929 | Z11: =SUM(B11:Y11) -> 37413.489
A12: 1994 | B12: =+'[1]1.1.1.3'!B12/Deflactores!$B12*100 -> 3770.4586 | C12: =+'[1]1.1.1.3'!C12/Deflactores!$B12*100 -> 7800.9196 | D12: =+'[1]1.1.1.3'!D12/Deflactores!$B12*100 -> 55.998184 | E12: =+'[1]1.1.1.3'!E12/Deflactores!$B12*100 -> 2873.7721 | F12: =+'[1]1.1.1.3'!F12/Deflactores!$B12*100 -> 328.26612 | G12: =+'[1]1.1.1.3'!G12/Deflactores!$B12*100 -> 180.52888 | H12: =+'[1]1.1.1.3'!H12/Deflactores!$B12*100 -> 1504.9883 | I12: =+'[1]1.1.1.3'!I12/Deflactores!$B12*100 -> 1021.3051 | ... Y12: =+'[1]1.1.1.3'!Y12/Deflactores!$B12*100 -> 982.49954 | Z12: =SUM(B12:Y12) -> 42979.079
A13: 1995 | B13: =+'[1]1.1.1.3'!B13/Deflactores!$B13*100 -> 2897.2975 | C13: =+'[1]1.1.1.3'!C13/Deflactores!$B13*100 -> 11028.763 | D13: =+'[1]1.1.1.3'!D13/Deflactores!$B13*100 -> 81.996894 | E13: =+'[1]1.1.1.3'!E13/Deflactores!$B13*100 -> 2111.4813 | F13: =+'[1]1.1.1.3'!F13/Deflactores!$B13*100 -> 326.88602 | G13: =+'[1]1.1.1.3'!G13/Deflactores!$B13*100 -> 131.65944 | H13: =+'[1]1.1.1.3'!H13/Deflactores!$B13*100 -> 1724.9337 | I13: =+'[1]1.1.1.3'!I13/Deflactores!$B13*100 -> 697.69791 | ... Y13: =+'[1]1.1.1.3'!Y13/Deflactores!$B13*100 -> 869.22137 | Z13: =SUM(B13:Y13) -> 40245.007
A14: 1996 | B14: =+'[1]1.1.1.3'!B14/Deflactores!$B14*100 -> 2010.9067 | C14: =+'[1]1.1.1.3'!C14/Deflactores!$B14*100 -> 3754.0833 | D14: =+'[1]1.1.1.3'!D14/Deflactores!$B14*100 -> 72.922625 | E14: =+'[1]1.1.1.3'!E14/Deflactores!$B14*100 -> 1417.6024 | F14: =+'[1]1.1.1.3'!F14/Deflactores!$B14*100 -> 150.59955 | G14: =+'[1]1.1.1.3'!G14/Deflactores!$B14*100 -> 103.97498 | H14: =+'[1]1.1.1.3'!H14/Deflactores!$B14*100 -> 1778.8532 | I14: =+'[1]1.1.1.3'!I14/Deflactores!$B14*100 -> 630.88346 | ... Y14: =+'[1]1.1.1.3'!Y14/Deflactores!$B14*100 -> 780.77676 | Z14: =SUM(B14:Y14) -> 31018.811
A15: 1997 | B15: =+'[1]1.1.1.3'!B15/Deflactores!$B15*100 -> 2718.5628 | C15: =+'[1]1.1.1.3'!C15/Deflactores!$B15*100 -> 5975.5514 | D15: =+'[1]1.1.1.3'!D15/Deflactores!$B15*100 -> 450.56039 | E15: =+'[1]1.1.1.3'!E15/Deflactores!$B15*100 -> 990.46126 | F15: =+'[1]1.1.1.3'!F15/Deflactores!$B15*100 -> 236.76843 | G15: =+'[1]1.1.1.3'!G15/Deflactores!$B15*100 -> 163.8465 | H15: =+'[1]1.1.1.3'!H15/Deflactores!$B15*100 -> 1873.613 | I15: =+'[1]1.1.1.3'!I15/Deflactores!$B15*100 -> 774.83508 | ... Y15: =+'[1]1.1.1.3'!Y15/Deflactores!$B15*100 -> 785.26865 | Z15: =SUM(B15:Y15) -> 32847.744
A16: 1998 | B16: =+'[1]1.1.1.3'!B16/Deflactores!$B16*100 -> 2930.7264 | C16: =+'[1]1.1.1.3'!C16/Deflactores!$B16*100 -> 6063.7923 | D16: =+'[1]1.1.1.3'!D16/Deflactores!$B16*100 -> 616.82225 | E16: =+'[1]1.1.1.3'!E16/Deflactores!$B16*100 -> 1767.8058 | F16: =+'[1]1.1.1.3'!F16/Deflactores!$B16*100 -> 280.38377 | G16: =+'[1]1.1.1.3'!G16/Deflactores!$B16*100 -> 395.4661 | H16: =+'[1]1.1.1.3'!H16/Deflactores!$B16*100 -> 1095.3047 | I16: =+'[1]1.1.1.3'!I16/Deflactores!$B16*100 -> 769.603 | ... Y16: =+'[1]1.1.1.3'!Y16/Deflactores!$B16*100 -> 828.92252 | Z16: =SUM(B16:Y16) -> 33242.877
A17: 1999 | B17: =+'[1]1.1.1.3'!B17/Deflactores!$B17*100 -> 3024.645 | C17: =+'[1]1.1.1.3'!C17/Deflactores!$B17*100 -> 6563.8776 | D17: =+'[1]1.1.1.3'!D17/Deflactores!$B17*100 -> 580.0095 | E17: =+'[1]1.1.1.3'!E17/Deflactores!$B17*100 -> 1105.0503 | F17: =+'[1]1.1.1.3'!F17/Deflactores!$B17*100 -> 300.17722 | G17: =+'[1]1.1.1.3'!G17/Deflactores!$B17*100 -> 398.50205 | H17: =+'[1]1.1.1.3'!H17/Deflactores!$B17*100 -> 1512.8442 | I17: =+'[1]1.1.1.3'!I17/Deflactores!$B17*100 -> 608.0956 | ... Y17: =+'[1]1.1.1.3'!Y17/Deflactores!$B17*100 -> 1047.5875 | Z17: =SUM(B17:Y17) -> 34443.832
A18: 2000 | B18: =+'[1]1.1.1.3'!B18/Deflactores!$B18*100 -> 3753.9845 | C18: =+'[1]1.1.1.3'!C18/Deflactores!$B18*100 -> 9928.4807 | D18: =+'[1]1.1.1.3'!D18/Deflactores!$B18*100 -> 434.57614 | E18: =+'[1]1.1.1.3'!E18/Deflactores!$B18*100 -> 602.58241 | F18: =+'[1]1.1.1.3'!F18/Deflactores!$B18*100 -> 323.23443 | G18: =+'[1]1.1.1.3'!G18/Deflactores!$B18*100 -> 523.04411 | H18: =+'[1]1.1.1.3'!H18/Deflactores!$B18*100 -> 2932.0918 | I18: =+'[1]1.1.1.3'!I18/Deflactores!$B18*100 -> 594.97671 | ... Y18: =+'[1]1.1.1.3'!Y18/Deflactores!$B18*100 -> 1311.2566 | Z18: =SUM(B18:Y18) -> 47296.205
A19: 2001 | B19: =+'[1]1.1.1.3'!B19/Deflactores!$B19*100 -> 3412.8991 | C19: =+'[1]1.1.1.3'!C19/Deflactores!$B19*100 -> 8447.6333 | D19: =+'[1]1.1.1.3'!D19/Deflactores!$B19*100 -> 597.92912 | E19: =+'[1]1.1.1.3'!E19/Deflactores!$B19*100 -> 653.90567 | F19: =+'[1]1.1.1.3'!F19/Deflactores!$B19*100 -> 239.95964 | G19: =+'[1]1.1.1.3'!G19/Deflactores!$B19*100 -> 485.55114 | H19: =+'[1]1.1.1.3'!H19/Deflactores!$B19*100 -> 2649.9997 | I19: =+'[1]1.1.1.3'!I19/Deflactores!$B19*100 -> 587.65153 | ... Y19: =+'[1]1.1.1.3'!Y19/Deflactores!$B19*100 -> 1313.226 | Z19: =SUM(B19:Y19) -> 43936.065
A20: 2002 | B20: =+'[1]1.1.1.3'!B20/Deflactores!$B20*100 -> 2137.2443 | C20: =+'[1]1.1.1.3'!C20/Deflactores!$B20*100 -> 5376.9302 | D20: =+'[1]1.1.1.3'!D20/Deflactores!$B20*100 -> 499.57124 | E20: =+'[1]1.1.1.3'!E20/Deflactores!$B20*100 -> 612.78704 | F20: =+'[1]1.1.1.3'!F20/Deflactores!$B20*100 -> 122.86206 | G20: =+'[1]1.1.1.3'!G20/Deflactores!$B20*100 -> 329.76149 | H20: =+'[1]1.1.1.3'!H20/Deflactores!$B20*100 -> 5605.3998 | I20: =+'[1]1.1.1.3'!I20/Deflactores!$B20*100 -> 454.3146 | ... Y20: =+'[1]1.1.1.3'!Y20/Deflactores!$B20*100 -> 1561.61 | Z20: =SUM(B20:Y20) -> 43559.38
A21: 2003 | B21: =+'[1]1.1.1.3'!B21/Deflactores!$B21*100 -> 1895.3289 | C21: =+'[1]1.1.1.3'!C21/Deflactores!$B21*100 -> 7764.9429 | D21: =+'[1]1.1.1.3'!D21/Deflactores!$B21*100 -> 743.88179 | E21: =+'[1]1.1.1.3'!E21/Deflactores!$B21*100 -> 382.76332 | F21: =+'[1]1.1.1.3'!F21/Deflactores!$B21*100 -> 79.561735 | G21: =+'[1]1.1.1.3'!G21/Deflactores!$B21*100 -> 307.45239 | H21: =+'[1]1.1.1.3'!H21/Deflactores!$B21*100 -> 5608.6031 | I21: =+'[1]1.1.1.3'!I21/Deflactores!$B21*100 -> 306.95353 | ... Y21: =+'[1]1.1.1.3'!Y21/Deflactores!$B21*100 -> 1407.4592 | Z21: =SUM(B21:Y21) -> 48390.254
... A48: 2030 | B48: =+'[1]1.1.1.3'!B48/Deflactores!$B48*100 -> #N/A | C48: =+'[1]1.1.1.3'!C48/Deflactores!$B48*100 -> #N/A | D48: =+'[1]1.1.1.3'!D48/Deflactores!$B48*100 -> #N/A | E48: =+'[1]1.1.1.3'!E48/Deflactores!$B48*100 -> #N/A | F48: =+'[1]1.1.1.3'!F48/Deflactores!$B48*100 -> #N/A | G48: =+'[1]1.1.1.3'!G48/Deflactores!$B48*100 -> #N/A | H48: =+'[1]1.1.1.3'!H48/Deflactores!$B48*100 -> #N/A | I48: =+'[1]1.1.1.3'!I48/Deflactores!$B48*100 -> #N/A | ... Y48: =+'[1]1.1.1.3'!Y48/Deflactores!$B48*100 -> #N/A | Z48: =SUM(B48:Y48) -> #N/A

Sheet 1.1.1.3.1
A2: Título | B2: Regalías por provincia | N2: =B2 -> Regalías por provincia
A3: Fuente | B3: Dirección Nacional de Asuntos Provinciales - Ministerio de Economía de la Nación | N3: =B3 -> Dirección Nacional de Asuntos Provinciales - Ministerio de Economía de la Nación
A5: VOLVER AL ÍNDICE | B5: Administración Pública No Financiera | N5: =B5 -> Administración Pública No Financiera
A7: Unidad de medida | B7: Millones de pesos constantes de 2016 | C7: Millones de pesos constantes de 2016 | D7: Millones de pesos constantes de 2016 | E7: Millones de pesos constantes de 2016 | F7: Millones de pesos constantes de 2016 | G7: Millones de pesos constantes de 2016 | H7: Millones de pesos constantes de 2016 | I7: Millones de pesos constantes de 2016 | J7: Millones de pesos constantes de 2016 | K7: Millones de pesos constantes de 2016 | L7: Millones de pesos constantes de 2016 | M7: Millones de pesos constantes de 2016 | N7: Millones de pesos constantes de 2016 | O7: Millones de pesos constantes de 2016 | P7: Millones de pesos constantes de 2016 | Q7: Millones de pesos constantes de 2016 | R7: Millones de pesos constantes de 2016 | S7: Millones de pesos constantes de 2016 | T7: Millones de pesos constantes de 2016 | U7: Millones de pesos constantes de 2016 | V7: Millones de pesos constantes de 2016 | W7: Millones de pesos constantes de 2016 | X7: Millones de pesos constantes de 2016 | Y7: Millones de pesos constantes de 2016 | Z7: Millones de pesos constantes de 2016
A8: CÓDIGO | B8: 1.1.1.3.1.1 | C8: 1.1.1.3.1.2 | D8: 1.1.1.3.1.3 | E8: 1.1.1.3.1.4 | F8: 1.1.1.3.1.5 | G8: 1.1.1.3.1.6 | H8: 1.1.1.3.1.7 | I8: 1.1.1.3.1.8 | J8: 1.1.1.3.1.9 | K8: 1.1.1.3.1.10 | L8: 1.1.1.3.1.11 | M8: 1.1.1.3.1.12 | N8: 1.1.1.3.1.13 | O8: 1.1.1.3.1.14 | P8: 1.1.1.3.1.15 | Q8: 1.1.1.3.1.16 | R8: 1.1.1.3.1.17 | S8: 1.1.1.3.1.18 | T8: 1.1.1.3.1.19 | U8: 1.1.1.3.1.20 | V8: 1.1.1.3.1.21 | W8: 1.1.1.3.1.22 | X8: 1.1.1.3.1.23 | Y8: 1.1.1.3.1.24 | Z8: 1.1.1.3.1.25
A9: Jurisdicción | B9: C.A.B.A. | C9: Buenos Aires | D9: Catamarca | E9: Córdoba | F9: Corrientes | G9: Chaco | H9: Chubut | I9: Entre Ríos | J9: Formosa | K9: Jujuy | L9: La Pampa | M9: La Rioja | N9: Mendoza | O9: Misiones | P9: Neuquén | Q9: Río Negro | R9: Salta | S9: San Juan | T9: San Luis | U9: Santa Cruz | V9: Santa Fe | W9: Santiago del Estero | X9: Tucumán | Y9: Tierra del Fuego | Z9: Total
A10: 1992 | D10: =+'[1]1.1.1.3.1'!D10/Deflactores!$B10*100 -> 0 | E10: =+'[1]1.1.1.3.1'!E10/Deflactores!$B10*100 -> 0 | F10: =+'[1]1.1.1.3.1'!F10/Deflactores!$B10*100 -> 101.18206 | H10: =+'[1]1.1.1.3.1'!H10/Deflactores!$B10*100 -> 1157.5729 | I10: =+'[1]1.1.1.3.1'!I10/Deflactores!$B10*100 -> 101.71945 | J10: =+'[1]1.1.1.3.1'!J10/Deflactores!$B10*100 -> 98.249469 | K10: =+'[1]1.1.1.3.1'!K10/Deflactores!$B10*100 -> 10.421445 | L10: =+'[1]1.1.1.3.1'!L10/Deflactores!$B10*100 -> 141.37084 | N10: =+'[1]1.1.1.3.1'!N10/Deflactores!$B10*100 -> 1044.2076 | O10: =+'[1]1.1.1.3.1'!O10/Deflactores!$B10*100 -> 66.586316 | P10: =+'[1]1.1.1.3.1'!P10/Deflactores!$B10*100 -> 4030.3754 | Q10: =+'[1]1.1.1.3.1'!Q10/Deflactores!$B10*100 -> 913.51739 | R10: =+'[1]1.1.1.3.1'!R10/Deflactores!$B10*100 -> 296.82886 | S10: =+'[1]1.1.1.3.1'!S10/Deflactores!$B10*100 -> 13.77216 | U10: =+'[1]1.1.1.3.1'!U10/Deflactores!$B10*100 -> 1611.4811 | W10: =+'[1]1.1.1.3.1'!W10/Deflactores!$B10*100 -> 9.5961741 | X10: =+'[1]1.1.1.3.1'!X10/Deflactores!$B10*100 -> 0 | Y10: =+'[1]1.1.1.3.1'!Y10/Deflactores!$B10*100 -> 772.56133 | Z10: =SUM(B10:Y10) -> 10369.442
A11: 1993 | D11: =+'[1]1.1.1.3.1'!D11/Deflactores!$B11*100 -> 0 | E11: =+'[1]1.1.1.3.1'!E11/Deflactores!$B11*100 -> 0 | F11: =+'[1]1.1.1.3.1'!F11/Deflactores!$B11*100 -> 76.391565 | H11: =+'[1]1.1.1.3.1'!H11/Deflactores!$B11*100 -> 1187.8465 | I11: =+'[1]1.1.1.3.1'!I11/Deflactores!$B11*100 -> 99.817371 | J11: =+'[1]1.1.1.3.1'!J11/Deflactores!$B11*100 -> 64.986126 | K11: =+'[1]1.1.1.3.1'!K11/Deflactores!$B11*100 -> 7.9098711 | L11: =+'[1]1.1.1.3.1'!L11/Deflactores!$B11*100 -> 132.27763 | N11: =+'[1]1.1.1.3.1'!N11/Deflactores!$B11*100 -> 962.55148 | O11: =+'[1]1.1.1.3.1'!O11/Deflactores!$B11*100 -> 121.09129 | P11: =+'[1]1.1.1.3.1'!P11/Deflactores!$B11*100 -> 3735.0092 | Q11: =+'[1]1.1.1.3.1'!Q11/Deflactores!$B11*100 -> 788.80508 | R11: =+'[1]1.1.1.3.1'!R11/Deflactores!$B11*100 -> 281.00015 | S11: =+'[1]1.1.1.3.1'!S11/Deflactores!$B11*100 -> 28.424768 | U11: =+'[1]1.1.1.3.1'!U11/Deflactores!$B11*100 -> 1590.4816 | W11: =+'[1]1.1.1.3.1'!W11/Deflactores!$B11*100 -> 15.988932 | X11: =+'[1]1.1.1.3.1'!X11/Deflactores!$B11*100 -> 15.988932 | Y11: =+'[1]1.1.1.3.1'!Y11/Deflactores!$B11*100 -> 608.57478 | Z11: =SUM(B11:Y11) -> 9717.1453
A12: 1994 | D12: =+'[1]1.1.1.3.1'!D12/Deflactores!$B12*100 -> 0 | E12: =+'[1]1.1.1.3.1'!E12/Deflactores!$B12*100 -> 0 | F12: =+'[1]1.1.1.3.1'!F12/Deflactores!$B12*100 -> 144.26501 | H12: =+'[1]1.1.1.3.1'!H12/Deflactores!$B12*100 -> 1043.4857 | I12: =+'[1]1.1.1.3.1'!I12/Deflactores!$B12*100 -> 96.194006 | J12: =+'[1]1.1.1.3.1'!J12/Deflactores!$B12*100 -> 57.31769 | K12: =+'[1]1.1.1.3.1'!K12/Deflactores!$B12*100 -> 6.2384233 | L12: =+'[1]1.1.1.3.1'!L12/Deflactores!$B12*100 -> 103.02414 | N12: =+'[1]1.1.1.3.1'!N12/Deflactores!$B12*100 -> 1332.8928 | O12: =+'[1]1.1.1.3.1'!O12/Deflactores!$B12*100 -> 156.01839 | P12: =+'[1]1.1.1.3.1'!P12/Deflactores!$B12*100 -> 4114.0082 | Q12: =+'[1]1.1.1.3.1'!Q12/Deflactores!$B12*100 -> 673.8781 | R12: =+'[1]1.1.1.3.1'!R12/Deflactores!$B12*100 -> 309.47139 | S12: =+'[1]1.1.1.3.1'!S12/Deflactores!$B12*100 -> 0 | U12: =+'[1]1.1.1.3.1'!U12/Deflactores!$B12*100 -> 1437.8767 | W12: =+'[1]1.1.1.3.1'!W12/Deflactores!$B12*100 -> 0 | X12: =+'[1]1.1.1.3.1'!X12/Deflactores!$B12*100 -> 0 | Y12: =+'[1]1.1.1.3.1'!Y12/Deflactores!$B12*100 -> 550.91604 | Z12: =SUM(B12:Y12) -> 10025.587
A13: 1995 | D13: =+'[1]1.1.1.3.1'!D13/Deflactores!$B13*100 -> 0 | E13: =+'[1]1.1.1.3.1'!E13/Deflactores!$B13*100 -> 0 | F13: =+'[1]1.1.1.3.1'!F13/Deflactores!$B13*100 -> 98.787797 | H13: =+'[1]1.1.1.3.1'!H13/Deflactores!$B13*100 -> 1293.0318 | I13: =+'[1]1.1.1.3.1'!I13/Deflactores!$B13*100 -> 96.671463 | J13: =+'[1]1.1.1.3.1'!J13/Deflactores!$B13*100 -> 49.32804 | K13: =+'[1]1.1.1.3.1'!K13/Deflactores!$B13*100 -> 5.0214186 | L13: =+'[1]1.1.1.3.1'!L13/Deflactores!$B13*100 -> 97.355373 | N13: =+'[1]1.1.1.3.1'!N13/Deflactores!$B13*100 -> 894.98288 | O13: =+'[1]1.1.1.3.1'!O13/Deflactores!$B13*100 -> 97.915171 | P13: =+'[1]1.1.1.3.1'!P13/Deflactores!$B13*100 -> 4386.6392 | Q13: =+'[1]1.1.1.3.1'!Q13/Deflactores!$B13*100 -> 585.18598 | R13: =+'[1]1.1.1.3.1'!R13/Deflactores!$B13*100 -> 351.92158 | S13: =+'[1]1.1.1.3.1'!S13/Deflactores!$B13*100 -> 26.343412 | U13: =+'[1]1.1.1.3.1'!U13/Deflactores!$B13*100 -> 2137.7487 | W13: =+'[1]1.1.1.3.1'!W13/Deflactores!$B13*100 -> 0 | X13: =+'[1]1.1.1.3.1'!X13/Deflactores!$B13*100 -> 0 | Y13: =+'[1]1.1.1.3.1'!Y13/Deflactores!$B13*100 -> 496.24403 | Z13: =SUM(B13:Y13) -> 10617.177
A14: 1996 | D14: =+'[1]1.1.1.3.1'!D14/Deflactores!$B14*100 -> 0 | E14: =+'[1]1.1.1.3.1'!E14/Deflactores!$B14*100 -> 0 | F14: =+'[1]1.1.1.3.1'!F14/Deflactores!$B14*100 -> 119.46064 | H14: =+'[1]1.1.1.3.1'!H14/Deflactores!$B14*100 -> 1450.8556 | I14: =+'[1]1.1.1.3.1'!I14/Deflactores!$B14*100 -> 107.22573 | J14: =+'[1]1.1.1.3.1'!J14/Deflactores!$B14*100 -> 54.985041 | K14: =+'[1]1.1.1.3.1'!K14/Deflactores!$B14*100 -> 3.267085 | L14: =+'[1]1.1.1.3.1'!L14/Deflactores!$B14*100 -> 127.12603 | N14: =+'[1]1.1.1.3.1'!N14/Deflactores!$B14*100 -> 1230.1273 | O14: =+'[1]1.1.1.3.1'!O14/Deflactores!$B14*100 -> 69.86279 | P14: =+'[1]1.1.1.3.1'!P14/Deflactores!$B14*100 -> 5332.9457 | Q14: =+'[1]1.1.1.3.1'!Q14/Deflactores!$B14*100 -> 543.79843 | R14: =+'[1]1.1.1.3.1'!R14/Deflactores!$B14*100 -> 402.4133 | S14: =+'[1]1.1.1.3.1'!S14/Deflactores!$B14*100 -> 16.335425 | U14: =+'[1]1.1.1.3.1'!U14/Deflactores!$B14*100 -> 2885.5548 | W14: =+'[1]1.1.1.3.1'!W14/Deflactores!$B14*100 -> 0 | X14: =+'[1]1.1.1.3.1'!X14/Deflactores!$B14*100 -> 0 | Y14: =+'[1]1.1.1.3.1'!Y14/Deflactores!$B14*100 -> 593.93662 | Z14: =SUM(B14:Y14) -> 12937.895
A15: 1997 | D15: =+'[1]1.1.1.3.1'!D15/Deflactores!$B15*100 -> 0 | E15: =+'[1]1.1.1.3.1'!E15/Deflactores!$B15*100 -> 0 | F15: =+'[1]1.1.1.3.1'!F15/Deflactores!$B15*100 -> 154.04812 | H15: =+'[1]1.1.1.3.1'!H15/Deflactores!$B15*100 -> 1552.835 | I15: =+'[1]1.1.1.3.1'!I15/Deflactores!$B15*100 -> 126.5028 | J15: =+'[1]1.1.1.3.1'!J15/Deflactores!$B15*100 -> 50.546015 | K15: =+'[1]1.1.1.3.1'!K15/Deflactores!$B15*100 -> 5.052056 | L15: =+'[1]1.1.1.3.1'!L15/Deflactores!$B15*100 -> 186.46411 | N15: =+'[1]1.1.1.3.1'!N15/Deflactores!$B15*100 -> 1366.7846 | O15: =+'[1]1.1.1.3.1'!O15/Deflactores!$B15*100 -> 91.31985 | P15: =+'[1]1.1.1.3.1'!P15/Deflactores!$B15*100 -> 5832.8351 | Q15: =+'[1]1.1.1.3.1'!Q15/Deflactores!$B15*100 -> 684.72016 | R15: =+'[1]1.1.1.3.1'!R15/Deflactores!$B15*100 -> 546.29996 | S15: =+'[1]1.1.1.3.1'!S15/Deflactores!$B15*100 -> 0 | U15: =+'[1]1.1.1.3.1'!U15/Deflactores!$B15*100 -> 2867.2696 | W15: =+'[1]1.1.1.3.1'!W15/Deflactores!$B15*100 -> 0 | X15: =+'[1]1.1.1.3.1'!X15/Deflactores!$B15*100 -> 0 | Y15: =+'[1]1.1.1.3.1'!Y15/Deflactores!$B15*100 -> 686.28558 | Z15: =SUM(B15:Y15) -> 14150.963
A16: 1998 | D16: =+'[1]1.1.1.3.1'!D16/Deflactores!$B16*100 -> 0 | E16: =+'[1]1.1.1.3.1'!E16/Deflactores!$B16*100 -> 0 | F16: =+'[1]1.1.1.3.1'!F16/Deflactores!$B16*100 -> 182.97149 | H16: =+'[1]1.1.1.3.1'!H16/Deflactores!$B16*100 -> 883.94787 | I16: =+'[1]1.1.1.3.1'!I16/Deflactores!$B16*100 -> 295.96775 | J16: =+'[1]1.1.1.3.1'!J16/Deflactores!$B16*100 -> 31.180274 | K16: =+'[1]1.1.1.3.1'!K16/Deflactores!$B16*100 -> 1.6623709 | L16: =+'[1]1.1.1.3.1'!L16/Deflactores!$B16*100 -> 92.118791 | N16: =+'[1]1.1.1.3.1'!N16/Deflactores!$B16*100 -> 1012.5398 | O16: =+'[1]1.1.1.3.1'!O16/Deflactores!$B16*100 -> 103.77919 | P16: =+'[1]1.1.1.3.1'!P16/Deflactores!$B16*100 -> 4712.3888 | Q16: =+'[1]1.1.1.3.1'!Q16/Deflactores!$B16*100 -> 473.29593 | R16: =+'[1]1.1.1.3.1'!R16/Deflactores!$B16*100 -> 545.49283 | S16: =+'[1]1.1.1.3.1'!S16/Deflactores!$B16*100 -> 0 | U16: =+'[1]1.1.1.3.1'!U16/Deflactores!$B16*100 -> 1979.4881 | W16: =+'[1]1.1.1.3.1'!W16/Deflactores!$B16*100 -> 5.1834724 | X16: =+'[1]1.1.1.3.1'!X16/Deflactores!$B16*100 -> 0 | Y16: =+'[1]1.1.1.3.1'!Y16/Deflactores!$B16*100 -> 627.51962 | Z16: =SUM(B16:Y16) -> 10947.536
A17: 1999 | D17: =+'[1]1.1.1.3.1'!D17/Deflactores!$B17*100 -> 0 | E17: =+'[1]1.1.1.3.1'!E17/Deflactores!$B17*100 -> 0 | F17: =+'[1]1.1.1.3.1'!F17/Deflactores!$B17*100 -> 209.20741 | H17: =+'[1]1.1.1.3.1'!H17/Deflactores!$B17*100 -> 1230.8161 | I17: =+'[1]1.1.1.3.1'!I17/Deflactores!$B17*100 -> 277.21485 | J17: =+'[1]1.1.1.3.1'!J17/Deflactores!$B17*100 -> 44.030618 | K17: =+'[1]1.1.1.3.1'!K17/Deflactores!$B17*100 -> 5.5713316 | L17: =+'[1]1.1.1.3.1'!L17/Deflactores!$B17*100 -> 117.28746 | N17: =+'[1]1.1.1.3.1'!N17/Deflactores!$B17*100 -> 1242.3914 | O17: =+'[1]1.1.1.3.1'!O17/Deflactores!$B17*100 -> 167.00394 | P17: =+'[1]1.1.1.3.1'!P17/Deflactores!$B17*100 -> 5788.9659 | Q17: =+'[1]1.1.1.3.1'!Q17/Deflactores!$B17*100 -> 563.54138 | R17: =+'[1]1.1.1.3.1'!R17/Deflactores!$B17*100 -> 690.66715 | S17: =+'[1]1.1.1.3.1'!S17/Deflactores!$B17*100 -> 0 | U17: =+'[1]1.1.1.3.1'!U17/Deflactores!$B17*100 -> 2256.5452 | W17: =+'[1]1.1.1.3.1'!W17/Deflactores!$B17*100 -> 6.8854227 | X17: =+'[1]1.1.1.3.1'!X17/Deflactores!$B17*100 -> 0 | Y17: =+'[1]1.1.1.3.1'!Y17/Deflactores!$B17*100 -> 745.32416 | Z17: =SUM(B17:Y17) -> 13345.452
A18: 2000 | D18: =+'[1]1.1.1.3.1'!D18/Deflactores!$B18*100 -> 0 | E18: =+'[1]1.1.1.3.1'!E18/Deflactores!$B18*100 -> 0 | F18: =+'[1]1.1.1.3.1'!F18/Deflactores!$B18*100 -> 135.15011 | H18: =+'[1]1.1.1.3.1'!H18/Deflactores!$B18*100 -> 2567.2398 | I18: =+'[1]1.1.1.3.1'!I18/Deflactores!$B18*100 -> 366.12734 | J18: =+'[1]1.1.1.3.1'!J18/Deflactores!$B18*100 -> 81.777072 | K18: =+'[1]1.1.1.3.1'!K18/Deflactores!$B18*100 -> 10.165713 | L18: =+'[1]1.1.1.3.1'!L18/Deflactores!$B18*100 -> 364.6046 | N18: =+'[1]1.1.1.3.1'!N18/Deflactores!$B18*100 -> 2253.4129 | O18: =+'[1]1.1.1.3.1'!O18/Deflactores!$B18*100 -> 177.93053 | P18: =+'[1]1.1.1.3.1'!P18/Deflactores!$B18*100 -> 8966.2253 | Q18: =+'[1]1.1.1.3.1'!Q18/Deflactores!$B18*100 -> 1215.5704 | R18: =+'[1]1.1.1.3.1'!R18/Deflactores!$B18*100 -> 1006.7486 | S18: =+'[1]1.1.1.3.1'!S18/Deflactores!$B18*100 -> 0 | U18: =+'[1]1.1.1.3.1'!U18/Deflactores!$B18*100 -> 3167.1072 | W18: =+'[1]1.1.1.3.1'!W18/Deflactores!$B18*100 -> 7.9862902 | X18: =+'[1]1.1.1.3.1'!X18/Deflactores!$B18*100 -> 0 | Y18: =+'[1]1.1.1.3.1'!Y18/Deflactores!$B18*100 -> 1092.4206 | Z18: =SUM(B18:Y18) -> 21412.467
A19: 2001 | D19: =+'[1]1.1.1.3.1'!D19/Deflactores!$B19*100 -> 0 | E19: =+'[1]1.1.1.3.1'!E19/Deflactores!$B19*100 -> 0 | F19: =+'[1]1.1.1.3.1'!F19/Deflactores!$B19*100 -> 116.52835 | H19: =+'[1]1.1.1.3.1'!H19/Deflactores!$B19*100 -> 2320.9229 | I19: =+'[1]1.1.1.3.1'!I19/Deflactores!$B19*100 -> 230.81156 | J19: =+'[1]1.1.1.3.1'!J19/Deflactores!$B19*100 -> 67.216453 | K19: =+'[1]1.1.1.3.1'!K19/Deflactores!$B19*100 -> 9.3905738 | L19: =+'[1]1.1.1.3.1'!L19/Deflactores!$B19*100 -> 362.67476 | N19: =+'[1]1.1.1.3.1'!N19/Deflactores!$B19*100 -> 2146.9596 | O19: =+'[1]1.1.1.3.1'!O19/Deflactores!$B19*100 -> 145.00181 | P19: =+'[1]1.1.1.3.1'!P19/Deflactores!$B19*100 -> 8612.59 | Q19: =+'[1]1.1.1.3.1'!Q19/Deflactores!$B19*100 -> 1231.4628 | R19: =+'[1]1.1.1.3.1'!R19/Deflactores!$B19*100 -> 685.63138 | S19: =+'[1]1.1.1.3.1'!S19/Deflactores!$B19*100 -> 0 | U19: =+'[1]1.1.1.3.1'!U19/Deflactores!$B19*100 -> 3514.8641 | W19: =+'[1]1.1.1.3.1'!W19/Deflactores!$B19*100 -> 6.4174178 | X19: =+'[1]1.1.1.3.1'!X19/Deflactores!$B19*100 -> 0 | Y19: =+'[1]1.1.1.3.1'!Y19/Deflactores!$B19*100 -> 1058.7384 | Z19: =SUM(B19:Y19) -> 20509.21
A20: 2002 | D20: =+'[1]1.1.1.3.1'!D20/Deflactores!$B20*100 -> 0 | E20: =+'[1]1.1.1.3.1'!E20/Deflactores!$B20*100 -> 0 | F20: =+'[1]1.1.1.3.1'!F20/Deflactores!$B20*100 -> 0 | H20: =+'[1]1.1.1.3.1'!H20/Deflactores!$B20*100 -> 4961.5264 | I20: =+'[1]1.1.1.3.1'!I20/Deflactores!$B20*100 -> 300.90889 | J20: =+'[1]1.1.1.3.1'!J20/Deflactores!$B20*100 -> 93.745103 | K20: =+'[1]1.1.1.3.1'!K20/Deflactores!$B20*100 -> 14.350542 | L20: =+'[1]1.1.1.3.1'!L20/Deflactores!$B20*100 -> 245.3875 | N20: =+'[1]1.1.1.3.1'!N20/Deflactores!$B20*100 -> 4070.6181 | O20: =+'[1]1.1.1.3.1'!O20/Deflactores!$B20*100 -> 107.42298 | P20: =+'[1]1.1.1.3.1'!P20/Deflactores!$B20*100 -> 10955.431 | Q20: =+'[1]1.1.1.3.1'!Q20/Deflactores!$B20*100 -> 1633.1473 | R20: =+'[1]1.1.1.3.1'!R20/Deflactores!$B20*100 -> 318.80792 | S20: =+'[1]1.1.1.3.1'!S20/Deflactores!$B20*100 -> 0 | U20: =+'[1]1.1.1.3.1'!U20/Deflactores!$B20*100 -> 4028.4121 | W20: =+'[1]1.1.1.3.1'!W20/Deflactores!$B20*100 -> 7.1839487 | X20: =+'[1]1.1.1.3.1'!X20/Deflactores!$B20*100 -> 0 | Y20: =+'[1]1.1.1.3.1'!Y20/Deflactores!$B20*100 -> 1345.5494 | Z20: =SUM(B20:Y20) -> 28082.491
A21: 2003 | D21: =+'[1]1.1.1.3.1'!D21/Deflactores!$B21*100 -> 231.51641 | E21: =+'[1]1.1.1.3.1'!E21/Deflactores!$B21*100 -> 0 | F21: =+'[1]1.1.1.3.1'!F21/Deflactores!$B21*100 -> 0 | H21: =+'[1]1.1.1.3.1'!H21/Deflactores!$B21*100 -> 5270.6039 | I21: =+'[1]1.1.1.3.1'!I21/Deflactores!$B21*100 -> 89.046074 | J21: =+'[1]1.1.1.3.1'!J21/Deflactores!$B21*100 -> 120.9183 | K21: =+'[1]1.1.1.3.1'!K21/Deflactores!$B21*100 -> 15.532223 | L21: =+'[1]1.1.1.3.1'!L21/Deflactores!$B21*100 -> 296.68031 | N21: =+'[1]1.1.1.3.1'!N21/Deflactores!$B21*100 -> 3805.8178 | O21: =+'[1]1.1.1.3.1'!O21/Deflactores!$B21*100 -> 162.79297 | P21: =+'[1]1.1.1.3.1'!P21/Deflactores!$B21*100 -> 11680.992 | Q21: =+'[1]1.1.1.3.1'!Q21/Deflactores!$B21*100 -> 1670.1931 | R21: =+'[1]1.1.1.3.1'!R21/Deflactores!$B21*100 -> 264.2573 | S21: =+'[1]1.1.1.3.1'!S21/Deflactores!$B21*100 -> 0 | U21: =+'[1]1.1.1.3.1'!U21/Deflactores!$B21*100 -> 5659.4337 | W21: =+'[1]1.1.1.3.1'!W21/Deflactores!$B21*100 -> 1.6432373 | X21: =+'[1]1.1.1.3.1'!X21/Deflactores!$B21*100 -> 0 | Y21: =+'[1]1.1.1.3.1'!Y21/Deflactores!$B21*100 -> 1172.8329 | Z21: =SUM(B21:Y21) -> 30442.26
... A26: 2008 | D26: =+'[1]1.1.1.3.1'!D26/Deflactores!$B26*100 -> 787.14573 | E26: =+'[1]1.1.1.3.1'!E26/Deflactores!$B26*100 -> 0 | F26: =+'[1]1.1.1.3.1'!F26/Deflactores!$B26*100 -> 104.89453 | H26: =+'[1]1.1.1.3.1'!H26/Deflactores!$B26*100 -> 8260.9496 | I26: =+'[1]1.1.1.3.1'!I26/Deflactores!$B26*100 -> 983.12911 | J26: =+'[1]1.1.1.3.1'!J26/Deflactores!$B26*100 -> 76.813838 | K26: =+'[1]1.1.1.3.1'!K26/Deflactores!$B26*100 -> 13.235513 | L26: =+'[1]1.1.1.3.1'!L26/Deflactores!$B26*100 -> 493.78925 | N26: =+'[1]1.1.1.3.1'!N26/Deflactores!$B26*100 -> 4666.7118 | O26: =+'[1]1.1.1.3.1'!O26/Deflactores!$B26*100 -> 264.2599 | P26: =+'[1]1.1.1.3.1'!P26/Deflactores!$B26*100 -> 12393.105 | Q26: =+'[1]1.1.1.3.1'!Q26/Deflactores!$B26*100 -> 1994.1098 | R26: =+'[1]1.1.1.3.1'!R26/Deflactores!$B26*100 -> 1096.9816 | S26: =+'[1]1.1.1.3.1'!S26/Deflactores!$B26*100 -> 408.94596 | U26: =+'[1]1.1.1.3.1'!U26/Deflactores!$B26*100 -> 4906.613 | W26: =+'[1]1.1.1.3.1'!W26/Deflactores!$B26*100 -> 8.0611545 | X26: =+'[1]1.1.1.3.1'!X26/Deflactores!$B26*100 -> 0 | Y26: =+'[1]1.1.1.3.1'!Y26/Deflactores!$B26*100 -> 1426.778 | Z26: =SUM(B26:Y26) -> 37885.524
A27: 2009 | D27: =+'[1]1.1.1.3.1'!D27/Deflactores!$B27*100 -> 416.12091 | E27: =+'[1]1.1.1.3.1'!E27/Deflactores!$B27*100 -> 0 | F27: =+'[1]1.1.1.3.1'!F27/Deflactores!$B27*100 -> 115.50704 | G27: =+'[1]1.1.1.3.1'!G27/Deflactores!$B27*100 -> 0.47344555 | H27: =+'[1]1.1.1.3.1'!H27/Deflactores!$B27*100 -> 7870.4031 | I27: =+'[1]1.1.1.3.1'!I27/Deflactores!$B27*100 -> 1201.9571 | J27: =+'[1]1.1.1.3.1'!J27/Deflactores!$B27*100 -> 92.982474 | K27: =+'[1]1.1.1.3.1'!K27/Deflactores!$B27*100 -> 11.359448 | L27: =+'[1]1.1.1.3.1'!L27/Deflactores!$B27*100 -> 466.28077 | N27: =+'[1]1.1.1.3.1'!N27/Deflactores!$B27*100 -> 4313.1707 | O27: =+'[1]1.1.1.3.1'!O27/Deflactores!$B27*100 -> 566.46552 | P27: =+'[1]1.1.1.3.1'!P27/Deflactores!$B27*100 -> 10967.64 | Q27: =+'[1]1.1.1.3.1'!Q27/Deflactores!$B27*100 -> 2043.8029 | R27: =+'[1]1.1.1.3.1'!R27/Deflactores!$B27*100 -> 2290.5041 | S27: =+'[1]1.1.1.3.1'!S27/Deflactores!$B27*100 -> 348.18446 | U27: =+'[1]1.1.1.3.1'!U27/Deflactores!$B27*100 -> 5922.8831 | W27: =+'[1]1.1.1.3.1'!W27/Deflactores!$B27*100 -> 10.953753 | X27: =+'[1]1.1.1.3.1'!X27/Deflactores!$B27*100 -> 0 | Y27: =+'[1]1.1.1.3.1'!Y27/Deflactores!$B27*100 -> 1454.2759 | Z27: =SUM(B27:Y27) -> 38092.965
A28: 2010 | D28: =+'[1]1.1.1.3.1'!D28/Deflactores!$B28*100 -> 568.42921 | E28: =+'[1]1.1.1.3.1'!E28/Deflactores!$B28*100 -> 0 | F28: =+'[1]1.1.1.3.1'!F28/Deflactores!$B28*100 -> 84.62567 | G28: =+'[1]1.1.1.3.1'!G28/Deflactores!$B28*100 -> 0 | H28: =+'[1]1.1.1.3.1'!H28/Deflactores!$B28*100 -> 8089.6856 | I28: =+'[1]1.1.1.3.1'!I28/Deflactores!$B28*100 -> 838.03052 | J28: =+'[1]1.1.1.3.1'!J28/Deflactores!$B28*100 -> 92.7161 | K28: =+'[1]1.1.1.3.1'!K28/Deflactores!$B28*100 -> 9.9754282 | L28: =+'[1]1.1.1.3.1'!L28/Deflactores!$B28*100 -> 754.30643 | N28: =+'[1]1.1.1.3.1'!N28/Deflactores!$B28*100 -> 4100.1374 | O28: =+'[1]1.1.1.3.1'!O28/Deflactores!$B28*100 -> 448.98882 | P28: =+'[1]1.1.1.3.1'!P28/Deflactores!$B28*100 -> 9702.2932 | Q28: =+'[1]1.1.1.3.1'!Q28/Deflactores!$B28*100 -> 2075.7972 | R28: =+'[1]1.1.1.3.1'!R28/Deflactores!$B28*100 -> 1425.1199 | S28: =+'[1]1.1.1.3.1'!S28/Deflactores!$B28*100 -> 947.4726 | U28: =+'[1]1.1.1.3.1'!U28/Deflactores!$B28*100 -> 5196.4741 | W28: =+'[1]1.1.1.3.1'!W28/Deflactores!$B28*100 -> 7.238095 | X28: =+'[1]1.1.1.3.1'!X28/Deflactores!$B28*100 -> 0 | Y28: =+'[1]1.1.1.3.1'!Y28/Deflactores!$B28*100 -> 1310.1377 | Z28: =SUM(B28:Y28) -> 35651.428
A29: 2011 | D29: =+'[1]1.1.1.3.1'!D29/Deflactores!$B29*100 -> 789.93556 | E29: =+'[1]1.1.1.3.1'!E29/Deflactores!$B29*100 -> 0 | F29: =+'[1]1.1.1.3.1'!F29/Deflactores!$B29*100 -> 291.94105 | G29: =+'[1]1.1.1.3.1'!G29/Deflactores!$B29*100 -> 0 | H29: =+'[1]1.1.1.3.1'!H29/Deflactores!$B29*100 -> 7983.4202 | I29: =+'[1]1.1.1.3.1'!I29/Deflactores!$B29*100 -> 1207.3981 | J29: =+'[1]1.1.1.3.1'!J29/Deflactores!$B29*100 -> 80.898402 | K29: =+'[1]1.1.1.3.1'!K29/Deflactores!$B29*100 -> 11.944453 | L29: =+'[1]1.1.1.3.1'!L29/Deflactores!$B29*100 -> 791.99829 | N29: =+'[1]1.1.1.3.1'!N29/Deflactores!$B29*100 -> 3759.0125 | O29: =+'[1]1.1.1.3.1'!O29/Deflactores!$B29*100 -> 181.45486 | P29: =+'[1]1.1.1.3.1'!P29/Deflactores!$B29*100 -> 9077.469 | Q29: =+'[1]1.1.1.3.1'!Q29/Deflactores!$B29*100 -> 2288.2412 | R29: =+'[1]1.1.1.3.1'!R29/Deflactores!$B29*100 -> 1070.7632 | S29: =+'[1]1.1.1.3.1'!S29/Deflactores!$B29*100 -> 766.31424 | U29: =+'[1]1.1.1.3.1'!U29/Deflactores!$B29*100 -> 3813.9226 | W29: =+'[1]1.1.1.3.1'!W29/Deflactores!$B29*100 -> 8.349483 | X29: =+'[1]1.1.1.3.1'!X29/Deflactores!$B29*100 -> 0 | Y29: =+'[1]1.1.1.3.1'!Y29/Deflactores!$B29*100 -> 1166.9963 | Z29: =SUM(B29:Y29) -> 33290.059
A30: 2012 | D30: =+'[1]1.1.1.3.1'!D30/Deflactores!$B30*100 -> 479.98944 | E30: =+'[1]1.1.1.3.1'!E30/Deflactores!$B30*100 -> 0 | F30: =+'[1]1.1.1.3.1'!F30/Deflactores!$B30*100 -> 145.60186 | G30: =+'[1]1.1.1.3.1'!G30/Deflactores!$B30*100 -> 0 | H30: =+'[1]1.1.1.3.1'!H30/Deflactores!$B30*100 -> 7461.2098 | I30: =+'[1]1.1.1.3.1'!I30/Deflactores!$B30*100 -> 1200.3114 | J30: =+'[1]1.1.1.3.1'!J30/Deflactores!$B30*100 -> 118.61203 | K30: =+'[1]1.1.1.3.1'!K30/Deflactores!$B30*100 -> 12.904519 | L30: =+'[1]1.1.1.3.1'!L30/Deflactores!$B30*100 -> 1012.5245 | N30: =+'[1]1.1.1.3.1'!N30/Deflactores!$B30*100 -> 3733.4881 | O30: =+'[1]1.1.1.3.1'!O30/Deflactores!$B30*100 -> 396.32628 | P30: =+'[1]1.1.1.3.1'!P30/Deflactores!$B30*100 -> 8378.1233 | Q30: =+'[1]1.1.1.3.1'!Q30/Deflactores!$B30*100 -> 2420.5932 | R30: =+'[1]1.1.1.3.1'!R30/Deflactores!$B30*100 -> 898.56236 | S30: =+'[1]1.1.1.3.1'!S30/Deflactores!$B30*100 -> 1042.9395 | U30: =+'[1]1.1.1.3.1'!U30/Deflactores!$B30*100 -> 5727.1192 | W30: =+'[1]1.1.1.3.1'!W30/Deflactores!$B30*100 -> 7.514326 | X30: =+'[1]1.1.1.3.1'!X30/Deflactores!$B30*100 -> 0 | Y30: =+'[1]1.1.1.3.1'!Y30/Deflactores!$B30*100 -> 1240.7555 | Z30: =SUM(B30:Y30) -> 34276.575
A31: 2013 | D31: =+'[1]1.1.1.3.1'!D31/Deflactores!$B31*100 -> 251.97595 | E31: =+'[1]1.1.1.3.1'!E31/Deflactores!$B31*100 -> 0 | F31: =+'[1]1.1.1.3.1'!F31/Deflactores!$B31*100 -> 55.195079 | G31: =+'[1]1.1.1.3.1'!G31/Deflactores!$B31*100 -> 0 | H31: =+'[1]1.1.1.3.1'!H31/Deflactores!$B31*100 -> 6519.0908 | I31: =+'[1]1.1.1.3.1'!I31/Deflactores!$B31*100 -> 462.64064 | J31: =+'[1]1.1.1.3.1'!J31/Deflactores!$B31*100 -> 110.37811 | K31: =+'[1]1.1.1.3.1'!K31/Deflactores!$B31*100 -> 13.604863 | L31: =+'[1]1.1.1.3.1'!L31/Deflactores!$B31*100 -> 1039.3278 | N31: =+'[1]1.1.1.3.1'!N31/Deflactores!$B31*100 -> 3706.296 | O31: =+'[1]1.1.1.3.1'!O31/Deflactores!$B31*100 -> 148.54459 | P31: =+'[1]1.1.1.3.1'!P31/Deflactores!$B31*100 -> 7459.8396 | Q31: =+'[1]1.1.1.3.1'!Q31/Deflactores!$B31*100 -> 2480.4558 | R31: =+'[1]1.1.1.3.1'!R31/Deflactores!$B31*100 -> 753.62227 | S31: =+'[1]1.1.1.3.1'!S31/Deflactores!$B31*100 -> 579.13045 | U31: =+'[1]1.1.1.3.1'!U31/Deflactores!$B31*100 -> 6212.1355 | W31: =+'[1]1.1.1.3.1'!W31/Deflactores!$B31*100 -> 3.325912 | X31: =+'[1]1.1.1.3.1'!X31/Deflactores!$B31*100 -> 0 | Y31: =+'[1]1.1.1.3.1'!Y31/Deflactores!$B31*100 -> 1107.7458 | Z31: =SUM(B31:Y31) -> 30903.309
A32: 2014 | D32: =+'[1]1.1.1.3.1'!D32/Deflactores!$B32*100 -> 314.19141 | E32: =+'[1]1.1.1.3.1'!E32/Deflactores!$B32*100 -> 0 | F32: =+'[1]1.1.1.3.1'!F32/Deflactores!$B32*100 -> 332.28837 | G32: =+'[1]1.1.1.3.1'!G32/Deflactores!$B32*100 -> 0 | H32: =+'[1]1.1.1.3.1'!H32/Deflactores!$B32*100 -> 7322.2598 | I32: =+'[1]1.1.1.3.1'!I32/Deflactores!$B32*100 -> 416.88887 | J32: =+'[1]1.1.1.3.1'!J32/Deflactores!$B32*100 -> 111.18765 | K32: =+'[1]1.1.1.3.1'!K32/Deflactores!$B32*100 -> 14.585668 | L32: =+'[1]1.1.1.3.1'!L32/Deflactores!$B32*100 -> 1041.9869 | N32: =+'[1]1.1.1.3.1'!N32/Deflactores!$B32*100 -> 3949.9949 | O32: =+'[1]1.1.1.3.1'!O32/Deflactores!$B32*100 -> 118.74512 | P32: =+'[1]1.1.1.3.1'!P32/Deflactores!$B32*100 -> 8713.3938 | Q32: =+'[1]1.1.1.3.1'!Q32/Deflactores!$B32*100 -> 2614.1386 | R32: =+'[1]1.1.1.3.1'!R32/Deflactores!$B32*100 -> 801.72193 | S32: =+'[1]1.1.1.3.1'!S32/Deflactores!$B32*100 -> 581.82103 | U32: =+'[1]1.1.1.3.1'!U32/Deflactores!$B32*100 -> 6483.7473 | W32: =+'[1]1.1.1.3.1'!W32/Deflactores!$B32*100 -> 1.4658234 | X32: =+'[1]1.1.1.3.1'!X32/Deflactores!$B32*100 -> 0 | Y32: =+'[1]1.1.1.3.1'!Y32/Deflactores!$B32*100 -> 1036.5461 | Z32: =SUM(B32:Y32) -> 33854.963
A33: 2015 | D33: =+'[1]1.1.1.3.1'!D33/Deflactores!$B33*100 -> 145.74896 | E33: =+'[1]1.1.1.3.1'!E33/Deflactores!$B33*100 -> 0 | F33: =+'[1]1.1.1.3.1'!F33/Deflactores!$B33*100 -> 102.05477 | G33: =+'[1]1.1.1.3.1'!G33/Deflactores!$B33*100 -> 0 | H33: =+'[1]1.1.1.3.1'!H33/Deflactores!$B33*100 -> 5387.7483 | I33: =+'[1]1.1.1.3.1'!I33/Deflactores!$B33*100 -> 199.9804 | J33: =+'[1]1.1.1.3.1'!J33/Deflactores!$B33*100 -> 91.877844 | K33: =+'[1]1.1.1.3.1'!K33/Deflactores!$B33*100 -> 13.376068 | L33: =+'[1]1.1.1.3.1'!L33/Deflactores!$B33*100 -> 846.77957 | N33: =+'[1]1.1.1.3.1'!N33/Deflactores!$B33*100 -> 3389.3722 | O33: =+'[1]1.1.1.3.1'!O33/Deflactores!$B33*100 -> 120.53487 | P33: =+'[1]1.1.1.3.1'!P33/Deflactores!$B33*100 -> 7577.3083 | Q33: =+'[1]1.1.1.3.1'!Q33/Deflactores!$B33*100 -> 4540.4311 | R33: =+'[1]1.1.1.3.1'!R33/Deflactores!$B33*100 -> 710.43807 | S33: =+'[1]1.1.1.3.1'!S33/Deflactores!$B33*100 -> 514.16685 | U33: =+'[1]1.1.1.3.1'!U33/Deflactores!$B33*100 -> 5385.7534 | W33: =+'[1]1.1.1.3.1'!W33/Deflactores!$B33*100 -> 4.1149976 | X33: =+'[1]1.1.1.3.1'!X33/Deflactores!$B33*100 -> 0 | Y33: =+'[1]1.1.1.3.1'!Y33/Deflactores!$B33*100 -> 742.85637 | Z33: =SUM(B33:Y33) -> 29772.542
A34: 2016 | D34: =+'[1]1.1.1.3.1'!D34/Deflactores!$B34*100 -> 63.030679 | E34: =+'[1]1.1.1.3.1'!E34/Deflactores!$B34*100 -> 0 | F34: =+'[1]1.1.1.3.1'!F34/Deflactores!$B34*100 -> 141.89422 | G34: =+'[1]1.1.1.3.1'!G34/Deflactores!$B34*100 -> 0 | H34: =+'[1]1.1.1.3.1'!H34/Deflactores!$B34*100 -> 4791.3805 | I34: =+'[1]1.1.1.3.1'!I34/Deflactores!$B34*100 -> 135.55634 | J34: =+'[1]1.1.1.3.1'!J34/Deflactores!$B34*100 -> 68.276734 | K34: =+'[1]1.1.1.3.1'!K34/Deflactores!$B34*100 -> 14.566688 | L34: =+'[1]1.1.1.3.1'!L34/Deflactores!$B34*100 -> 667.00278 | N34: =+'[1]1.1.1.3.1'!N34/Deflactores!$B34*100 -> 3348.812 | O34: =+'[1]1.1.1.3.1'!O34/Deflactores!$B34*100 -> 36.922428 | P34: =+'[1]1.1.1.3.1'!P34/Deflactores!$B34*100 -> 8558.8081 | Q34: =+'[1]1.1.1.3.1'!Q34/Deflactores!$B34*100 -> 2330.1884 | R34: =+'[1]1.1.1.3.1'!R34/Deflactores!$B34*100 -> 805.66005 | S34: =+'[1]1.1.1.3.1'!S34/Deflactores!$B34*100 -> 471.75672 | U34: =+'[1]1.1.1.3.1'!U34/Deflactores!$B34*100 -> 5399.5411 | W34: =+'[1]1.1.1.3.1'!W34/Deflactores!$B34*100 -> 2.7983102 | X34: =+'[1]1.1.1.3.1'!X34/Deflactores!$B34*100 -> 0 | Y34: =+'[1]1.1.1.3.1'!Y34/Deflactores!$B34*100 -> 1029.4194 | Z34: =SUM(B34:Y34) -> 27865.614
A35: 2017 | D35: =+'[1]1.1.1.3.1'!D35/Deflactores!$B35*100 -> 186.311 | E35: =+'[1]1.1.1.3.1'!E35/Deflactores!$B35*100 -> 0 | F35: =+'[1]1.1.1.3.1'!F35/Deflactores!$B35*100 -> 241.95934 | G35: =+'[1]1.1.1.3.1'!G35/Deflactores!$B35*100 -> 0 | H35: =+'[1]1.1.1.3.1'!H35/Deflactores!$B35*100 -> 4109.4607 | I35: =+'[1]1.1.1.3.1'!I35/Deflactores!$B35*100 -> 110.32725 | J35: =+'[1]1.1.1.3.1'!J35/Deflactores!$B35*100 -> 36.736888 | K35: =+'[1]1.1.1.3.1'!K35/Deflactores!$B35*100 -> 4.9190279 | L35: =+'[1]1.1.1.3.1'!L35/Deflactores!$B35*100 -> 243.35193 | N35: =+'[1]1.1.1.3.1'!N35/Deflactores!$B35*100 -> 2614.0388 | O35: =+'[1]1.1.1.3.1'!O35/Deflactores!$B35*100 -> 129.50082 | P35: =+'[1]1.1.1.3.1'!P35/Deflactores!$B35*100 -> 7940.9192 | Q35: =+'[1]1.1.1.3.1'!Q35/Deflactores!$B35*100 -> 1932.5786 | R35: =+'[1]1.1.1.3.1'!R35/Deflactores!$B35*100 -> 802.70475 | S35: =+'[1]1.1.1.3.1'!S35/Deflactores!$B35*100 -> 492.40294 | U35: =+'[1]1.1.1.3.1'!U35/Deflactores!$B35*100 -> 4112.4043 | W35: =+'[1]1.1.1.3.1'!W35/Deflactores!$B35*100 -> 0.90480228 | X35: =+'[1]1.1.1.3.1'!X35/Deflactores!$B35*100 -> 0 | Y35: =+'[1]1.1.1.3.1'!Y35/Deflactores!$B35*100 -> 1074.5042 | Z35: =SUM(B35:Y35) -> 24033.025
A36: 2018 | D36: =+'[1]1.1.1.3.1'!D36/Deflactores!$B36*100 -> 87.093966 | E36: =+'[1]1.1.1.3.1'!E36/Deflactores!$B36*100 -> 0 | F36: =+'[1]1.1.1.3.1'!F36/Deflactores!$B36*100 -> 115.11106 | G36: =+'[1]1.1.1.3.1'!G36/Deflactores!$B36*100 -> 0 | H36: =+'[1]1.1.1.3.1'!H36/Deflactores!$B36*100 -> 7079.0759 | I36: =+'[1]1.1.1.3.1'!I36/Deflactores!$B36*100 -> 65.687827 | J36: =+'[1]1.1.1.3.1'!J36/Deflactores!$B36*100 -> 47.606583 | K36: =+'[1]1.1.1.3.1'!K36/Deflactores!$B36*100 -> 1.0476704 | L36: =+'[1]1.1.1.3.1'!L36/Deflactores!$B36*100 -> 371.13659 | N36: =+'[1]1.1.1.3.1'!N36/Deflactores!$B36*100 -> 3763.4412 | O36: =+'[1]1.1.1.3.1'!O36/Deflactores!$B36*100 -> 91.367906 | P36: =+'[1]1.1.1.3.1'!P36/Deflactores!$B36*100 -> 13162.611 | Q36: =+'[1]1.1.1.3.1'!Q36/Deflactores!$B36*100 -> 2908.3184 | R36: =+'[1]1.1.1.3.1'!R36/Deflactores!$B36*100 -> 936.25976 | S36: =+'[1]1.1.1.3.1'!S36/Deflactores!$B36*100 -> 484.34999 | U36: =+'[1]1.1.1.3.1'!U36/Deflactores!$B36*100 -> 6394.3372 | W36: =+'[1]1.1.1.3.1'!W36/Deflactores!$B36*100 -> 2.3752604 | X36: =+'[1]1.1.1.3.1'!X36/Deflactores!$B36*100 -> 0 | Y36: =+'[1]1.1.1.3.1'!Y36/Deflactores!$B36*100 -> 1650.8832 | Z36: =SUM(B36:Y36) -> 37160.704
A37: 2019 | D37: =+'[1]1.1.1.3.1'!D37/Deflactores!$B37*100 -> 248.74445 | E37: =+'[1]1.1.1.3.1'!E37/Deflactores!$B37*100 -> 0 | F37: =+'[1]1.1.1.3.1'!F37/Deflactores!$B37*100 -> 7.1498194 | G37: =+'[1]1.1.1.3.1'!G37/Deflactores!$B37*100 -> 0 | H37: =+'[1]1.1.1.3.1'!H37/Deflactores!$B37*100 -> 6710.3004 | I37: =+'[1]1.1.1.3.1'!I37/Deflactores!$B37*100 -> 192.57337 | J37: =+'[1]1.1.1.3.1'!J37/Deflactores!$B37*100 -> 37.040785 | K37: =+'[1]1.1.1.3.1'!K37/Deflactores!$B37*100 -> 1.8603321e-17 | L37: =+'[1]1.1.1.3.1'!L37/Deflactores!$B37*100 -> 346.68228 | N37: =+'[1]1.1.1.3.1'!N37/Deflactores!$B37*100 -> 3069.7838 | O37: =+'[1]1.1.1.3.1'!O37/Deflactores!$B37*100 -> 398.89918 | P37: =+'[1]1.1.1.3.1'!P37/Deflactores!$B37*100 -> 12891.144 | Q37: =+'[1]1.1.1.3.1'!Q37/Deflactores!$B37*100 -> 2339.7231 | R37: =+'[1]1.1.1.3.1'!R37/Deflactores!$B37*100 -> 838.9515 | S37: =+'[1]1.1.1.3.1'!S37/Deflactores!$B37*100 -> 568.21126 | U37: =+'[1]1.1.1.3.1'!U37/Deflactores!$B37*100 -> 6156.2664 | W37: =+'[1]1.1.1.3.1'!W37/Deflactores!$B37*100 -> 2.4738209 | X37: =+'[1]1.1.1.3.1'!X37/Deflactores!$B37*100 -> 0 | Y37: =+'[1]1.1.1.3.1'!Y37/Deflactores!$B37*100 -> 1345.7296 | Z37: =SUM(B37:Y37) -> 35153.674
A38: 2020 | D38: =+'[1]1.1.1.3.1'!D38/Deflactores!$B38*100 -> 89.24508 | E38: =+'[1]1.1.1.3.1'!E38/Deflactores!$B38*100 -> 0 | F38: =+'[1]1.1.1.3.1'!F38/Deflactores!$B38*100 -> 11.396946 | G38: =+'[1]1.1.1.3.1'!G38/Deflactores!$B38*100 -> 0 | H38: =+'[1]1.1.1.3.1'!H38/Deflactores!$B38*100 -> 5235.499 | I38: =+'[1]1.1.1.3.1'!I38/Deflactores!$B38*100 -> 215.25093 | J38: =+'[1]1.1.1.3.1'!J38/Deflactores!$B38*100 -> 23.645103 | K38: =+'[1]1.1.1.3.1'!K38/Deflactores!$B38*100 -> 26.609092 | L38: =+'[1]1.1.1.3.1'!L38/Deflactores!$B38*100 -> 213.54616 | N38: =+'[1]1.1.1.3.1'!N38/Deflactores!$B38*100 -> 2189.4585 | O38: =+'[1]1.1.1.3.1'!O38/Deflactores!$B38*100 -> 261.99637 | P38: =+'[1]1.1.1.3.1'!P38/Deflactores!$B38*100 -> 9677.8363 | Q38: =+'[1]1.1.1.3.1'!Q38/Deflactores!$B38*100 -> 1596.309 | R38: =+'[1]1.1.1.3.1'!R38/Deflactores!$B38*100 -> 562.33877 | S38: =+'[1]1.1.1.3.1'!S38/Deflactores!$B38*100 -> 516.07531 | U38: =+'[1]1.1.1.3.1'!U38/Deflactores!$B38*100 -> 4239.7569 | W38: =+'[1]1.1.1.3.1'!W38/Deflactores!$B38*100 -> 0.53922169 | X38: =+'[1]1.1.1.3.1'!X38/Deflactores!$B38*100 -> 0 | Y38: =+'[1]1.1.1.3.1'!Y38/Deflactores!$B38*100 -> 844.67956 | Z38: =SUM(B38:Y38) -> 25704.182
... A42: 2024 | D42: =+'[1]1.1.1.3.1'!D42/Deflactores!$B42*100 -> 78.691064 | E42: =+'[1]1.1.1.3.1'!E42/Deflactores!$B42*100 -> 0 | F42: =+'[1]1.1.1.3.1'!F42/Deflactores!$B42*100 -> 114.41812 | G42: =+'[1]1.1.1.3.1'!G42/Deflactores!$B42*100 -> 0 | H42: =+'[1]1.1.1.3.1'!H42/Deflactores!$B42*100 -> 5414.2117 | I42: =+'[1]1.1.1.3.1'!I42/Deflactores!$B42*100 -> 338.58446 | J42: =+'[1]1.1.1.3.1'!J42/Deflactores!$B42*100 -> 28.311008 | K42: =+'[1]1.1.1.3.1'!K42/Deflactores!$B42*100 -> 173.39253 | L42: =+'[1]1.1.1.3.1'!L42/Deflactores!$B42*100 -> #N/A | N42: =+'[1]1.1.1.3.1'!N42/Deflactores!$B42*100 -> 2216.5901 | O42: =+'[1]1.1.1.3.1'!O42/Deflactores!$B42*100 -> 241.7658 | P42: =+'[1]1.1.1.3.1'!P42/Deflactores!$B42*100 -> 22177.776 | Q42: =+'[1]1.1.1.3.1'!Q42/Deflactores!$B42*100 -> 1348.9224 | R42: =+'[1]1.1.1.3.1'!R42/Deflactores!$B42*100 -> 450.03731 | S42: =+'[1]1.1.1.3.1'!S42/Deflactores!$B42*100 -> 596.86681 | U42: =+'[1]1.1.1.3.1'!U42/Deflactores!$B42*100 -> 4866.5347 | W42: =+'[1]1.1.1.3.1'!W42/Deflactores!$B42*100 -> 0 | X42: =+'[1]1.1.1.3.1'!X42/Deflactores!$B42*100 -> 0 | Y42: =+'[1]1.1.1.3.1'!Y42/Deflactores!$B42*100 -> 677.78461 | Z42: =SUM(B42:Y42) -> #N/A
A43: 2025 | B43: #N/A | C43: #N/A | D43: =+'[1]1.1.1.3.1'!D43/Deflactores!$B43*100 -> 89.318148 | E43: =+'[1]1.1.1.3.1'!E43/Deflactores!$B43*100 -> 0 | F43: =+'[1]1.1.1.3.1'!F43/Deflactores!$B43*100 -> 311.43874 | G43: =+'[1]1.1.1.3.1'!G43/Deflactores!$B43*100 -> 0 | H43: =+'[1]1.1.1.3.1'!H43/Deflactores!$B43*100 -> 4553.0081 | I43: =+'[1]1.1.1.3.1'!I43/Deflactores!$B43*100 -> 300.32711 | J43: =+'[1]1.1.1.3.1'!J43/Deflactores!$B43*100 -> 21.470563 | K43: =+'[1]1.1.1.3.1'!K43/Deflactores!$B43*100 -> 223.9795 | ... Y43: =+'[1]1.1.1.3.1'!Y43/Deflactores!$B43*100 -> 395.17559 | Z43: =SUM(B43:Y43) -> #N/A
A44: 2026 | B44: #N/A | C44: #N/A | D44: =+'[1]1.1.1.3.1'!D44/Deflactores!$B44*100 -> #N/A | E44: =+'[1]1.1.1.3.1'!E44/Deflactores!$B44*100 -> #N/A | F44: =+'[1]1.1.1.3.1'!F44/Deflactores!$B44*100 -> #N/A | G44: =+'[1]1.1.1.3.1'!G44/Deflactores!$B44*100 -> #N/A | H44: =+'[1]1.1.1.3.1'!H44/Deflactores!$B44*100 -> #N/A | I44: =+'[1]1.1.1.3.1'!I44/Deflactores!$B44*100 -> #N/A | J44: =+'[1]1.1.1.3.1'!J44/Deflactores!$B44*100 -> #N/A | K44: =+'[1]1.1.1.3.1'!K44/Deflactores!$B44*100 -> #N/A | ... Y44: =+'[1]1.1.1.3.1'!Y44/Deflactores!$B44*100 -> #N/A | Z44: =SUM(B44:Y44) -> #N/A
A45: 2027 | B45: #N/A | C45: #N/A | D45: =+'[1]1.1.1.3.1'!D45/Deflactores!$B45*100 -> #N/A | E45: =+'[1]1.1.1.3.1'!E45/Deflactores!$B45*100 -> #N/A | F45: =+'[1]1.1.1.3.1'!F45/Deflactores!$B45*100 -> #N/A | G45: =+'[1]1.1.1.3.1'!G45/Deflactores!$B45*100 -> #N/A | H45: =+'[1]1.1.1.3.1'!H45/Deflactores!$B45*100 -> #N/A | I45: =+'[1]1.1.1.3.1'!I45/Deflactores!$B45*100 -> #N/A | J45: =+'[1]1.1.1.3.1'!J45/Deflactores!$B45*100 -> #N/A | K45: =+'[1]1.1.1.3.1'!K45/Deflactores!$B45*100 -> #N/A | ... Y45: =+'[1]1.1.1.3.1'!Y45/Deflactores!$B45*100 -> #N/A | Z45: =SUM(B45:Y45) -> #N/A
A46: 2028 | B46: #N/A | C46: #N/A | D46: =+'[1]1.1.1.3.1'!D46/Deflactores!$B46*100 -> #N/A | E46: =+'[1]1.1.1.3.1'!E46/Deflactores!$B46*100 -> #N/A | F46: =+'[1]1.1.1.3.1'!F46/Deflactores!$B46*100 -> #N/A | G46: =+'[1]1.1.1.3.1'!G46/Deflactores!$B46*100 -> #N/A | H46: =+'[1]1.1.1.3.1'!H46/Deflactores!$B46*100 -> #N/A | I46: =+'[1]1.1.1.3.1'!I46/Deflactores!$B46*100 -> #N/A | J46: =+'[1]1.1.1.3.1'!J46/Deflactores!$B46*100 -> #N/A | K46: =+'[1]1.1.1.3.1'!K46/Deflactores!$B46*100 -> #N/A | ... Y46: =+'[1]1.1.1.3.1'!Y46/Deflactores!$B46*100 -> #N/A | Z46: =SUM(B46:Y46) -> #N/A
A47: 2029 | B47: #N/A | C47: #N/A | D47: =+'[1]1.1.1.3.1'!D47/Deflactores!$B47*100 -> #N/A | E47: =+'[1]1.1.1.3.1'!E47/Deflactores!$B47*100 -> #N/A | F47: =+'[1]1.1.1.3.1'!F47/Deflactores!$B47*100 -> #N/A | G47: =+'[1]1.1.1.3.1'!G47/Deflactores!$B47*100 -> #N/A | H47: =+'[1]1.1.1.3.1'!H47/Deflactores!$B47*100 -> #N/A | I47: =+'[1]1.1.1.3.1'!I47/Deflactores!$B47*100 -> #N/A | J47: =+'[1]1.1.1.3.1'!J47/Deflactores!$B47*100 -> #N/A | K47: =+'[1]1.1.1.3.1'!K47/Deflactores!$B47*100 -> #N/A | ... Y47: =+'[1]1.1.1.3.1'!Y47/Deflactores!$B47*100 -> #N/A | Z47: =SUM(B47:Y47) -> #N/A
A48: 2030 | B48: #N/A | C48: #N/A | D48: =+'[1]1.1.1.3.1'!D48/Deflactores!$B48*100 -> #N/A | E48: =+'[1]1.1.1.3.1'!E48/Deflactores!$B48*100 -> #N/A | F48: =+'[1]1.1.1.3.1'!F48/Deflactores!$B48*100 -> #N/A | G48: =+'[1]1.1.1.3.1'!G48/Deflactores!$B48*100 -> #N/A | H48: =+'[1]1.1.1.3.1'!H48/Deflactores!$B48*100 -> #N/A | I48: =+'[1]1.1.1.3.1'!I48/Deflactores!$B48*100 -> #N/A | J48: =+'[1]1.1.1.3.1'!J48/Deflactores!$B48*100 -> #N/A | K48: =+'[1]1.1.1.3.1'!K48/Deflactores!$B48*100 -> #N/A | ... Y48: =+'[1]1.1.1.3.1'!Y48/Deflactores!$B48*100 -> #N/A | Z48: =SUM(B48:Y48) -> #N/A

Sheet 1.1.1.4
A2: Título | B2: Venta de Bienes y Servicios de la Administración Pública por provincia | N2: =B2 -> Venta de Bienes y Servicios de la Administración Pública por provincia
A3: Fuente | B3: Dirección Nacional de Asuntos Provinciales - Ministerio de Economía de la Nación | N3: =B3 -> Dirección Nacional de Asuntos Provinciales - Ministerio de Economía de la Nación
A5: VOLVER AL ÍNDICE | B5: Administración Pública No Financiera | N5: =B5 -> Administración Pública No Financiera
A7: Unidad de medida | B7: Millones de pesos constantes de 2016 | C7: Millones de pesos constantes de 2016 | D7: Millones de pesos constantes de 2016 | E7: Millones de pesos constantes de 2016 | F7: Millones de pesos constantes de 2016 | G7: Millones de pesos constantes de 2016 | H7: Millones de pesos constantes de 2016 | I7: Millones de pesos constantes de 2016 | J7: Millones de pesos constantes de 2016 | K7: Millones de pesos constantes de 2016 | L7: Millones de pesos constantes de 2016 | M7: Millones de pesos constantes de 2016 | N7: Millones de pesos constantes de 2016 | O7: Millones de pesos constantes de 2016 | P7: Millones de pesos constantes de 2016 | Q7: Millones de pesos constantes de 2016 | R7: Millones de pesos constantes de 2016 | S7: Millones de pesos constantes de 2016 | T7: Millones de pesos constantes de 2016 | U7: Millones de pesos constantes de 2016 | V7: Millones de pesos constantes de 2016 | W7: Millones de pesos constantes de 2016 | X7: Millones de pesos constantes de 2016 | Y7: Millones de pesos constantes de 2016 | Z7: Millones de pesos constantes de 2016
A8: CÓDIGO | B8: 1.1.1.4.1 | C8: 1.1.1.4.2 | D8: 1.1.1.4.3 | E8: 1.1.1.4.4 | F8: 1.1.1.4.5 | G8: 1.1.1.4.6 | H8: 1.1.1.4.7 | I8: 1.1.1.4.8 | J8: 1.1.1.4.9 | K8: 1.1.1.4.10 | L8: 1.1.1.4.11 | M8: 1.1.1.4.12 | N8: 1.1.1.4.13 | O8: 1.1.1.4.14 | P8: 1.1.1.4.15 | Q8: 1.1.1.4.16 | R8: 1.1.1.4.17 | S8: 1.1.1.4.18 | T8: 1.1.1.4.19 | U8: 1.1.1.4.20 | V8: 1.1.1.4.21 | W8: 1.1.1.4.22 | X8: 1.1.1.4.23 | Y8: 1.1.1.4.24 | Z8: 1.1.1.4.25
A9: Jurisdicción | B9: C.A.B.A. | C9: Buenos Aires | D9: Catamarca | E9: Córdoba | F9: Corrientes | G9: Chaco | H9: Chubut | I9: Entre Ríos | J9: Formosa | K9: Jujuy | L9: La Pampa | M9: La Rioja | N9: Mendoza | O9: Misiones | P9: Neuquén | Q9: Río Negro | R9: Salta | S9: San Juan | T9: San Luis | U9: Santa Cruz | V9: Santa Fe | W9: Santiago del Estero | X9: Tucumán | Y9: Tierra del Fuego | Z9: Total
A10: 1992
A11: 1993
A12: 1994
A13: 1995
A14: 1996 | B14: =+'[1]1.1.1.4'!B14/Deflactores!$B14*100 -> 1128.4022 | C14: =+'[1]1.1.1.4'!C14/Deflactores!$B14*100 -> 3835.5415 | E14: =+'[1]1.1.1.4'!E14/Deflactores!$B14*100 -> 733.0687 | F14: =+'[1]1.1.1.4'!F14/Deflactores!$B14*100 -> 75.191962 | G14: =+'[1]1.1.1.4'!G14/Deflactores!$B14*100 -> 55.788744 | H14: =+'[1]1.1.1.4'!H14/Deflactores!$B14*100 -> 47.64096 | I14: =+'[1]1.1.1.4'!I14/Deflactores!$B14*100 -> 109.51269 | M14: =+'[1]1.1.1.4'!M14/Deflactores!$B14*100 -> 1.1125327 | N14: =+'[1]1.1.1.4'!N14/Deflactores!$B14*100 -> 507.93371 | O14: =+'[1]1.1.1.4'!O14/Deflactores!$B14*100 -> 29.384679 | P14: =+'[1]1.1.1.4'!P14/Deflactores!$B14*100 -> 286.8664 | Q14: =+'[1]1.1.1.4'!Q14/Deflactores!$B14*100 -> 394.42798 | R14: =+'[1]1.1.1.4'!R14/Deflactores!$B14*100 -> 76.776498 | T14: =+'[1]1.1.1.4'!T14/Deflactores!$B14*100 -> 21.818568 | V14: =+'[1]1.1.1.4'!V14/Deflactores!$B14*100 -> 747.3457 | W14: =+'[1]1.1.1.4'!W14/Deflactores!$B14*100 -> 156.46146 | X14: =+'[1]1.1.1.4'!X14/Deflactores!$B14*100 -> 421.9767 | Y14: =+'[1]1.1.1.4'!Y14/Deflactores!$B14*100 -> 111.85764 | Z14: =SUM(B14:Y14) -> 8741.1086
A15: 1997 | B15: =+'[1]1.1.1.4'!B15/Deflactores!$B15*100 -> 948.0391 | C15: =+'[1]1.1.1.4'!C15/Deflactores!$B15*100 -> 1304.0405 | D15: =+'[1]1.1.1.4'!D15/Deflactores!$B15*100 -> 32.533357 | E15: =+'[1]1.1.1.4'!E15/Deflactores!$B15*100 -> 551.89606 | F15: =+'[1]1.1.1.4'!F15/Deflactores!$B15*100 -> 58.776635 | G15: =+'[1]1.1.1.4'!G15/Deflactores!$B15*100 -> 131.90531 | H15: =+'[1]1.1.1.4'!H15/Deflactores!$B15*100 -> 72.496286 | I15: =+'[1]1.1.1.4'!I15/Deflactores!$B15*100 -> 253.13453 | M15: =+'[1]1.1.1.4'!M15/Deflactores!$B15*100 -> 1.9010406 | N15: =+'[1]1.1.1.4'!N15/Deflactores!$B15*100 -> 424.83927 | O15: =+'[1]1.1.1.4'!O15/Deflactores!$B15*100 -> 51.406767 | P15: =+'[1]1.1.1.4'!P15/Deflactores!$B15*100 -> 162.59352 | Q15: =+'[1]1.1.1.4'!Q15/Deflactores!$B15*100 -> 581.43143 | R15: =+'[1]1.1.1.4'!R15/Deflactores!$B15*100 -> 173.67972 | T15: =+'[1]1.1.1.4'!T15/Deflactores!$B15*100 -> 11.983428 | V15: =+'[1]1.1.1.4'!V15/Deflactores!$B15*100 -> 355.64759 | W15: =+'[1]1.1.1.4'!W15/Deflactores!$B15*100 -> 6.1654529 | X15: =+'[1]1.1.1.4'!X15/Deflactores!$B15*100 -> 346.70112 | Y15: =+'[1]1.1.1.4'!Y15/Deflactores!$B15*100 -> 139.70035 | Z15: =SUM(B15:Y15) -> 5608.8715
A16: 1998 | B16: =+'[1]1.1.1.4'!B16/Deflactores!$B16*100 -> 852.31351 | C16: =+'[1]1.1.1.4'!C16/Deflactores!$B16*100 -> 1493.2984 | D16: =+'[1]1.1.1.4'!D16/Deflactores!$B16*100 -> 14.240069 | E16: =+'[1]1.1.1.4'!E16/Deflactores!$B16*100 -> 1204.1725 | F16: =+'[1]1.1.1.4'!F16/Deflactores!$B16*100 -> 19.746522 | G16: =+'[1]1.1.1.4'!G16/Deflactores!$B16*100 -> 4.3022593 | H16: =+'[1]1.1.1.4'!H16/Deflactores!$B16*100 -> 120.47819 | I16: =+'[1]1.1.1.4'!I16/Deflactores!$B16*100 -> 189.91356 | J16: =+'[1]1.1.1.4'!J16/Deflactores!$B16*100 -> 3.976154 | M16: =+'[1]1.1.1.4'!M16/Deflactores!$B16*100 -> 0.75593163 | N16: =+'[1]1.1.1.4'!N16/Deflactores!$B16*100 -> 408.02885 | O16: =+'[1]1.1.1.4'!O16/Deflactores!$B16*100 -> 8.942174 | P16: =+'[1]1.1.1.4'!P16/Deflactores!$B16*100 -> 148.89169 | Q16: =+'[1]1.1.1.4'!Q16/Deflactores!$B16*100 -> 367.81662 | R16: =+'[1]1.1.1.4'!R16/Deflactores!$B16*100 -> 44.980592 | S16: =+'[1]1.1.1.4'!S16/Deflactores!$B16*100 -> 74.800731 | T16: =+'[1]1.1.1.4'!T16/Deflactores!$B16*100 -> 94.689508 | V16: =+'[1]1.1.1.4'!V16/Deflactores!$B16*100 -> 502.30244 | W16: =+'[1]1.1.1.4'!W16/Deflactores!$B16*100 -> 3.7728959 | X16: =+'[1]1.1.1.4'!X16/Deflactores!$B16*100 -> 2.4770248 | Y16: =+'[1]1.1.1.4'!Y16/Deflactores!$B16*100 -> 0 | Z16: =SUM(B16:Y16) -> 5559.8996
A17: 1999 | B17: =+'[1]1.1.1.4'!B17/Deflactores!$B17*100 -> 693.20803 | C17: =+'[1]1.1.1.4'!C17/Deflactores!$B17*100 -> 1569.277 | D17: =+'[1]1.1.1.4'!D17/Deflactores!$B17*100 -> 10.604128 | E17: =+'[1]1.1.1.4'!E17/Deflactores!$B17*100 -> 1508.3206 | F17: =+'[1]1.1.1.4'!F17/Deflactores!$B17*100 -> 0.13466375 | G17: =+'[1]1.1.1.4'!G17/Deflactores!$B17*100 -> 3.7400637 | H17: =+'[1]1.1.1.4'!H17/Deflactores!$B17*100 -> 141.39613 | I17: =+'[1]1.1.1.4'!I17/Deflactores!$B17*100 -> 253.95946 | J17: =+'[1]1.1.1.4'!J17/Deflactores!$B17*100 -> 0 | M17: =+'[1]1.1.1.4'!M17/Deflactores!$B17*100 -> 50.803765 | N17: =+'[1]1.1.1.4'!N17/Deflactores!$B17*100 -> 376.82554 | O17: =+'[1]1.1.1.4'!O17/Deflactores!$B17*100 -> 97.41607 | P17: =+'[1]1.1.1.4'!P17/Deflactores!$B17*100 -> 294.681 | Q17: =+'[1]1.1.1.4'!Q17/Deflactores!$B17*100 -> 60.276868 | R17: =+'[1]1.1.1.4'!R17/Deflactores!$B17*100 -> 21.78878 | S17: =+'[1]1.1.1.4'!S17/Deflactores!$B17*100 -> 0 | T17: =+'[1]1.1.1.4'!T17/Deflactores!$B17*100 -> 152.3212 | ... Y17: =+'[1]1.1.1.4'!Y17/Deflactores!$B17*100 -> 113.09988 | Z17: =SUM(B17:Y17) -> 6135.6943
A18: 2000 | B18: =+'[1]1.1.1.4'!B18/Deflactores!$B18*100 -> 692.03827 | C18: =+'[1]1.1.1.4'!C18/Deflactores!$B18*100 -> 2304.8682 | D18: =+'[1]1.1.1.4'!D18/Deflactores!$B18*100 -> 6.6011174 | E18: =+'[1]1.1.1.4'!E18/Deflactores!$B18*100 -> 1623.3956 | F18: =+'[1]1.1.1.4'!F18/Deflactores!$B18*100 -> 0.16279321 | G18: =+'[1]1.1.1.4'!G18/Deflactores!$B18*100 -> 0.56739621 | H18: =+'[1]1.1.1.4'!H18/Deflactores!$B18*100 -> 135.91628 | I18: =+'[1]1.1.1.4'!I18/Deflactores!$B18*100 -> 306.93831 | J18: =+'[1]1.1.1.4'!J18/Deflactores!$B18*100 -> 0.6676694 | M18: =+'[1]1.1.1.4'!M18/Deflactores!$B18*100 -> 65.259977 | N18: =+'[1]1.1.1.4'!N18/Deflactores!$B18*100 -> 448.93474 | O18: =+'[1]1.1.1.4'!O18/Deflactores!$B18*100 -> 28.89521 | P18: =+'[1]1.1.1.4'!P18/Deflactores!$B18*100 -> 209.78064 | Q18: =+'[1]1.1.1.4'!Q18/Deflactores!$B18*100 -> 0 | R18: =+'[1]1.1.1.4'!R18/Deflactores!$B18*100 -> 15.155249 | S18: =+'[1]1.1.1.4'!S18/Deflactores!$B18*100 -> 0 | T18: =+'[1]1.1.1.4'!T18/Deflactores!$B18*100 -> 144.02858 | ... Y18: =+'[1]1.1.1.4'!Y18/Deflactores!$B18*100 -> 664.59191 | Z18: =SUM(B18:Y18) -> 7179.7183
A19: 2001 | B19: =+'[1]1.1.1.4'!B19/Deflactores!$B19*100 -> 692.8875 | C19: =+'[1]1.1.1.4'!C19/Deflactores!$B19*100 -> 1440.2415 | D19: =+'[1]1.1.1.4'!D19/Deflactores!$B19*100 -> 5.7719872 | E19: =+'[1]1.1.1.4'!E19/Deflactores!$B19*100 -> 923.03145 | F19: =+'[1]1.1.1.4'!F19/Deflactores!$B19*100 -> 0.0017753969 | G19: =+'[1]1.1.1.4'!G19/Deflactores!$B19*100 -> 0.59166879 | H19: =+'[1]1.1.1.4'!H19/Deflactores!$B19*100 -> 127.95062 | I19: =+'[1]1.1.1.4'!I19/Deflactores!$B19*100 -> 214.09386 | J19: =+'[1]1.1.1.4'!J19/Deflactores!$B19*100 -> 0 | L19: =+'[1]1.1.1.4'!L19/Deflactores!$B19*100 -> 506.71637 | M19: =+'[1]1.1.1.4'!M19/Deflactores!$B19*100 -> 19.18033 | N19: =+'[1]1.1.1.4'!N19/Deflactores!$B19*100 -> 518.23365 | O19: =+'[1]1.1.1.4'!O19/Deflactores!$B19*100 -> 3.4992425 | P19: =+'[1]1.1.1.4'!P19/Deflactores!$B19*100 -> 213.62563 | Q19: =+'[1]1.1.1.4'!Q19/Deflactores!$B19*100 -> 0 | R19: =+'[1]1.1.1.4'!R19/Deflactores!$B19*100 -> 21.655321 | S19: =+'[1]1.1.1.4'!S19/Deflactores!$B19*100 -> 0 | ... Y19: =+'[1]1.1.1.4'!Y19/Deflactores!$B19*100 -> 651.28223 | Z19: =SUM(B19:Y19) -> 6069.2773
A20: 2002 | B20: =+'[1]1.1.1.4'!B20/Deflactores!$B20*100 -> 229.11076 | C20: =+'[1]1.1.1.4'!C20/Deflactores!$B20*100 -> 949.57727 | D20: =+'[1]1.1.1.4'!D20/Deflactores!$B20*100 -> 3.8538834 | E20: =+'[1]1.1.1.4'!E20/Deflactores!$B20*100 -> 825.73168 | F20: =+'[1]1.1.1.4'!F20/Deflactores!$B20*100 -> 0.01575309 | G20: =+'[1]1.1.1.4'!G20/Deflactores!$B20*100 -> 0.44160999 | H20: =+'[1]1.1.1.4'!H20/Deflactores!$B20*100 -> 90.897581 | I20: =+'[1]1.1.1.4'!I20/Deflactores!$B20*100 -> 181.74125 | J20: =+'[1]1.1.1.4'!J20/Deflactores!$B20*100 -> 0 | L20: =+'[1]1.1.1.4'!L20/Deflactores!$B20*100 -> 296.5259 | M20: =+'[1]1.1.1.4'!M20/Deflactores!$B20*100 -> 25.36881 | N20: =+'[1]1.1.1.4'!N20/Deflactores!$B20*100 -> 383.76099 | O20: =+'[1]1.1.1.4'!O20/Deflactores!$B20*100 -> 2.8451558 | P20: =+'[1]1.1.1.4'!P20/Deflactores!$B20*100 -> 137.55074 | Q20: =+'[1]1.1.1.4'!Q20/Deflactores!$B20*100 -> 0 | R20: =+'[1]1.1.1.4'!R20/Deflactores!$B20*100 -> 34.029931 | S20: =+'[1]1.1.1.4'!S20/Deflactores!$B20*100 -> 0 | ... Y20: =+'[1]1.1.1.4'!Y20/Deflactores!$B20*100 -> 428.67251 | Z20: =SUM(B20:Y20) -> 3990.4963
A21: 2003 | B21: =+'[1]1.1.1.4'!B21/Deflactores!$B21*100 -> 391.34489 | C21: =+'[1]1.1.1.4'!C21/Deflactores!$B21*100 -> 1592.8088 | D21: =+'[1]1.1.1.4'!D21/Deflactores!$B21*100 -> 27.51219 | E21: =+'[1]1.1.1.4'!E21/Deflactores!$B21*100 -> 949.46645 | F21: =+'[1]1.1.1.4'!F21/Deflactores!$B21*100 -> 82.040739 | G21: =+'[1]1.1.1.4'!G21/Deflactores!$B21*100 -> 1.8178138 | H21: =+'[1]1.1.1.4'!H21/Deflactores!$B21*100 -> 120.03339 | I21: =+'[1]1.1.1.4'!I21/Deflactores!$B21*100 -> 187.84342 | J21: =+'[1]1.1.1.4'!J21/Deflactores!$B21*100 -> 0 | L21: =+'[1]1.1.1.4'!L21/Deflactores!$B21*100 -> 326.90917 | M21: =+'[1]1.1.1.4'!M21/Deflactores!$B21*100 -> 42.008676 | N21: =+'[1]1.1.1.4'!N21/Deflactores!$B21*100 -> 458.96483 | O21: =+'[1]1.1.1.4'!O21/Deflactores!$B21*100 -> 2.219048 | P21: =+'[1]1.1.1.4'!P21/Deflactores!$B21*100 -> 117.33882 | Q21: =+'[1]1.1.1.4'!Q21/Deflactores!$B21*100 -> 1.3374473 | R21: =+'[1]1.1.1.4'!R21/Deflactores!$B21*100 -> 60.94759 | S21: =+'[1]1.1.1.4'!S21/Deflactores!$B21*100 -> 0 | ... Y21: =+'[1]1.1.1.4'!Y21/Deflactores!$B21*100 -> 388.91408 | Z21: =SUM(B21:Y21) -> 5146.8855
A22: 2004 | B22: =+'[1]1.1.1.4'!B22/Deflactores!$B22*100 -> 476.84349 | C22: =+'[1]1.1.1.4'!C22/Deflactores!$B22*100 -> 1858.0912 | D22: =+'[1]1.1.1.4'!D22/Deflactores!$B22*100 -> 25.888372 | E22: =+'[1]1.1.1.4'!E22/Deflactores!$B22*100 -> 1310.1596 | F22: =+'[1]1.1.1.4'!F22/Deflactores!$B22*100 -> 111.05347 | G22: =+'[1]1.1.1.4'!G22/Deflactores!$B22*100 -> 1.1009004 | H22: =+'[1]1.1.1.4'!H22/Deflactores!$B22*100 -> 95.002436 | I22: =+'[1]1.1.1.4'!I22/Deflactores!$B22*100 -> 0 | J22: =+'[1]1.1.1.4'!J22/Deflactores!$B22*100 -> 8.3005844 | L22: =+'[1]1.1.1.4'!L22/Deflactores!$B22*100 -> 341.05663 | M22: =+'[1]1.1.1.4'!M22/Deflactores!$B22*100 -> 35.497487 | N22: =+'[1]1.1.1.4'!N22/Deflactores!$B22*100 -> 484.84422 | O22: =+'[1]1.1.1.4'!O22/Deflactores!$B22*100 -> 1.3238541 | P22: =+'[1]1.1.1.4'!P22/Deflactores!$B22*100 -> 133.57227 | Q22: =+'[1]1.1.1.4'!Q22/Deflactores!$B22*100 -> 1.3953273 | R22: =+'[1]1.1.1.4'!R22/Deflactores!$B22*100 -> 49.954332 | S22: =+'[1]1.1.1.4'!S22/Deflactores!$B22*100 -> 0 | ... Y22: =+'[1]1.1.1.4'!Y22/Deflactores!$B22*100 -> 506.71288 | Z22: =SUM(B22:Y22) -> 5814.0476
A23: 2005 | B23: =+'[1]1.1.1.4'!B23/Deflactores!$B23*100 -> 382.49847 | C23: =+'[1]1.1.1.4'!C23/Deflactores!$B23*100 -> 1536.5995 | D23: =+'[1]1.1.1.4'!D23/Deflactores!$B23*100 -> 19.683726 | E23: =+'[1]1.1.1.4'!E23/Deflactores!$B23*100 -> 136.96974 | F23: =+'[1]1.1.1.4'!F23/Deflactores!$B23*100 -> 87.965605 | G23: =+'[1]1.1.1.4'!G23/Deflactores!$B23*100 -> 3.0701223 | H23: =+'[1]1.1.1.4'!H23/Deflactores!$B23*100 -> 125.44523 | I23: =+'[1]1.1.1.4'!I23/Deflactores!$B23*100 -> 43.565821 | J23: =+'[1]1.1.1.4'!J23/Deflactores!$B23*100 -> 0 | L23: =+'[1]1.1.1.4'!L23/Deflactores!$B23*100 -> 438.60716 | M23: =+'[1]1.1.1.4'!M23/Deflactores!$B23*100 -> 284.89239 | N23: =+'[1]1.1.1.4'!N23/Deflactores!$B23*100 -> 587.11583 | O23: =+'[1]1.1.1.4'!O23/Deflactores!$B23*100 -> 0 | P23: =+'[1]1.1.1.4'!P23/Deflactores!$B23*100 -> 155.82912 | Q23: =+'[1]1.1.1.4'!Q23/Deflactores!$B23*100 -> 1.106564 | R23: =+'[1]1.1.1.4'!R23/Deflactores!$B23*100 -> 80.967655 | S23: =+'[1]1.1.1.4'!S23/Deflactores!$B23*100 -> 45.421693 | ... Y23: =+'[1]1.1.1.4'!Y23/Deflactores!$B23*100 -> 230.53908 | Z23: =SUM(B23:Y23) -> 4893.9887
A24: 2006 | B24: =+'[1]1.1.1.4'!B24/Deflactores!$B24*100 -> 379.81356 | C24: =+'[1]1.1.1.4'!C24/Deflactores!$B24*100 -> 1266.1046 | D24: =+'[1]1.1.1.4'!D24/Deflactores!$B24*100 -> 20.759151 | E24: =+'[1]1.1.1.4'!E24/Deflactores!$B24*100 -> 178.73079 | F24: =+'[1]1.1.1.4'!F24/Deflactores!$B24*100 -> 72.496421 | G24: =+'[1]1.1.1.4'!G24/Deflactores!$B24*100 -> 0.31260742 | H24: =+'[1]1.1.1.4'!H24/Deflactores!$B24*100 -> 125.79078 | I24: =+'[1]1.1.1.4'!I24/Deflactores!$B24*100 -> 243.75363 | J24: =+'[1]1.1.1.4'!J24/Deflactores!$B24*100 -> 28.521044 | L24: =+'[1]1.1.1.4'!L24/Deflactores!$B24*100 -> 272.99287 | M24: =+'[1]1.1.1.4'!M24/Deflactores!$B24*100 -> 325.49771 | N24: =+'[1]1.1.1.4'!N24/Deflactores!$B24*100 -> 613.10766 | O24: =+'[1]1.1.1.4'!O24/Deflactores!$B24*100 -> 0 | P24: =+'[1]1.1.1.4'!P24/Deflactores!$B24*100 -> 145.07685 | Q24: =+'[1]1.1.1.4'!Q24/Deflactores!$B24*100 -> 25.06497 | R24: =+'[1]1.1.1.4'!R24/Deflactores!$B24*100 -> 31.975278 | S24: =+'[1]1.1.1.4'!S24/Deflactores!$B24*100 -> 52.799099 | ... Y24: =+'[1]1.1.1.4'!Y24/Deflactores!$B24*100 -> 312.48507 | Z24: =SUM(B24:Y24) -> 4692.9664
A25: 2007 | B25: =+'[1]1.1.1.4'!B25/Deflactores!$B25*100 -> 395.25713 | C25: =+'[1]1.1.1.4'!C25/Deflactores!$B25*100 -> 1515.6694 | D25: =+'[1]1.1.1.4'!D25/Deflactores!$B25*100 -> 28.460937 | E25: =+'[1]1.1.1.4'!E25/Deflactores!$B25*100 -> 335.20129 | F25: =+'[1]1.1.1.4'!F25/Deflactores!$B25*100 -> 83.181812 | G25: =+'[1]1.1.1.4'!G25/Deflactores!$B25*100 -> 69.617864 | H25: =+'[1]1.1.1.4'!H25/Deflactores!$B25*100 -> 131.64702 | I25: =+'[1]1.1.1.4'!I25/Deflactores!$B25*100 -> 249.38684 | J25: =+'[1]1.1.1.4'!J25/Deflactores!$B25*100 -> 36.825719 | L25: =+'[1]1.1.1.4'!L25/Deflactores!$B25*100 -> 640.51581 | M25: =+'[1]1.1.1.4'!M25/Deflactores!$B25*100 -> 328.05537 | N25: =+'[1]1.1.1.4'!N25/Deflactores!$B25*100 -> 626.44072 | O25: =+'[1]1.1.1.4'!O25/Deflactores!$B25*100 -> 0 | P25: =+'[1]1.1.1.4'!P25/Deflactores!$B25*100 -> 121.69602 | Q25: =+'[1]1.1.1.4'!Q25/Deflactores!$B25*100 -> 24.272738 | R25: =+'[1]1.1.1.4'!R25/Deflactores!$B25*100 -> 34.01811 | S25: =+'[1]1.1.1.4'!S25/Deflactores!$B25*100 -> 64.802565 | ... Y25: =+'[1]1.1.1.4'!Y25/Deflactores!$B25*100 -> 138.21344 | Z25: =SUM(B25:Y25) -> 5825.8313
A26: 2008 | B26: =+'[1]1.1.1.4'!B26/Deflactores!$B26*100 -> 361.02693 | C26: =+'[1]1.1.1.4'!C26/Deflactores!$B26*100 -> 1498.7776 | D26: =+'[1]1.1.1.4'!D26/Deflactores!$B26*100 -> 34.915711 | E26: =+'[1]1.1.1.4'!E26/Deflactores!$B26*100 -> 183.69468 | F26: =+'[1]1.1.1.4'!F26/Deflactores!$B26*100 -> 120.95049 | G26: =+'[1]1.1.1.4'!G26/Deflactores!$B26*100 -> 15.183765 | H26: =+'[1]1.1.1.4'!H26/Deflactores!$B26*100 -> 146.67641 | I26: =+'[1]1.1.1.4'!I26/Deflactores!$B26*100 -> 275.00811 | ... Y26: =+'[1]1.1.1.4'!Y26/Deflactores!$B26*100 -> 111.7723 | Z26: =SUM(B26:Y26) -> 7250.7847
A27: 2009 | B27: =+'[1]1.1.1.4'!B27/Deflactores!$B27*100 -> 414.37858 | C27: =+'[1]1.1.1.4'!C27/Deflactores!$B27*100 -> 2146.356 | D27: =+'[1]1.1.1.4'!D27/Deflactores!$B27*100 -> 24.556112 | E27: =+'[1]1.1.1.4'!E27/Deflactores!$B27*100 -> 477.20243 | F27: =+'[1]1.1.1.4'!F27/Deflactores!$B27*100 -> 135.15424 | G27: =+'[1]1.1.1.4'!G27/Deflactores!$B27*100 -> 1.4346519 | H27: =+'[1]1.1.1.4'!H27/Deflactores!$B27*100 -> 218.63575 | I27: =+'[1]1.1.1.4'!I27/Deflactores!$B27*100 -> 307.98013 | ... Y27: =+'[1]1.1.1.4'!Y27/Deflactores!$B27*100 -> 133.17214 | Z27: =SUM(B27:Y27) -> 8675.7654
A28: 2010 | B28: =+'[1]1.1.1.4'!B28/Deflactores!$B28*100 -> 538.95678 | C28: =+'[1]1.1.1.4'!C28/Deflactores!$B28*100 -> 2642.2214 | D28: =+'[1]1.1.1.4'!D28/Deflactores!$B28*100 -> 24.465801 | E28: =+'[1]1.1.1.4'!E28/Deflactores!$B28*100 -> 340.32965 | F28: =+'[1]1.1.1.4'!F28/Deflactores!$B28*100 -> 112.66088 | G28: =+'[1]1.1.1.4'!G28/Deflactores!$B28*100 -> 27.087684 | H28: =+'[1]1.1.1.4'!H28/Deflactores!$B28*100 -> 178.76944 | I28: =+'[1]1.1.1.4'!I28/Deflactores!$B28*100 -> 368.28713 | ... Y28: =+'[1]1.1.1.4'!Y28/Deflactores!$B28*100 -> 121.18491 | Z28: =SUM(B28:Y28) -> 8584.7113
A29: 2011 | B29: =+'[1]1.1.1.4'!B29/Deflactores!$B29*100 -> 579.4611 | C29: =+'[1]1.1.1.4'!C29/Deflactores!$B29*100 -> 1400.9913 | D29: =+'[1]1.1.1.4'!D29/Deflactores!$B29*100 -> 27.112466 | E29: =+'[1]1.1.1.4'!E29/Deflactores!$B29*100 -> 408.03881 | F29: =+'[1]1.1.1.4'!F29/Deflactores!$B29*100 -> 164.8955 | G29: =+'[1]1.1.1.4'!G29/Deflactores!$B29*100 -> 1.5430062 | H29: =+'[1]1.1.1.4'!H29/Deflactores!$B29*100 -> 165.996 | I29: =+'[1]1.1.1.4'!I29/Deflactores!$B29*100 -> 417.51293 | ... Y29: =+'[1]1.1.1.4'!Y29/Deflactores!$B29*100 -> 140.66533 | Z29: =SUM(B29:Y29) -> 7906.3645
A30: 2012 | B30: =+'[1]1.1.1.4'!B30/Deflactores!$B30*100 -> 635.4388 | C30: =+'[1]1.1.1.4'!C30/Deflactores!$B30*100 -> 1367.7645 | D30: =+'[1]1.1.1.4'!D30/Deflactores!$B30*100 -> 24.580321 | E30: =+'[1]1.1.1.4'!E30/Deflactores!$B30*100 -> 476.85787 | F30: =+'[1]1.1.1.4'!F30/Deflactores!$B30*100 -> 173.86704 | G30: =+'[1]1.1.1.4'!G30/Deflactores!$B30*100 -> 11.851161 | H30: =+'[1]1.1.1.4'!H30/Deflactores!$B30*100 -> 170.53281 | I30: =+'[1]1.1.1.4'!I30/Deflactores!$B30*100 -> 283.53218 | ... Y30: =+'[1]1.1.1.4'!Y30/Deflactores!$B30*100 -> 106.982 | Z30: =SUM(B30:Y30) -> 7907.201
A31: 2013 | B31: =+'[1]1.1.1.4'!B31/Deflactores!$B31*100 -> 576.81995 | C31: =+'[1]1.1.1.4'!C31/Deflactores!$B31*100 -> 1327.1017 | D31: =+'[1]1.1.1.4'!D31/Deflactores!$B31*100 -> 25.794938 | E31: =+'[1]1.1.1.4'!E31/Deflactores!$B31*100 -> 244.38049 | F31: =+'[1]1.1.1.4'!F31/Deflactores!$B31*100 -> 152.97187 | G31: =+'[1]1.1.1.4'!G31/Deflactores!$B31*100 -> 5.2037596 | H31: =+'[1]1.1.1.4'!H31/Deflactores!$B31*100 -> 146.59256 | I31: =+'[1]1.1.1.4'!I31/Deflactores!$B31*100 -> 349.05761 | ... Y31: =+'[1]1.1.1.4'!Y31/Deflactores!$B31*100 -> 103.22625 | Z31: =SUM(B31:Y31) -> 7068.6038
A32: 2014 | B32: =+'[1]1.1.1.4'!B32/Deflactores!$B32*100 -> 720.10307 | C32: =+'[1]1.1.1.4'!C32/Deflactores!$B32*100 -> 1228.0806 | D32: =+'[1]1.1.1.4'!D32/Deflactores!$B32*100 -> 19.69259 | E32: =+'[1]1.1.1.4'!E32/Deflactores!$B32*100 -> 225.22521 | F32: =+'[1]1.1.1.4'!F32/Deflactores!$B32*100 -> 153.88606 | G32: =+'[1]1.1.1.4'!G32/Deflactores!$B32*100 -> 4.9325476 | H32: =+'[1]1.1.1.4'!H32/Deflactores!$B32*100 -> 130.42842 | I32: =+'[1]1.1.1.4'!I32/Deflactores!$B32*100 -> 379.31808 | ... Y32: =+'[1]1.1.1.4'!Y32/Deflactores!$B32*100 -> 124.79146 | Z32: =SUM(B32:Y32) -> 7446.3108
A33: 2015 | B33: =+'[1]1.1.1.4'!B33/Deflactores!$B33*100 -> 723.20302 | C33: =+'[1]1.1.1.4'!C33/Deflactores!$B33*100 -> 4165.9613 | D33: =+'[1]1.1.1.4'!D33/Deflactores!$B33*100 -> 13.086678 | E33: =+'[1]1.1.1.4'!E33/Deflactores!$B33*100 -> 204.81375 | F33: =+'[1]1.1.1.4'!F33/Deflactores!$B33*100 -> 138.50997 | G33: =+'[1]1.1.1.4'!G33/Deflactores!$B33*100 -> 19.594162 | H33: =+'[1]1.1.1.4'!H33/Deflactores!$B33*100 -> 143.23482 | I33: =+'[1]1.1.1.4'!I33/Deflactores!$B33*100 -> 342.19294 | ... Y33: =+'[1]1.1.1.4'!Y33/Deflactores!$B33*100 -> 133.4547 | Z33: =SUM(B33:Y33) -> 10092.549
A34: 2016 | B34: =+'[1]1.1.1.4'!B34/Deflactores!$B34*100 -> 682.69814 | C34: =+'[1]1.1.1.4'!C34/Deflactores!$B34*100 -> 1273.3115 | D34: =+'[1]1.1.1.4'!D34/Deflactores!$B34*100 -> 15.326354 | E34: =+'[1]1.1.1.4'!E34/Deflactores!$B34*100 -> 249.73764 | F34: =+'[1]1.1.1.4'!F34/Deflactores!$B34*100 -> 167.29596 | G34: =+'[1]1.1.1.4'!G34/Deflactores!$B34*100 -> 2.068108 | H34: =+'[1]1.1.1.4'!H34/Deflactores!$B34*100 -> 172.95304 | I34: =+'[1]1.1.1.4'!I34/Deflactores!$B34*100 -> 307.49271 | ... Y34: =+'[1]1.1.1.4'!Y34/Deflactores!$B34*100 -> 100.86023 | Z34: =SUM(B34:Y34) -> 7177.623
A35: 2017 | B35: =+'[1]1.1.1.4'!B35/Deflactores!$B35*100 -> 1118.031 | C35: =+'[1]1.1.1.4'!C35/Deflactores!$B35*100 -> 1371.8371 | D35: =+'[1]1.1.1.4'!D35/Deflactores!$B35*100 -> 11.589362 | E35: =+'[1]1.1.1.4'!E35/Deflactores!$B35*100 -> 239.07459 | F35: =+'[1]1.1.1.4'!F35/Deflactores!$B35*100 -> 186.49861 | G35: =+'[1]1.1.1.4'!G35/Deflactores!$B35*100 -> 11.159128 | H35: =+'[1]1.1.1.4'!H35/Deflactores!$B35*100 -> 181.12271 | I35: =+'[1]1.1.1.4'!I35/Deflactores!$B35*100 -> 439.52633 | ... Y35: =+'[1]1.1.1.4'!Y35/Deflactores!$B35*100 -> 115.61979 | Z35: =SUM(B35:Y35) -> 8796.799
A36: 2018 | B36: =+'[1]1.1.1.4'!B36/Deflactores!$B36*100 -> 1444.0229 | C36: =+'[1]1.1.1.4'!C36/Deflactores!$B36*100 -> 1215.4927 | D36: =+'[1]1.1.1.4'!D36/Deflactores!$B36*100 -> 15.716717 | E36: =+'[1]1.1.1.4'!E36/Deflactores!$B36*100 -> 215.08814 | F36: =+'[1]1.1.1.4'!F36/Deflactores!$B36*100 -> 155.28859 | G36: =+'[1]1.1.1.4'!G36/Deflactores!$B36*100 -> 37.552867 | H36: =+'[1]1.1.1.4'!H36/Deflactores!$B36*100 -> 197.87539 | I36: =+'[1]1.1.1.4'!I36/Deflactores!$B36*100 -> 280.88048 | ... Y36: =+'[1]1.1.1.4'!Y36/Deflactores!$B36*100 -> 134.72477 | Z36: =SUM(B36:Y36) -> 8369.1998
A37: 2019 | B37: =+'[1]1.1.1.4'!B37/Deflactores!$B37*100 -> 1351.3744 | C37: =+'[1]1.1.1.4'!C37/Deflactores!$B37*100 -> 912.088 | D37: =+'[1]1.1.1.4'!D37/Deflactores!$B37*100 -> 22.552471 | E37: =+'[1]1.1.1.4'!E37/Deflactores!$B37*100 -> 200.15898 | F37: =+'[1]1.1.1.4'!F37/Deflactores!$B37*100 -> 156.88614 | G37: =+'[1]1.1.1.4'!G37/Deflactores!$B37*100 -> 26.328283 | H37: =+'[1]1.1.1.4'!H37/Deflactores!$B37*100 -> 149.3306 | I37: =+'[1]1.1.1.4'!I37/Deflactores!$B37*100 -> 222.72326 | ... Y37: =+'[1]1.1.1.4'!Y37/Deflactores!$B37*100 -> 95.720396 | Z37: =SUM(B37:Y37) -> 7539.9013
... A48: 2030 | B48: =+'[1]1.1.1.4'!B48/Deflactores!$B48*100 -> #N/A | C48: =+'[1]1.1.1.4'!C48/Deflactores!$B48*100 -> #N/A | D48: =+'[1]1.1.1.4'!D48/Deflactores!$B48*100 -> #N/A | E48: =+'[1]1.1.1.4'!E48/Deflactores!$B48*100 -> #N/A | F48: =+'[1]1.1.1.4'!F48/Deflactores!$B48*100 -> #N/A | G48: =+'[1]1.1.1.4'!G48/Deflactores!$B48*100 -> #N/A | H48: =+'[1]1.1.1.4'!H48/Deflactores!$B48*100 -> #N/A | I48: =+'[1]1.1.1.4'!I48/Deflactores!$B48*100 -> #N/A | ... Y48: =+'[1]1.1.1.4'!Y48/Deflactores!$B48*100 -> #N/A | Z48: =SUM(B48:Y48) -> #N/A

Sheet 1.1.1.5
A2: Título | B2: Rentas de la propiedad por provincia | N2: =B2 -> Rentas de la propiedad por provincia
A3: Fuente | B3: Dirección Nacional de Asuntos Provinciales - Ministerio de Economía de la Nación | N3: =B3 -> Dirección Nacional de Asuntos Provinciales - Ministerio de Economía de la Nación
A5: VOLVER AL ÍNDICE | B5: Administración Pública No Financiera | N5: =B5 -> Administración Pública No Financiera
A7: Unidad de medida | B7: Millones de pesos constantes de 2016 | C7: Millones de pesos constantes de 2016 | D7: Millones de pesos constantes de 2016 | E7: Millones de pesos constantes de 2016 | F7: Millones de pesos constantes de 2016 | G7: Millones de pesos constantes de 2016 | H7: Millones de pesos constantes de 2016 | I7: Millones de pesos constantes de 2016 | J7: Millones de pesos constantes de 2016 | K7: Millones de pesos constantes de 2016 | L7: Millones de pesos constantes de 2016 | M7: Millones de pesos constantes de 2016 | N7: Millones de pesos constantes de 2016 | O7: Millones de pesos constantes de 2016 | P7: Millones de pesos constantes de 2016 | Q7: Millones de pesos constantes de 2016 | R7: Millones de pesos constantes de 2016 | S7: Millones de pesos constantes de 2016 | T7: Millones de pesos constantes de 2016 | U7: Millones de pesos constantes de 2016 | V7: Millones de pesos constantes de 2016 | W7: Millones de pesos constantes de 2016 | X7: Millones de pesos constantes de 2016 | Y7: Millones de pesos constantes de 2016 | Z7: Millones de pesos constantes de 2016
A8: CÓDIGO | B8: 1.1.1.5.1 | C8: 1.1.1.5.2 | D8: 1.1.1.5.3 | E8: 1.1.1.5.4 | F8: 1.1.1.5.5 | G8: 1.1.1.5.6 | H8: 1.1.1.5.7 | I8: 1.1.1.5.8 | J8: 1.1.1.5.9 | K8: 1.1.1.5.10 | L8: 1.1.1.5.11 | M8: 1.1.1.5.12 | N8: 1.1.1.5.13 | O8: 1.1.1.5.14 | P8: 1.1.1.5.15 | Q8: 1.1.1.5.16 | R8: 1.1.1.5.17 | S8: 1.1.1.5.18 | T8: 1.1.1.5.19 | U8: 1.1.1.5.20 | V8: 1.1.1.5.21 | W8: 1.1.1.5.22 | X8: 1.1.1.5.23 | Y8: 1.1.1.5.24 | Z8: 1.1.1.5.25
A9: Jurisdicción | B9: C.A.B.A. | C9: Buenos Aires | D9: Catamarca | E9: Córdoba | F9: Corrientes | G9: Chaco | H9: Chubut | I9: Entre Ríos | J9: Formosa | K9: Jujuy | L9: La Pampa | M9: La Rioja | N9: Mendoza | O9: Misiones | P9: Neuquén | Q9: Río Negro | R9: Salta | S9: San Juan | T9: San Luis | U9: Santa Cruz | V9: Santa Fe | W9: Santiago del Estero | X9: Tucumán | Y9: Tierra del Fuego | Z9: Total
A10: 1992
A11: 1993
A12: 1994
A13: 1995
A14: 1996 | B14: =+'[1]1.1.1.5'!B14/Deflactores!$B14*100 -> 25.679288 | C14: =+'[1]1.1.1.5'!C14/Deflactores!$B14*100 -> 661.02931 | E14: =+'[1]1.1.1.5'!E14/Deflactores!$B14*100 -> 168.98997 | H14: =+'[1]1.1.1.5'!H14/Deflactores!$B14*100 -> 93.111923 | I14: =+'[1]1.1.1.5'!I14/Deflactores!$B14*100 -> 21.791457 | N14: =+'[1]1.1.1.5'!N14/Deflactores!$B14*100 -> 199.73324 | O14: =+'[1]1.1.1.5'!O14/Deflactores!$B14*100 -> 0.36291336 | P14: =+'[1]1.1.1.5'!P14/Deflactores!$B14*100 -> 118.79121 | R14: =+'[1]1.1.1.5'!R14/Deflactores!$B14*100 -> 7.1712516 | T14: =+'[1]1.1.1.5'!T14/Deflactores!$B14*100 -> 433.50134 | U14: =+'[1]1.1.1.5'!U14/Deflactores!$B14*100 -> 246.93555 | V14: =+'[1]1.1.1.5'!V14/Deflactores!$B14*100 -> 0.3920502 | X14: =+'[1]1.1.1.5'!X14/Deflactores!$B14*100 -> 1.0127964 | Z14: =SUM(B14:Y14) -> 1978.5023
A15: 1997 | B15: =+'[1]1.1.1.5'!B15/Deflactores!$B15*100 -> 38.267269 | C15: =+'[1]1.1.1.5'!C15/Deflactores!$B15*100 -> 1246.0073 | D15: =+'[1]1.1.1.5'!D15/Deflactores!$B15*100 -> 21.206009 | E15: =+'[1]1.1.1.5'!E15/Deflactores!$B15*100 -> 255.81847 | F15: =+'[1]1.1.1.5'!F15/Deflactores!$B15*100 -> 8.9834229 | G15: =+'[1]1.1.1.5'!G15/Deflactores!$B15*100 -> 62.388984 | H15: =+'[1]1.1.1.5'!H15/Deflactores!$B15*100 -> 107.45863 | I15: =+'[1]1.1.1.5'!I15/Deflactores!$B15*100 -> 179.67217 | ... K15: =+'[1]1.1.1.5'!K15/Deflactores!$B15*100 -> 5.3319118 | N15: =+'[1]1.1.1.5'!N15/Deflactores!$B15*100 -> 142.87347 | O15: =+'[1]1.1.1.5'!O15/Deflactores!$B15*100 -> 1.6238691 | P15: =+'[1]1.1.1.5'!P15/Deflactores!$B15*100 -> 36.342934 | R15: =+'[1]1.1.1.5'!R15/Deflactores!$B15*100 -> 72.644005 | T15: =+'[1]1.1.1.5'!T15/Deflactores!$B15*100 -> 340.59347 | U15: =+'[1]1.1.1.5'!U15/Deflactores!$B15*100 -> 558.09107 | V15: =+'[1]1.1.1.5'!V15/Deflactores!$B15*100 -> 233.08092 | X15: =+'[1]1.1.1.5'!X15/Deflactores!$B15*100 -> 4.0512327 | Z15: =SUM(B15:Y15) -> 3314.664
A16: 1998 | B16: =+'[1]1.1.1.5'!B16/Deflactores!$B16*100 -> 0 | C16: =+'[1]1.1.1.5'!C16/Deflactores!$B16*100 -> 1160.7463 | D16: =+'[1]1.1.1.5'!D16/Deflactores!$B16*100 -> 7.756988 | E16: =+'[1]1.1.1.5'!E16/Deflactores!$B16*100 -> 299.58487 | F16: =+'[1]1.1.1.5'!F16/Deflactores!$B16*100 -> 0.57762425 | G16: =+'[1]1.1.1.5'!G16/Deflactores!$B16*100 -> 173.71548 | H16: =+'[1]1.1.1.5'!H16/Deflactores!$B16*100 -> 206.58595 | I16: =+'[1]1.1.1.5'!I16/Deflactores!$B16*100 -> 78.152633 | ... K16: =+'[1]1.1.1.5'!K16/Deflactores!$B16*100 -> 0 | M16: =+'[1]1.1.1.5'!M16/Deflactores!$B16*100 -> 4.3575568 | N16: =+'[1]1.1.1.5'!N16/Deflactores!$B16*100 -> 578.43548 | O16: =+'[1]1.1.1.5'!O16/Deflactores!$B16*100 -> 2.76826 | P16: =+'[1]1.1.1.5'!P16/Deflactores!$B16*100 -> 122.74571 | R16: =+'[1]1.1.1.5'!R16/Deflactores!$B16*100 -> 82.844394 | S16: =+'[1]1.1.1.5'!S16/Deflactores!$B16*100 -> 80.225342 | T16: =+'[1]1.1.1.5'!T16/Deflactores!$B16*100 -> 543.92664 | U16: =+'[1]1.1.1.5'!U16/Deflactores!$B16*100 -> 996.11326 | V16: =+'[1]1.1.1.5'!V16/Deflactores!$B16*100 -> 173.17199 | X16: =+'[1]1.1.1.5'!X16/Deflactores!$B16*100 -> 0 | Z16: =SUM(B16:Y16) -> 4511.7863
A17: 1999 | B17: =+'[1]1.1.1.5'!B17/Deflactores!$B17*100 -> 0 | C17: =+'[1]1.1.1.5'!C17/Deflactores!$B17*100 -> 150.28235 | D17: =+'[1]1.1.1.5'!D17/Deflactores!$B17*100 -> 2.9909217 | E17: =+'[1]1.1.1.5'!E17/Deflactores!$B17*100 -> 235.36805 | F17: =+'[1]1.1.1.5'!F17/Deflactores!$B17*100 -> 4.2224006 | G17: =+'[1]1.1.1.5'!G17/Deflactores!$B17*100 -> 129.50639 | H17: =+'[1]1.1.1.5'!H17/Deflactores!$B17*100 -> 68.317009 | I17: =+'[1]1.1.1.5'!I17/Deflactores!$B17*100 -> 53.469944 | ... P17: =+'[1]1.1.1.5'!P17/Deflactores!$B17*100 -> 33.677106 | R17: =+'[1]1.1.1.5'!R17/Deflactores!$B17*100 -> 14.69824 | S17: =+'[1]1.1.1.5'!S17/Deflactores!$B17*100 -> 23.063231 | T17: =+'[1]1.1.1.5'!T17/Deflactores!$B17*100 -> 645.26773 | U17: =+'[1]1.1.1.5'!U17/Deflactores!$B17*100 -> 2229.8726 | V17: =+'[1]1.1.1.5'!V17/Deflactores!$B17*100 -> 82.061643 | W17: =+'[1]1.1.1.5'!W17/Deflactores!$B17*100 -> 5.3249914 | X17: =+'[1]1.1.1.5'!X17/Deflactores!$B17*100 -> 4.6107773 | Y17: =+'[1]1.1.1.5'!Y17/Deflactores!$B17*100 -> 32.491255 | Z17: =SUM(B17:Y17) -> 4391.5061
A18: 2000 | B18: =+'[1]1.1.1.5'!B18/Deflactores!$B18*100 -> 0 | C18: =+'[1]1.1.1.5'!C18/Deflactores!$B18*100 -> 323.23276 | D18: =+'[1]1.1.1.5'!D18/Deflactores!$B18*100 -> 0.62627214 | E18: =+'[1]1.1.1.5'!E18/Deflactores!$B18*100 -> 156.97814 | F18: =+'[1]1.1.1.5'!F18/Deflactores!$B18*100 -> 25.728346 | G18: =+'[1]1.1.1.5'!G18/Deflactores!$B18*100 -> 158.13599 | H18: =+'[1]1.1.1.5'!H18/Deflactores!$B18*100 -> 106.27183 | I18: =+'[1]1.1.1.5'!I18/Deflactores!$B18*100 -> 0 | ... P18: =+'[1]1.1.1.5'!P18/Deflactores!$B18*100 -> 36.022976 | R18: =+'[1]1.1.1.5'!R18/Deflactores!$B18*100 -> 72.58156 | S18: =+'[1]1.1.1.5'!S18/Deflactores!$B18*100 -> 0 | T18: =+'[1]1.1.1.5'!T18/Deflactores!$B18*100 -> 833.08482 | U18: =+'[1]1.1.1.5'!U18/Deflactores!$B18*100 -> 2234.5503 | V18: =+'[1]1.1.1.5'!V18/Deflactores!$B18*100 -> 169.59233 | W18: =+'[1]1.1.1.5'!W18/Deflactores!$B18*100 -> 228.80774 | X18: =+'[1]1.1.1.5'!X18/Deflactores!$B18*100 -> 0 | Y18: =+'[1]1.1.1.5'!Y18/Deflactores!$B18*100 -> 54.629974 | Z18: =SUM(B18:Y18) -> 4590.2139
A19: 2001 | B19: =+'[1]1.1.1.5'!B19/Deflactores!$B19*100 -> 269.96636 | C19: =+'[1]1.1.1.5'!C19/Deflactores!$B19*100 -> 221.94465 | D19: =+'[1]1.1.1.5'!D19/Deflactores!$B19*100 -> 21.651563 | E19: =+'[1]1.1.1.5'!E19/Deflactores!$B19*100 -> 72.263848 | F19: =+'[1]1.1.1.5'!F19/Deflactores!$B19*100 -> 10.824286 | G19: =+'[1]1.1.1.5'!G19/Deflactores!$B19*100 -> 100.11505 | H19: =+'[1]1.1.1.5'!H19/Deflactores!$B19*100 -> 169.57597 | I19: =+'[1]1.1.1.5'!I19/Deflactores!$B19*100 -> 56.591794 | ... P19: =+'[1]1.1.1.5'!P19/Deflactores!$B19*100 -> 39.249316 | R19: =+'[1]1.1.1.5'!R19/Deflactores!$B19*100 -> 9.0674607 | S19: =+'[1]1.1.1.5'!S19/Deflactores!$B19*100 -> 3.7860944 | T19: =+'[1]1.1.1.5'!T19/Deflactores!$B19*100 -> 1197.721 | U19: =+'[1]1.1.1.5'!U19/Deflactores!$B19*100 -> 1993.7709 | V19: =+'[1]1.1.1.5'!V19/Deflactores!$B19*100 -> 537.34307 | W19: =+'[1]1.1.1.5'!W19/Deflactores!$B19*100 -> 322.02407 | X19: =+'[1]1.1.1.5'!X19/Deflactores!$B19*100 -> 0 | Y19: =+'[1]1.1.1.5'!Y19/Deflactores!$B19*100 -> 87.512715 | Z19: =SUM(B19:Y19) -> 5375.1609
A20: 2002 | B20: =+'[1]1.1.1.5'!B20/Deflactores!$B20*100 -> 0 | C20: =+'[1]1.1.1.5'!C20/Deflactores!$B20*100 -> 102.74757 | D20: =+'[1]1.1.1.5'!D20/Deflactores!$B20*100 -> 3.9192893 | E20: =+'[1]1.1.1.5'!E20/Deflactores!$B20*100 -> 19.582845 | F20: =+'[1]1.1.1.5'!F20/Deflactores!$B20*100 -> 0 | G20: =+'[1]1.1.1.5'!G20/Deflactores!$B20*100 -> 71.068242 | H20: =+'[1]1.1.1.5'!H20/Deflactores!$B20*100 -> 240.37773 | I20: =+'[1]1.1.1.5'!I20/Deflactores!$B20*100 -> 8.9995346 | ... P20: =+'[1]1.1.1.5'!P20/Deflactores!$B20*100 -> 123.25575 | R20: =+'[1]1.1.1.5'!R20/Deflactores!$B20*100 -> 3.597721 | S20: =+'[1]1.1.1.5'!S20/Deflactores!$B20*100 -> 0 | T20: =+'[1]1.1.1.5'!T20/Deflactores!$B20*100 -> 804.87842 | U20: =+'[1]1.1.1.5'!U20/Deflactores!$B20*100 -> 1480.5394 | V20: =+'[1]1.1.1.5'!V20/Deflactores!$B20*100 -> 463.21926 | W20: =+'[1]1.1.1.5'!W20/Deflactores!$B20*100 -> 98.608615 | X20: =+'[1]1.1.1.5'!X20/Deflactores!$B20*100 -> 0 | Y20: =+'[1]1.1.1.5'!Y20/Deflactores!$B20*100 -> 6.0754764 | Z20: =SUM(B20:Y20) -> 3914.0635
A21: 2003 | B21: =+'[1]1.1.1.5'!B21/Deflactores!$B21*100 -> 154.26563 | C21: =+'[1]1.1.1.5'!C21/Deflactores!$B21*100 -> 597.3033 | D21: =+'[1]1.1.1.5'!D21/Deflactores!$B21*100 -> 30.186637 | E21: =+'[1]1.1.1.5'!E21/Deflactores!$B21*100 -> 17.904786 | F21: =+'[1]1.1.1.5'!F21/Deflactores!$B21*100 -> 2.6119554 | G21: =+'[1]1.1.1.5'!G21/Deflactores!$B21*100 -> 70.935977 | H21: =+'[1]1.1.1.5'!H21/Deflactores!$B21*100 -> 107.2955 | I21: =+'[1]1.1.1.5'!I21/Deflactores!$B21*100 -> 0 | ... P21: =+'[1]1.1.1.5'!P21/Deflactores!$B21*100 -> 33.501194 | R21: =+'[1]1.1.1.5'!R21/Deflactores!$B21*100 -> 6.8323495 | S21: =+'[1]1.1.1.5'!S21/Deflactores!$B21*100 -> 0 | T21: =+'[1]1.1.1.5'!T21/Deflactores!$B21*100 -> 666.28598 | U21: =+'[1]1.1.1.5'!U21/Deflactores!$B21*100 -> 112.80723 | V21: =+'[1]1.1.1.5'!V21/Deflactores!$B21*100 -> 337.15852 | W21: =+'[1]1.1.1.5'!W21/Deflactores!$B21*100 -> 557.26382 | X21: =+'[1]1.1.1.5'!X21/Deflactores!$B21*100 -> 0 | Y21: =+'[1]1.1.1.5'!Y21/Deflactores!$B21*100 -> 7.1114043 | Z21: =SUM(B21:Y21) -> 2806.8389
A22: 2004 | B22: =+'[1]1.1.1.5'!B22/Deflactores!$B22*100 -> 153.61401 | C22: =+'[1]1.1.1.5'!C22/Deflactores!$B22*100 -> 696.78419 | D22: =+'[1]1.1.1.5'!D22/Deflactores!$B22*100 -> 64.263319 | E22: =+'[1]1.1.1.5'!E22/Deflactores!$B22*100 -> 33.569878 | F22: =+'[1]1.1.1.5'!F22/Deflactores!$B22*100 -> 0.08357349 | G22: =+'[1]1.1.1.5'!G22/Deflactores!$B22*100 -> 43.667983 | H22: =+'[1]1.1.1.5'!H22/Deflactores!$B22*100 -> 168.65279 | I22: =+'[1]1.1.1.5'!I22/Deflactores!$B22*100 -> 178.63368 | ... P22: =+'[1]1.1.1.5'!P22/Deflactores!$B22*100 -> 45.141717 | R22: =+'[1]1.1.1.5'!R22/Deflactores!$B22*100 -> 7.1280292 | S22: =+'[1]1.1.1.5'!S22/Deflactores!$B22*100 -> 0 | T22: =+'[1]1.1.1.5'!T22/Deflactores!$B22*100 -> 34.53115 | U22: =+'[1]1.1.1.5'!U22/Deflactores!$B22*100 -> 120.63289 | V22: =+'[1]1.1.1.5'!V22/Deflactores!$B22*100 -> 147.69825 | W22: =+'[1]1.1.1.5'!W22/Deflactores!$B22*100 -> 159.03317 | X22: =+'[1]1.1.1.5'!X22/Deflactores!$B22*100 -> 0 | Y22: =+'[1]1.1.1.5'!Y22/Deflactores!$B22*100 -> 13.841198 | Z22: =SUM(B22:Y22) -> 2056.056
A23: 2005 | B23: =+'[1]1.1.1.5'!B23/Deflactores!$B23*100 -> 412.1944 | C23: =+'[1]1.1.1.5'!C23/Deflactores!$B23*100 -> 298.63033 | D23: =+'[1]1.1.1.5'!D23/Deflactores!$B23*100 -> 86.715647 | E23: =+'[1]1.1.1.5'!E23/Deflactores!$B23*100 -> 51.250352 | F23: =+'[1]1.1.1.5'!F23/Deflactores!$B23*100 -> 0.024613902 | G23: =+'[1]1.1.1.5'!G23/Deflactores!$B23*100 -> 107.96899 | H23: =+'[1]1.1.1.5'!H23/Deflactores!$B23*100 -> 16.59673 | I23: =+'[1]1.1.1.5'!I23/Deflactores!$B23*100 -> 206.56739 | ... Y23: =+'[1]1.1.1.5'!Y23/Deflactores!$B23*100 -> 38.332827 | Z23: =SUM(B23:Y23) -> 3073.2057
A24: 2006 | B24: =+'[1]1.1.1.5'!B24/Deflactores!$B24*100 -> 681.64448 | C24: =+'[1]1.1.1.5'!C24/Deflactores!$B24*100 -> 506.13902 | D24: =+'[1]1.1.1.5'!D24/Deflactores!$B24*100 -> 97.24506 | E24: =+'[1]1.1.1.5'!E24/Deflactores!$B24*100 -> 1.034882 | F24: =+'[1]1.1.1.5'!F24/Deflactores!$B24*100 -> 0 | G24: =+'[1]1.1.1.5'!G24/Deflactores!$B24*100 -> 123.63579 | H24: =+'[1]1.1.1.5'!H24/Deflactores!$B24*100 -> 415.79018 | I24: =+'[1]1.1.1.5'!I24/Deflactores!$B24*100 -> 45.920337 | ... Y24: =+'[1]1.1.1.5'!Y24/Deflactores!$B24*100 -> 42.43449 | Z24: =SUM(B24:Y24) -> 4595.6403
A25: 2007 | B25: =+'[1]1.1.1.5'!B25/Deflactores!$B25*100 -> 173.75404 | C25: =+'[1]1.1.1.5'!C25/Deflactores!$B25*100 -> 1164.6247 | D25: =+'[1]1.1.1.5'!D25/Deflactores!$B25*100 -> 205.57079 | E25: =+'[1]1.1.1.5'!E25/Deflactores!$B25*100 -> 61.851109 | F25: =+'[1]1.1.1.5'!F25/Deflactores!$B25*100 -> 0 | G25: =+'[1]1.1.1.5'!G25/Deflactores!$B25*100 -> 69.72642 | H25: =+'[1]1.1.1.5'!H25/Deflactores!$B25*100 -> 36.095165 | I25: =+'[1]1.1.1.5'!I25/Deflactores!$B25*100 -> 60.521575 | ... Y25: =+'[1]1.1.1.5'!Y25/Deflactores!$B25*100 -> 11.180777 | Z25: =SUM(B25:Y25) -> 5299.5762
A26: 2008 | B26: =+'[1]1.1.1.5'!B26/Deflactores!$B26*100 -> 252.65582 | C26: =+'[1]1.1.1.5'!C26/Deflactores!$B26*100 -> 1200.2163 | D26: =+'[1]1.1.1.5'!D26/Deflactores!$B26*100 -> 135.88683 | E26: =+'[1]1.1.1.5'!E26/Deflactores!$B26*100 -> 39.323313 | F26: =+'[1]1.1.1.5'!F26/Deflactores!$B26*100 -> 0.33173475 | G26: =+'[1]1.1.1.5'!G26/Deflactores!$B26*100 -> 58.370853 | H26: =+'[1]1.1.1.5'!H26/Deflactores!$B26*100 -> 445.12678 | I26: =+'[1]1.1.1.5'!I26/Deflactores!$B26*100 -> 40.272599 | ... Y26: =+'[1]1.1.1.5'!Y26/Deflactores!$B26*100 -> 55.737656 | Z26: =SUM(B26:Y26) -> 5672.7776
A27: 2009 | B27: =+'[1]1.1.1.5'!B27/Deflactores!$B27*100 -> 63.039335 | C27: =+'[1]1.1.1.5'!C27/Deflactores!$B27*100 -> 110.17505 | D27: =+'[1]1.1.1.5'!D27/Deflactores!$B27*100 -> 1.3950097 | E27: =+'[1]1.1.1.5'!E27/Deflactores!$B27*100 -> 11.512058 | F27: =+'[1]1.1.1.5'!F27/Deflactores!$B27*100 -> 0 | G27: =+'[1]1.1.1.5'!G27/Deflactores!$B27*100 -> 109.91726 | H27: =+'[1]1.1.1.5'!H27/Deflactores!$B27*100 -> 370.84382 | I27: =+'[1]1.1.1.5'!I27/Deflactores!$B27*100 -> 17.226504 | ... Y27: =+'[1]1.1.1.5'!Y27/Deflactores!$B27*100 -> 68.620337 | Z27: =SUM(B27:Y27) -> 3212.3535
A28: 2010 | B28: =+'[1]1.1.1.5'!B28/Deflactores!$B28*100 -> 251.87531 | C28: =+'[1]1.1.1.5'!C28/Deflactores!$B28*100 -> 58.528815 | D28: =+'[1]1.1.1.5'!D28/Deflactores!$B28*100 -> 0.018910764 | E28: =+'[1]1.1.1.5'!E28/Deflactores!$B28*100 -> 260.24524 | F28: =+'[1]1.1.1.5'!F28/Deflactores!$B28*100 -> 0.28366146 | G28: =+'[1]1.1.1.5'!G28/Deflactores!$B28*100 -> 34.9973 | H28: =+'[1]1.1.1.5'!H28/Deflactores!$B28*100 -> 277.79632 | I28: =+'[1]1.1.1.5'!I28/Deflactores!$B28*100 -> 18.296164 | ... Y28: =+'[1]1.1.1.5'!Y28/Deflactores!$B28*100 -> 69.506514 | Z28: =SUM(B28:Y28) -> 2672.8786
A29: 2011 | B29: =+'[1]1.1.1.5'!B29/Deflactores!$B29*100 -> 420.3827 | C29: =+'[1]1.1.1.5'!C29/Deflactores!$B29*100 -> 1628.6727 | D29: =+'[1]1.1.1.5'!D29/Deflactores!$B29*100 -> 4.9762997 | E29: =+'[1]1.1.1.5'!E29/Deflactores!$B29*100 -> 53.901284 | F29: =+'[1]1.1.1.5'!F29/Deflactores!$B29*100 -> 12.913971 | G29: =+'[1]1.1.1.5'!G29/Deflactores!$B29*100 -> 26.089866 | H29: =+'[1]1.1.1.5'!H29/Deflactores!$B29*100 -> 257.17908 | I29: =+'[1]1.1.1.5'!I29/Deflactores!$B29*100 -> 52.198812 | ... Y29: =+'[1]1.1.1.5'!Y29/Deflactores!$B29*100 -> 68.083383 | Z29: =SUM(B29:Y29) -> 4742.6233
